Workbook

Sheet Accueil
A1: Pilotage locatif
A2: Outil de suivi d'un ou plusieurs biens en location. Version 1.2, 26/10/2026.
A5: Comment l'utiliser
A6: 1. Biens | B6: Renseignez une ligne par bien (identifiant, régime fiscal, coût d'acquisition, date de mise en location).
A7: 2. Journal | B7: Saisissez chaque mouvement : relevé de l'agence (montants bruts : loyers, honoraires, travaux) et dépenses payées depuis la banque. Le prêt ne se saisit pas ici.
A8: 3. Prêts et Échéancier | B8: Une ligne par prêt, et le tableau d'amortissement de la banque collé dans l'Échéancier.
A9: 4. Amortissements | B9: Le plan d'amortissement du comptable, et chaque nouvel équipement immobilisé.
A10: 5. Synthèse | B10: Choisissez le bien en C3 : résultat fiscal estimé, cash-flow et rentabilité par année.
A11: 6. Revente et Vendre quand | B11: Revente : détail de la somme perçue et de la plus-value pour une date. Vendre quand : comparaison de trois dates de vente (somme nette, impôt, effort de trésorerie, gain total et TRI depuis l'achat).
A12: 7. Contrôles | B12: Vérifiez que tout est « OK » ou « Écart expliqué ».
A14: Code couleur
A15: Fond jaune, texte bleu | B15: Cellule à saisir
A16: Fond gris | B16: Calcul automatique : ne pas modifier
A17: Texte noir | B17: Formule
A19: Ce qui change par rapport au fichier d'origine
A20: Un seul journal | B20: Les deux listings (dépenses, recettes) fusionnent en une table, avec bien, compte, catégorie, pièce justificative.
A21: Référentiels | B21: Biens, catégories (avec traitement fiscal LMNP) et listes déroulantes : plus de codes tapés à la main, plus de montants qui disparaissent des totaux.
A22: Multi-biens | B22: Chaque ligne est rattachée à un bien ; la synthèse se filtre par bien.
A23: Prêt | B23: Un seul échéancier pour tous les prêts (au lieu d'un onglet par prêt aux mises en page différentes) ; il fait foi pour le capital, les intérêts et l'assurance.
A24: Fiscalité LMNP réel | B24: Nouvel onglet Amortissements et calcul du résultat fiscal avec report des amortissements, absents du fichier d'origine.
A25: Synthèse | B25: Recap et Ratio Trésorerie remplacés par une synthèse unique : résultat fiscal, cash-flow, rendements, capital restant dû.
A26: Revente | B26: Simulation corrigée : capital restant dû exact, somme nette, cash-flow cumulé, amortissements à réintégrer.
A27: Nouveaux onglets | B27: Échéances (rappels annuels) et Contrôles (rapprochement avec l'agence et les comptes du comptable).
A28: Erreurs corrigées | B28: Addition capital restant dû + mensualité, intérêts décalés d'un mois, capital du prêt 1 jamais compté, formules limitées à 93 lignes, cumul fiscal faux, valeurs en dur.
A30: Données de départ
A31: Contenu | B31: Mise en location du 18/05/2024 au 25/10/2026 : grand livre de l'agence (ligne à ligne), dépenses payées depuis le compte BANQUE, assurance PNO d'après les comptes annuels, échéancier BANQUE complet, plan d'amortissement déduit des comptes 2024 et 2025.
A32: Avertissement | B32: Outil de suivi, pas un conseil fiscal. Les règles fiscales sont à confirmer avec un expert-comptable ou sur impots.gouv.fr.
A34: Nouveautés de la version 1.2
A35: Vendre quand | B35: Nouvel onglet : trois dates de vente comparées (somme nette, impôt sur la plus-value, exonération pour remploi, cash-flow d'ici la vente, gain total et TRI depuis l'achat, rendement de l'attente).
A36: Avant la location | B36: Les dépenses payées pendant l'occupation et la vacance (copropriété, taxe foncière) se saisissent dans l'onglet Vendre quand, sans fausser le résultat fiscal.
A37: Contrôles | B37: Nouveau contrôle : l'onglet Vendre quand retombe sur l'onglet Revente pour une même date et un même prix.

Sheet Synthèse
A1: Synthèse annuelle
A2: Tout est calculé à partir du Journal, de l'Échéancier et des Amortissements. Choisissez le bien en C3.
B3: Bien | C3: APPART-01 | E3: =IFERROR(INDEX(Biens!$B$5:$B$30,MATCH(Synthèse!$C$3,Biens!$A$5:$A$30,0)),0) -> Appartement exemple
B4: Données à jour au | C4: 46320 | E4: ="Régime : "&IFERROR(INDEX(Biens!$G$5:$G$30,MATCH(Synthèse!$C$3,Biens!$A$5:$A$30,0)),0) -> Régime : LMNP réel | G4: Mis en location le | H4: =IFERROR(INDEX(Biens!$O$5:$O$30,MATCH(Synthèse!$C$3,Biens!$A$5:$A$30,0)),0) -> 45430
B7: Rubrique | D7: 2024 | E7: 2025 | F7: 2026 | G7: 2027 | H7: 2028
B9: 1. Résultat fiscal estimé (LMNP réel)
B10: Loyers hors charges | D10: =IF(D$7>YEAR($C$4),"",SUMIFS(Journal!$K$5:$K$1004,Journal!$C$5:$C$1004,$C$3,Journal!$B$5:$B$1004,D$7,Journal!$E$5:$E$1004,"Loyer hors charges")) -> 7692.3 | E10: =IF(E$7>YEAR($C$4),"",SUMIFS(Journal!$K$5:$K$1004,Journal!$C$5:$C$1004,$C$3,Journal!$B$5:$B$1004,E$7,Journal!$E$5:$E$1004,"Loyer hors charges")) -> 12387.89 | F10: =IF(F$7>YEAR($C$4),"",SUMIFS(Journal!$K$5:$K$1004,Journal!$C$5:$C$1004,$C$3,Journal!$B$5:$B$1004,F$7,Journal!$E$5:$E$1004,"Loyer hors charges")) -> 10511.92 | G10: =IF(G$7>YEAR($C$4),"",SUMIFS(Journal!$K$5:$K$1004,Journal!$C$5:$C$1004,$C$3,Journal!$B$5:$B$1004,G$7,Journal!$E$5:$E$1004,"Loyer hors charges")) | H10: =IF(H$7>YEAR($C$4),"",SUMIFS(Journal!$K$5:$K$1004,Journal!$C$5:$C$1004,$C$3,Journal!$B$5:$B$1004,H$7,Journal!$E$5:$E$1004,"Loyer hors charges"))
B11: Charges refacturées au locataire | D11: =IF(D$7>YEAR($C$4),"",SUMIFS(Journal!$K$5:$K$1004,Journal!$C$5:$C$1004,$C$3,Journal!$B$5:$B$1004,D$7,Journal!$J$5:$J$1004,"Charges refacturées")) -> 674.46 | E11: =IF(E$7>YEAR($C$4),"",SUMIFS(Journal!$K$5:$K$1004,Journal!$C$5:$C$1004,$C$3,Journal!$B$5:$B$1004,E$7,Journal!$J$5:$J$1004,"Charges refacturées")) -> 1315.26 | F11: =IF(F$7>YEAR($C$4),"",SUMIFS(Journal!$K$5:$K$1004,Journal!$C$5:$C$1004,$C$3,Journal!$B$5:$B$1004,F$7,Journal!$J$5:$J$1004,"Charges refacturées")) -> 920.7 | G11: =IF(G$7>YEAR($C$4),"",SUMIFS(Journal!$K$5:$K$1004,Journal!$C$5:$C$1004,$C$3,Journal!$B$5:$B$1004,G$7,Journal!$J$5:$J$1004,"Charges refacturées")) | H11: =IF(H$7>YEAR($C$4),"",SUMIFS(Journal!$K$5:$K$1004,Journal!$C$5:$C$1004,$C$3,Journal!$B$5:$B$1004,H$7,Journal!$J$5:$J$1004,"Charges refacturées"))
B12: Autres recettes | D12: =IF(D$7>YEAR($C$4),"",SUMIFS(Journal!$K$5:$K$1004,Journal!$C$5:$C$1004,$C$3,Journal!$B$5:$B$1004,D$7,Journal!$J$5:$J$1004,"Autres recettes")) -> 0 | E12: =IF(E$7>YEAR($C$4),"",SUMIFS(Journal!$K$5:$K$1004,Journal!$C$5:$C$1004,$C$3,Journal!$B$5:$B$1004,E$7,Journal!$J$5:$J$1004,"Autres recettes")) -> 0 | F12: =IF(F$7>YEAR($C$4),"",SUMIFS(Journal!$K$5:$K$1004,Journal!$C$5:$C$1004,$C$3,Journal!$B$5:$B$1004,F$7,Journal!$J$5:$J$1004,"Autres recettes")) -> 0 | G12: =IF(G$7>YEAR($C$4),"",SUMIFS(Journal!$K$5:$K$1004,Journal!$C$5:$C$1004,$C$3,Journal!$B$5:$B$1004,G$7,Journal!$J$5:$J$1004,"Autres recettes")) | H12: =IF(H$7>YEAR($C$4),"",SUMIFS(Journal!$K$5:$K$1004,Journal!$C$5:$C$1004,$C$3,Journal!$B$5:$B$1004,H$7,Journal!$J$5:$J$1004,"Autres recettes"))
B13: Total des recettes imposables | D13: =IF(D$7>YEAR($C$4),"",SUMIFS(Journal!$K$5:$K$1004,Journal!$C$5:$C$1004,$C$3,Journal!$B$5:$B$1004,D$7,Journal!$I$5:$I$1004,"Imposable")) -> 8366.76 | E13: =IF(E$7>YEAR($C$4),"",SUMIFS(Journal!$K$5:$K$1004,Journal!$C$5:$C$1004,$C$3,Journal!$B$5:$B$1004,E$7,Journal!$I$5:$I$1004,"Imposable")) -> 13703.15 | F13: =IF(F$7>YEAR($C$4),"",SUMIFS(Journal!$K$5:$K$1004,Journal!$C$5:$C$1004,$C$3,Journal!$B$5:$B$1004,F$7,Journal!$I$5:$I$1004,"Imposable")) -> 11432.62 | G13: =IF(G$7>YEAR($C$4),"",SUMIFS(Journal!$K$5:$K$1004,Journal!$C$5:$C$1004,$C$3,Journal!$B$5:$B$1004,G$7,Journal!$I$5:$I$1004,"Imposable")) | H13: =IF(H$7>YEAR($C$4),"",SUMIFS(Journal!$K$5:$K$1004,Journal!$C$5:$C$1004,$C$3,Journal!$B$5:$B$1004,H$7,Journal!$I$5:$I$1004,"Imposable"))
B15: Frais de gestion (agence, comptable) | D15: =IF(D$7>YEAR($C$4),"",-SUMIFS(Journal!$K$5:$K$1004,Journal!$C$5:$C$1004,$C$3,Journal!$B$5:$B$1004,D$7,Journal!$J$5:$J$1004,"Frais de gestion",Journal!$I$5:$I$1004,"Déductible")) -> 1260.15 | E15: =IF(E$7>YEAR($C$4),"",-SUMIFS(Journal!$K$5:$K$1004,Journal!$C$5:$C$1004,$C$3,Journal!$B$5:$B$1004,E$7,Journal!$J$5:$J$1004,"Frais de gestion",Journal!$I$5:$I$1004,"Déductible")) -> 1611.54 | F15: =IF(F$7>YEAR($C$4),"",-SUMIFS(Journal!$K$5:$K$1004,Journal!$C$5:$C$1004,$C$3,Journal!$B$5:$B$1004,F$7,Journal!$J$5:$J$1004,"Frais de gestion",Journal!$I$5:$I$1004,"Déductible")) -> 1411.05 | G15: =IF(G$7>YEAR($C$4),"",-SUMIFS(Journal!$K$5:$K$1004,Journal!$C$5:$C$1004,$C$3,Journal!$B$5:$B$1004,G$7,Journal!$J$5:$J$1004,"Frais de gestion",Journal!$I$5:$I$1004,"Déductible")) | H15: =IF(H$7>YEAR($C$4),"",-SUMIFS(Journal!$K$5:$K$1004,Journal!$C$5:$C$1004,$C$3,Journal!$B$5:$B$1004,H$7,Journal!$J$5:$J$1004,"Frais de gestion",Journal!$I$5:$I$1004,"Déductible"))
B16: Copropriété | D16: =IF(D$7>YEAR($C$4),"",-SUMIFS(Journal!$K$5:$K$1004,Journal!$C$5:$C$1004,$C$3,Journal!$B$5:$B$1004,D$7,Journal!$J$5:$J$1004,"Copropriété",Journal!$I$5:$I$1004,"Déductible")) -> 1177.59 | E16: =IF(E$7>YEAR($C$4),"",-SUMIFS(Journal!$K$5:$K$1004,Journal!$C$5:$C$1004,$C$3,Journal!$B$5:$B$1004,E$7,Journal!$J$5:$J$1004,"Copropriété",Journal!$I$5:$I$1004,"Déductible")) -> 2426.77 | F16: =IF(F$7>YEAR($C$4),"",-SUMIFS(Journal!$K$5:$K$1004,Journal!$C$5:$C$1004,$C$3,Journal!$B$5:$B$1004,F$7,Journal!$J$5:$J$1004,"Copropriété",Journal!$I$5:$I$1004,"Déductible")) -> 3791.6 | G16: =IF(G$7>YEAR($C$4),"",-SUMIFS(Journal!$K$5:$K$1004,Journal!$C$5:$C$1004,$C$3,Journal!$B$5:$B$1004,G$7,Journal!$J$5:$J$1004,"Copropriété",Journal!$I$5:$I$1004,"Déductible")) | H16: =IF(H$7>YEAR($C$4),"",-SUMIFS(Journal!$K$5:$K$1004,Journal!$C$5:$C$1004,$C$3,Journal!$B$5:$B$1004,H$7,Journal!$J$5:$J$1004,"Copropriété",Journal!$I$5:$I$1004,"Déductible"))
B17: Assurances | D17: =IF(D$7>YEAR($C$4),"",-SUMIFS(Journal!$K$5:$K$1004,Journal!$C$5:$C$1004,$C$3,Journal!$B$5:$B$1004,D$7,Journal!$J$5:$J$1004,"Assurances",Journal!$I$5:$I$1004,"Déductible")) -> 105.8 | E17: =IF(E$7>YEAR($C$4),"",-SUMIFS(Journal!$K$5:$K$1004,Journal!$C$5:$C$1004,$C$3,Journal!$B$5:$B$1004,E$7,Journal!$J$5:$J$1004,"Assurances",Journal!$I$5:$I$1004,"Déductible")) -> 114.18 | F17: =IF(F$7>YEAR($C$4),"",-SUMIFS(Journal!$K$5:$K$1004,Journal!$C$5:$C$1004,$C$3,Journal!$B$5:$B$1004,F$7,Journal!$J$5:$J$1004,"Assurances",Journal!$I$5:$I$1004,"Déductible")) -> 0 | G17: =IF(G$7>YEAR($C$4),"",-SUMIFS(Journal!$K$5:$K$1004,Journal!$C$5:$C$1004,$C$3,Journal!$B$5:$B$1004,G$7,Journal!$J$5:$J$1004,"Assurances",Journal!$I$5:$I$1004,"Déductible")) | H17: =IF(H$7>YEAR($C$4),"",-SUMIFS(Journal!$K$5:$K$1004,Journal!$C$5:$C$1004,$C$3,Journal!$B$5:$B$1004,H$7,Journal!$J$5:$J$1004,"Assurances",Journal!$I$5:$I$1004,"Déductible"))
B18: Impôts et taxes | D18: =IF(D$7>YEAR($C$4),"",-SUMIFS(Journal!$K$5:$K$1004,Journal!$C$5:$C$1004,$C$3,Journal!$B$5:$B$1004,D$7,Journal!$J$5:$J$1004,"Impôts et taxes",Journal!$I$5:$I$1004,"Déductible")) -> 553.35 | E18: =IF(E$7>YEAR($C$4),"",-SUMIFS(Journal!$K$5:$K$1004,Journal!$C$5:$C$1004,$C$3,Journal!$B$5:$B$1004,E$7,Journal!$J$5:$J$1004,"Impôts et taxes",Journal!$I$5:$I$1004,"Déductible")) -> 561.72 | F18: =IF(F$7>YEAR($C$4),"",-SUMIFS(Journal!$K$5:$K$1004,Journal!$C$5:$C$1004,$C$3,Journal!$B$5:$B$1004,F$7,Journal!$J$5:$J$1004,"Impôts et taxes",Journal!$I$5:$I$1004,"Déductible")) -> 885.36 | G18: =IF(G$7>YEAR($C$4),"",-SUMIFS(Journal!$K$5:$K$1004,Journal!$C$5:$C$1004,$C$3,Journal!$B$5:$B$1004,G$7,Journal!$J$5:$J$1004,"Impôts et taxes",Journal!$I$5:$I$1004,"Déductible")) | H18: =IF(H$7>YEAR($C$4),"",-SUMIFS(Journal!$K$5:$K$1004,Journal!$C$5:$C$1004,$C$3,Journal!$B$5:$B$1004,H$7,Journal!$J$5:$J$1004,"Impôts et taxes",Journal!$I$5:$I$1004,"Déductible"))
B19: Entretien et petit équipement | D19: =IF(D$7>YEAR($C$4),"",-SUMIFS(Journal!$K$5:$K$1004,Journal!$C$5:$C$1004,$C$3,Journal!$B$5:$B$1004,D$7,Journal!$J$5:$J$1004,"Entretien et petit équipement",Journal!$I$5:$I$1004,"Déductible")) -> 453.84 | E19: =IF(E$7>YEAR($C$4),"",-SUMIFS(Journal!$K$5:$K$1004,Journal!$C$5:$C$1004,$C$3,Journal!$B$5:$B$1004,E$7,Journal!$J$5:$J$1004,"Entretien et petit équipement",Journal!$I$5:$I$1004,"Déductible")) -> 386.42 | F19: =IF(F$7>YEAR($C$4),"",-SUMIFS(Journal!$K$5:$K$1004,Journal!$C$5:$C$1004,$C$3,Journal!$B$5:$B$1004,F$7,Journal!$J$5:$J$1004,"Entretien et petit équipement",Journal!$I$5:$I$1004,"Déductible")) -> 1141.67 | G19: =IF(G$7>YEAR($C$4),"",-SUMIFS(Journal!$K$5:$K$1004,Journal!$C$5:$C$1004,$C$3,Journal!$B$5:$B$1004,G$7,Journal!$J$5:$J$1004,"Entretien et petit équipement",Journal!$I$5:$I$1004,"Déductible")) | H19: =IF(H$7>YEAR($C$4),"",-SUMIFS(Journal!$K$5:$K$1004,Journal!$C$5:$C$1004,$C$3,Journal!$B$5:$B$1004,H$7,Journal!$J$5:$J$1004,"Entretien et petit équipement",Journal!$I$5:$I$1004,"Déductible"))
B20: Autres charges | D20: =IF(D$7>YEAR($C$4),"",-SUMIFS(Journal!$K$5:$K$1004,Journal!$C$5:$C$1004,$C$3,Journal!$B$5:$B$1004,D$7,Journal!$J$5:$J$1004,"Autres charges",Journal!$I$5:$I$1004,"Déductible")) -> 0 | E20: =IF(E$7>YEAR($C$4),"",-SUMIFS(Journal!$K$5:$K$1004,Journal!$C$5:$C$1004,$C$3,Journal!$B$5:$B$1004,E$7,Journal!$J$5:$J$1004,"Autres charges",Journal!$I$5:$I$1004,"Déductible")) -> 0 | F20: =IF(F$7>YEAR($C$4),"",-SUMIFS(Journal!$K$5:$K$1004,Journal!$C$5:$C$1004,$C$3,Journal!$B$5:$B$1004,F$7,Journal!$J$5:$J$1004,"Autres charges",Journal!$I$5:$I$1004,"Déductible")) -> 0 | G20: =IF(G$7>YEAR($C$4),"",-SUMIFS(Journal!$K$5:$K$1004,Journal!$C$5:$C$1004,$C$3,Journal!$B$5:$B$1004,G$7,Journal!$J$5:$J$1004,"Autres charges",Journal!$I$5:$I$1004,"Déductible")) | H20: =IF(H$7>YEAR($C$4),"",-SUMIFS(Journal!$K$5:$K$1004,Journal!$C$5:$C$1004,$C$3,Journal!$B$5:$B$1004,H$7,Journal!$J$5:$J$1004,"Autres charges",Journal!$I$5:$I$1004,"Déductible"))
B21: Intérêts d'emprunt (période louée) | D21: =IF(D$7>YEAR($C$4),"",SUMIFS(Échéancier!$G$5:$G$300,Échéancier!$J$5:$J$300,$C$3,Échéancier!$D$5:$D$300,D$7,Échéancier!$K$5:$K$300,1,Échéancier!$C$5:$C$300,"<="&$C$4)) -> 1035.57 | E21: =IF(E$7>YEAR($C$4),"",SUMIFS(Échéancier!$G$5:$G$300,Échéancier!$J$5:$J$300,$C$3,Échéancier!$D$5:$D$300,E$7,Échéancier!$K$5:$K$300,1,Échéancier!$C$5:$C$300,"<="&$C$4)) -> 1678.76 | F21: =IF(F$7>YEAR($C$4),"",SUMIFS(Échéancier!$G$5:$G$300,Échéancier!$J$5:$J$300,$C$3,Échéancier!$D$5:$D$300,F$7,Échéancier!$K$5:$K$300,1,Échéancier!$C$5:$C$300,"<="&$C$4)) -> 1304.71 | G21: =IF(G$7>YEAR($C$4),"",SUMIFS(Échéancier!$G$5:$G$300,Échéancier!$J$5:$J$300,$C$3,Échéancier!$D$5:$D$300,G$7,Échéancier!$K$5:$K$300,1,Échéancier!$C$5:$C$300,"<="&$C$4)) | H21: =IF(H$7>YEAR($C$4),"",SUMIFS(Échéancier!$G$5:$G$300,Échéancier!$J$5:$J$300,$C$3,Échéancier!$D$5:$D$300,H$7,Échéancier!$K$5:$K$300,1,Échéancier!$C$5:$C$300,"<="&$C$4))
B22: Assurance emprunteur (période louée) | D22: =IF(D$7>YEAR($C$4),"",SUMIFS(Échéancier!$H$5:$H$300,Échéancier!$J$5:$J$300,$C$3,Échéancier!$D$5:$D$300,D$7,Échéancier!$K$5:$K$300,1,Échéancier!$C$5:$C$300,"<="&$C$4)) -> 140.56 | E22: =IF(E$7>YEAR($C$4),"",SUMIFS(Échéancier!$H$5:$H$300,Échéancier!$J$5:$J$300,$C$3,Échéancier!$D$5:$D$300,E$7,Échéancier!$K$5:$K$300,1,Échéancier!$C$5:$C$300,"<="&$C$4)) -> 240.96 | F22: =IF(F$7>YEAR($C$4),"",SUMIFS(Échéancier!$H$5:$H$300,Échéancier!$J$5:$J$300,$C$3,Échéancier!$D$5:$D$300,F$7,Échéancier!$K$5:$K$300,1,Échéancier!$C$5:$C$300,"<="&$C$4)) -> 200.8 | G22: =IF(G$7>YEAR($C$4),"",SUMIFS(Échéancier!$H$5:$H$300,Échéancier!$J$5:$J$300,$C$3,Échéancier!$D$5:$D$300,G$7,Échéancier!$K$5:$K$300,1,Échéancier!$C$5:$C$300,"<="&$C$4)) | H22: =IF(H$7>YEAR($C$4),"",SUMIFS(Échéancier!$H$5:$H$300,Échéancier!$J$5:$J$300,$C$3,Échéancier!$D$5:$D$300,H$7,Échéancier!$K$5:$K$300,1,Échéancier!$C$5:$C$300,"<="&$C$4))
B23: Total des charges déductibles | D23: =IF(D$7>YEAR($C$4),"",SUM(D15:D22)) -> 4726.86 | E23: =IF(E$7>YEAR($C$4),"",SUM(E15:E22)) -> 7020.35 | F23: =IF(F$7>YEAR($C$4),"",SUM(F15:F22)) -> 8735.19 | G23: =IF(G$7>YEAR($C$4),"",SUM(G15:G22)) | H23: =IF(H$7>YEAR($C$4),"",SUM(H15:H22))
B24: Résultat avant amortissements | D24: =IF(D$7>YEAR($C$4),"",D13-D23) -> 3639.9 | E24: =IF(E$7>YEAR($C$4),"",E13-E23) -> 6682.8 | F24: =IF(F$7>YEAR($C$4),"",F13-F23) -> 2697.43 | G24: =IF(G$7>YEAR($C$4),"",G13-G23) | H24: =IF(H$7>YEAR($C$4),"",H13-H23)
B25: Dotations aux amortissements de l'année | D25: =IF(D$7>YEAR($C$4),"",SUMPRODUCT((Amortissements!$A$5:$A$40=$C$3)*(Amortissements!$H$4:$L$4=D$7)*Amortissements!$H$5:$L$40)) -> 5751.0489 | E25: =IF(E$7>YEAR($C$4),"",SUMPRODUCT((Amortissements!$A$5:$A$40=$C$3)*(Amortissements!$H$4:$L$4=E$7)*Amortissements!$H$5:$L$40)) -> 9297.3367 | F25: =IF(F$7>YEAR($C$4),"",SUMPRODUCT((Amortissements!$A$5:$A$40=$C$3)*(Amortissements!$H$4:$L$4=F$7)*Amortissements!$H$5:$L$40)) -> 9388.3868 | G25: =IF(G$7>YEAR($C$4),"",SUMPRODUCT((Amortissements!$A$5:$A$40=$C$3)*(Amortissements!$H$4:$L$4=G$7)*Amortissements!$H$5:$L$40)) | H25: =IF(H$7>YEAR($C$4),"",SUMPRODUCT((Amortissements!$A$5:$A$40=$C$3)*(Amortissements!$H$4:$L$4=H$7)*Amortissements!$H$5:$L$40))
B26: Amortissements en report (début d'année) | D26: =IF(D$7>YEAR($C$4),"",0) -> 0 | E26: =IF(E$7>YEAR($C$4),"",IF(ISNUMBER(D32),D32,D28)) -> 1834.69 | F26: =IF(F$7>YEAR($C$4),"",IF(ISNUMBER(E32),E32,E28)) -> 3824.3 | G26: =IF(G$7>YEAR($C$4),"",IF(ISNUMBER(F32),F32,F28)) | H26: =IF(H$7>YEAR($C$4),"",IF(ISNUMBER(G32),G32,G28))
B27: Amortissements utilisés | D27: =IF(D$7>YEAR($C$4),"",MIN(D25+D26,MAX(0,D24))) -> 3639.9 | E27: =IF(E$7>YEAR($C$4),"",MIN(E25+E26,MAX(0,E24))) -> 6682.8 | F27: =IF(F$7>YEAR($C$4),"",MIN(F25+F26,MAX(0,F24))) -> 2697.43 | G27: =IF(G$7>YEAR($C$4),"",MIN(G25+G26,MAX(0,G24))) | H27: =IF(H$7>YEAR($C$4),"",MIN(H25+H26,MAX(0,H24))) | I27: Un amortissement ne peut pas créer de déficit : l'excédent est reporté sans limite de durée.
B28: Amortissements en report (fin d'année, calcul de l'outil) | D28: =IF(D$7>YEAR($C$4),"",D26+D25-D27) -> 2111.1489 | E28: =IF(E$7>YEAR($C$4),"",E26+E25-E27) -> 4449.2267 | F28: =IF(F$7>YEAR($C$4),"",F26+F25-F27) -> 10515.257 | G28: =IF(G$7>YEAR($C$4),"",G26+G25-G27) | H28: =IF(H$7>YEAR($C$4),"",H26+H25-H27) | I28: Année en cours : estimation, la dotation est annuelle alors que les recettes ne sont saisies que jusqu'à la date de mise à jour.
B29: Résultat fiscal estimé | D29: =IF(D$7>YEAR($C$4),"",D24-D27) -> 0 | E29: =IF(E$7>YEAR($C$4),"",E24-E27) -> 0 | F29: =IF(F$7>YEAR($C$4),"",F24-F27) -> 0 | G29: =IF(G$7>YEAR($C$4),"",G24-G27) | H29: =IF(H$7>YEAR($C$4),"",H24-H27) | I29: Négatif = déficit imputable sur les revenus de location meublée des 10 années suivantes.
B30: Dépenses à qualifier (non retenues) | D30: =IF(D$7>YEAR($C$4),"",-SUMIFS(Journal!$K$5:$K$1004,Journal!$C$5:$C$1004,$C$3,Journal!$B$5:$B$1004,D$7,Journal!$I$5:$I$1004,"À valider")) -> 395.25 | E30: =IF(E$7>YEAR($C$4),"",-SUMIFS(Journal!$K$5:$K$1004,Journal!$C$5:$C$1004,$C$3,Journal!$B$5:$B$1004,E$7,Journal!$I$5:$I$1004,"À valider")) -> 0 | F30: =IF(F$7>YEAR($C$4),"",-SUMIFS(Journal!$K$5:$K$1004,Journal!$C$5:$C$1004,$C$3,Journal!$B$5:$B$1004,F$7,Journal!$I$5:$I$1004,"À valider")) -> 0 | G30: =IF(G$7>YEAR($C$4),"",-SUMIFS(Journal!$K$5:$K$1004,Journal!$C$5:$C$1004,$C$3,Journal!$B$5:$B$1004,G$7,Journal!$I$5:$I$1004,"À valider")) | H30: =IF(H$7>YEAR($C$4),"",-SUMIFS(Journal!$K$5:$K$1004,Journal!$C$5:$C$1004,$C$3,Journal!$B$5:$B$1004,H$7,Journal!$I$5:$I$1004,"À valider")) | I30: À valider avec le comptable (onglet Journal, lignes surlignées).
B31: Investissements de l'année (à amortir) | D31: =IF(D$7>YEAR($C$4),"",-SUMIFS(Journal!$K$5:$K$1004,Journal!$C$5:$C$1004,$C$3,Journal!$B$5:$B$1004,D$7,Journal!$I$5:$I$1004,"À amortir")) -> 1076.01 | E31: =IF(E$7>YEAR($C$4),"",-SUMIFS(Journal!$K$5:$K$1004,Journal!$C$5:$C$1004,$C$3,Journal!$B$5:$B$1004,E$7,Journal!$I$5:$I$1004,"À amortir")) -> 1590.11 | F31: =IF(F$7>YEAR($C$4),"",-SUMIFS(Journal!$K$5:$K$1004,Journal!$C$5:$C$1004,$C$3,Journal!$B$5:$B$1004,F$7,Journal!$I$5:$I$1004,"À amortir")) -> 0 | G31: =IF(G$7>YEAR($C$4),"",-SUMIFS(Journal!$K$5:$K$1004,Journal!$C$5:$C$1004,$C$3,Journal!$B$5:$B$1004,G$7,Journal!$I$5:$I$1004,"À amortir")) | H31: =IF(H$7>YEAR($C$4),"",-SUMIFS(Journal!$K$5:$K$1004,Journal!$C$5:$C$1004,$C$3,Journal!$B$5:$B$1004,H$7,Journal!$I$5:$I$1004,"À amortir")) | I31: À reporter dans l'onglet Amortissements.
B32: Stock reporté retenu par le comptable (comptes déposés) | D32: 1834.69 | E32: 3824.3 | I32: À saisir chaque année depuis les comptes du comptable. S'il est renseigné, c'est ce stock qui sert de point de départ l'année suivante (il fait foi pour la déclaration).
B33: 2. Trésorerie (cash-flow)
B34: Encaissements (recettes) | D34: =IF(D$7>YEAR($C$4),"",SUMIFS(Journal!$K$5:$K$1004,Journal!$C$5:$C$1004,$C$3,Journal!$B$5:$B$1004,D$7,Journal!$H$5:$H$1004,"Recette")) -> 8366.76 | E34: =IF(E$7>YEAR($C$4),"",SUMIFS(Journal!$K$5:$K$1004,Journal!$C$5:$C$1004,$C$3,Journal!$B$5:$B$1004,E$7,Journal!$H$5:$H$1004,"Recette")) -> 13703.15 | F34: =IF(F$7>YEAR($C$4),"",SUMIFS(Journal!$K$5:$K$1004,Journal!$C$5:$C$1004,$C$3,Journal!$B$5:$B$1004,F$7,Journal!$H$5:$H$1004,"Recette")) -> 11432.62 | G34: =IF(G$7>YEAR($C$4),"",SUMIFS(Journal!$K$5:$K$1004,Journal!$C$5:$C$1004,$C$3,Journal!$B$5:$B$1004,G$7,Journal!$H$5:$H$1004,"Recette")) | H34: =IF(H$7>YEAR($C$4),"",SUMIFS(Journal!$K$5:$K$1004,Journal!$C$5:$C$1004,$C$3,Journal!$B$5:$B$1004,H$7,Journal!$H$5:$H$1004,"Recette"))
B35: Dépenses payées (hors prêt) | D35: =IF(D$7>YEAR($C$4),"",-SUMIFS(Journal!$K$5:$K$1004,Journal!$C$5:$C$1004,$C$3,Journal!$B$5:$B$1004,D$7,Journal!$H$5:$H$1004,"Dépense")) -> 5021.99 | E35: =IF(E$7>YEAR($C$4),"",-SUMIFS(Journal!$K$5:$K$1004,Journal!$C$5:$C$1004,$C$3,Journal!$B$5:$B$1004,E$7,Journal!$H$5:$H$1004,"Dépense")) -> 6690.74 | F35: =IF(F$7>YEAR($C$4),"",-SUMIFS(Journal!$K$5:$K$1004,Journal!$C$5:$C$1004,$C$3,Journal!$B$5:$B$1004,F$7,Journal!$H$5:$H$1004,"Dépense")) -> 7229.68 | G35: =IF(G$7>YEAR($C$4),"",-SUMIFS(Journal!$K$5:$K$1004,Journal!$C$5:$C$1004,$C$3,Journal!$B$5:$B$1004,G$7,Journal!$H$5:$H$1004,"Dépense")) | H35: =IF(H$7>YEAR($C$4),"",-SUMIFS(Journal!$K$5:$K$1004,Journal!$C$5:$C$1004,$C$3,Journal!$B$5:$B$1004,H$7,Journal!$H$5:$H$1004,"Dépense"))
B36: Échéances de prêt (période louée) | D36: =IF(D$7>YEAR($C$4),"",SUMIFS(Échéancier!$I$5:$I$300,Échéancier!$J$5:$J$300,$C$3,Échéancier!$D$5:$D$300,D$7,Échéancier!$K$5:$K$300,1,Échéancier!$C$5:$C$300,"<="&$C$4)) -> 5889.26 | E36: =IF(E$7>YEAR($C$4),"",SUMIFS(Échéancier!$I$5:$I$300,Échéancier!$J$5:$J$300,$C$3,Échéancier!$D$5:$D$300,E$7,Échéancier!$K$5:$K$300,1,Échéancier!$C$5:$C$300,"<="&$C$4)) -> 10095.91 | F36: =IF(F$7>YEAR($C$4),"",SUMIFS(Échéancier!$I$5:$I$300,Échéancier!$J$5:$J$300,$C$3,Échéancier!$D$5:$D$300,F$7,Échéancier!$K$5:$K$300,1,Échéancier!$C$5:$C$300,"<="&$C$4)) -> 8413.25 | G36: =IF(G$7>YEAR($C$4),"",SUMIFS(Échéancier!$I$5:$I$300,Échéancier!$J$5:$J$300,$C$3,Échéancier!$D$5:$D$300,G$7,Échéancier!$K$5:$K$300,1,Échéancier!$C$5:$C$300,"<="&$C$4)) | H36: =IF(H$7>YEAR($C$4),"",SUMIFS(Échéancier!$I$5:$I$300,Échéancier!$J$5:$J$300,$C$3,Échéancier!$D$5:$D$300,H$7,Échéancier!$K$5:$K$300,1,Échéancier!$C$5:$C$300,"<="&$C$4))
B37: dont capital remboursé | D37: =IF(D$7>YEAR($C$4),"",SUMIFS(Échéancier!$F$5:$F$300,Échéancier!$J$5:$J$300,$C$3,Échéancier!$D$5:$D$300,D$7,Échéancier!$K$5:$K$300,1,Échéancier!$C$5:$C$300,"<="&$C$4)) -> 4713.13 | E37: =IF(E$7>YEAR($C$4),"",SUMIFS(Échéancier!$F$5:$F$300,Échéancier!$J$5:$J$300,$C$3,Échéancier!$D$5:$D$300,E$7,Échéancier!$K$5:$K$300,1,Échéancier!$C$5:$C$300,"<="&$C$4)) -> 8176.19 | F37: =IF(F$7>YEAR($C$4),"",SUMIFS(Échéancier!$F$5:$F$300,Échéancier!$J$5:$J$300,$C$3,Échéancier!$D$5:$D$300,F$7,Échéancier!$K$5:$K$300,1,Échéancier!$C$5:$C$300,"<="&$C$4)) -> 6907.74 | G37: =IF(G$7>YEAR($C$4),"",SUMIFS(Échéancier!$F$5:$F$300,Échéancier!$J$5:$J$300,$C$3,Échéancier!$D$5:$D$300,G$7,Échéancier!$K$5:$K$300,1,Échéancier!$C$5:$C$300,"<="&$C$4)) | H37: =IF(H$7>YEAR($C$4),"",SUMIFS(Échéancier!$F$5:$F$300,Échéancier!$J$5:$J$300,$C$3,Échéancier!$D$5:$D$300,H$7,Échéancier!$K$5:$K$300,1,Échéancier!$C$5:$C$300,"<="&$C$4))
B38: Cash-flow | D38: =IF(D$7>YEAR($C$4),"",D34-D35-D36) -> -2544.49 | E38: =IF(E$7>YEAR($C$4),"",E34-E35-E36) -> -3083.5 | F38: =IF(F$7>YEAR($C$4),"",F34-F35-F36) -> -4210.31 | G38: =IF(G$7>YEAR($C$4),"",G34-G35-G36) | H38: =IF(H$7>YEAR($C$4),"",H34-H35-H36)
B39: Mois de location sur la période | D39: =IF(D$7>YEAR($C$4),"",MAX(0,MIN(DATE(D$7,12,31),EOMONTH($C$4,0))-MAX(DATE(D$7,1,1),IFERROR(INDEX(Biens!$O$5:$O$30,MATCH(Synthèse!$C$3,Biens!$A$5:$A$30,0)),0))+1)/(365/12)) -> 7.4958904 | E39: =IF(E$7>YEAR($C$4),"",MAX(0,MIN(DATE(E$7,12,31),EOMONTH($C$4,0))-MAX(DATE(E$7,1,1),IFERROR(INDEX(Biens!$O$5:$O$30,MATCH(Synthèse!$C$3,Biens!$A$5:$A$30,0)),0))+1)/(365/12)) -> 12 | F39: =IF(F$7>YEAR($C$4),"",MAX(0,MIN(DATE(F$7,12,31),EOMONTH($C$4,0))-MAX(DATE(F$7,1,1),IFERROR(INDEX(Biens!$O$5:$O$30,MATCH(Synthèse!$C$3,Biens!$A$5:$A$30,0)),0))+1)/(365/12)) -> 9.9945205 | G39: =IF(G$7>YEAR($C$4),"",MAX(0,MIN(DATE(G$7,12,31),EOMONTH($C$4,0))-MAX(DATE(G$7,1,1),IFERROR(INDEX(Biens!$O$5:$O$30,MATCH(Synthèse!$C$3,Biens!$A$5:$A$30,0)),0))+1)/(365/12)) | H39: =IF(H$7>YEAR($C$4),"",MAX(0,MIN(DATE(H$7,12,31),EOMONTH($C$4,0))-MAX(DATE(H$7,1,1),IFERROR(INDEX(Biens!$O$5:$O$30,MATCH(Synthèse!$C$3,Biens!$A$5:$A$30,0)),0))+1)/(365/12)) | I39: Jusqu'à la fin du mois de la date de mise à jour (C4), les loyers étant payés d'avance.
B40: Cash-flow mensuel moyen | D40: =IF(D$7>YEAR($C$4),"",IF(D39>0,D38/D39,0)) -> -339.45133 | E40: =IF(E$7>YEAR($C$4),"",IF(E39>0,E38/E39,0)) -> -256.95833 | F40: =IF(F$7>YEAR($C$4),"",IF(F39>0,F38/F39,0)) -> -421.26183 | G40: =IF(G$7>YEAR($C$4),"",IF(G39>0,G38/G39,0)) | H40: =IF(H$7>YEAR($C$4),"",IF(H39>0,H38/H39,0))
B41: Enrichissement (cash-flow + capital remboursé) | D41: =IF(D$7>YEAR($C$4),"",D38+D37) -> 2168.64 | E41: =IF(E$7>YEAR($C$4),"",E38+E37) -> 5092.69 | F41: =IF(F$7>YEAR($C$4),"",F38+F37) -> 2697.43 | G41: =IF(G$7>YEAR($C$4),"",G38+G37) | H41: =IF(H$7>YEAR($C$4),"",H38+H37)
B43: 3. Rentabilité
B44: Coût total d'acquisition | D44: =IF(D$7>YEAR($C$4),"",IFERROR(INDEX(Biens!$M$5:$M$30,MATCH(Synthèse!$C$3,Biens!$A$5:$A$30,0)),0)) -> 268158.99 | E44: =IF(E$7>YEAR($C$4),"",IFERROR(INDEX(Biens!$M$5:$M$30,MATCH(Synthèse!$C$3,Biens!$A$5:$A$30,0)),0)) -> 268158.99 | F44: =IF(F$7>YEAR($C$4),"",IFERROR(INDEX(Biens!$M$5:$M$30,MATCH(Synthèse!$C$3,Biens!$A$5:$A$30,0)),0)) -> 268158.99 | G44: =IF(G$7>YEAR($C$4),"",IFERROR(INDEX(Biens!$M$5:$M$30,MATCH(Synthèse!$C$3,Biens!$A$5:$A$30,0)),0)) | H44: =IF(H$7>YEAR($C$4),"",IFERROR(INDEX(Biens!$M$5:$M$30,MATCH(Synthèse!$C$3,Biens!$A$5:$A$30,0)),0))
B45: Loyers hors charges annualisés | D45: =IF(D$7>YEAR($C$4),"",IF(D39>0,D10/D39*12,0)) -> 12314.428 | E45: =IF(E$7>YEAR($C$4),"",IF(E39>0,E10/E39*12,0)) -> 12387.89 | F45: =IF(F$7>YEAR($C$4),"",IF(F39>0,F10/F39*12,0)) -> 12621.22 | G45: =IF(G$7>YEAR($C$4),"",IF(G39>0,G10/G39*12,0)) | H45: =IF(H$7>YEAR($C$4),"",IF(H39>0,H10/H39*12,0))
B46: Rendement brut | D46: =IF(D$7>YEAR($C$4),"",IF(D44>0,D45/D44,0)) -> 0.045922114 | E46: =IF(E$7>YEAR($C$4),"",IF(E44>0,E45/E44,0)) -> 0.046196065 | F46: =IF(F$7>YEAR($C$4),"",IF(F44>0,F45/F44,0)) -> 0.047066182 | G46: =IF(G$7>YEAR($C$4),"",IF(G44>0,G45/G44,0)) | H46: =IF(H$7>YEAR($C$4),"",IF(H44>0,H45/H44,0))
B47: Rendement net (avant financement) | D47: =IF(D$7>YEAR($C$4),"",IF(AND(D39>0,D44>0),(D13-(D23-D21-D22))/D39*12/D44,0)) -> 0.028751125 | E47: =IF(E$7>YEAR($C$4),"",IF(AND(E39>0,E44>0),(E13-(E23-E21-E22))/E39*12/E44,0)) -> 0.032079924 | F47: =IF(F$7>YEAR($C$4),"",IF(AND(F39>0,F44>0),(F13-(F23-F21-F22))/F39*12/F44,0)) -> 0.018818288 | G47: =IF(G$7>YEAR($C$4),"",IF(AND(G39>0,G44>0),(G13-(G23-G21-G22))/G39*12/G44,0)) | H47: =IF(H$7>YEAR($C$4),"",IF(AND(H39>0,H44>0),(H13-(H23-H21-H22))/H39*12/H44,0)) | I47: Recettes moins charges hors intérêts, annualisées, rapportées au coût d'acquisition.
B48: Capital restant dû au 31/12 | D48: =IF(D$7>YEAR($C$4),"",SUMIFS(Prêts!$E$5:$E$14,Prêts!$B$5:$B$14,$C$3)-SUMIFS(Échéancier!$F$5:$F$300,Échéancier!$J$5:$J$300,$C$3,Échéancier!$C$5:$C$300,"<="&DATE(D$7,12,31))) -> 115654.93 | E48: =IF(E$7>YEAR($C$4),"",SUMIFS(Prêts!$E$5:$E$14,Prêts!$B$5:$B$14,$C$3)-SUMIFS(Échéancier!$F$5:$F$300,Échéancier!$J$5:$J$300,$C$3,Échéancier!$C$5:$C$300,"<="&DATE(E$7,12,31))) -> 107478.74 | F48: =IF(F$7>YEAR($C$4),"",SUMIFS(Prêts!$E$5:$E$14,Prêts!$B$5:$B$14,$C$3)-SUMIFS(Échéancier!$F$5:$F$300,Échéancier!$J$5:$J$300,$C$3,Échéancier!$C$5:$C$300,"<="&DATE(F$7,12,31))) -> 99179.07 | G48: =IF(G$7>YEAR($C$4),"",SUMIFS(Prêts!$E$5:$E$14,Prêts!$B$5:$B$14,$C$3)-SUMIFS(Échéancier!$F$5:$F$300,Échéancier!$J$5:$J$300,$C$3,Échéancier!$C$5:$C$300,"<="&DATE(G$7,12,31))) | H48: =IF(H$7>YEAR($C$4),"",SUMIFS(Prêts!$E$5:$E$14,Prêts!$B$5:$B$14,$C$3)-SUMIFS(Échéancier!$F$5:$F$300,Échéancier!$J$5:$J$300,$C$3,Échéancier!$C$5:$C$300,"<="&DATE(H$7,12,31)))
B49: Valeur estimée moins capital restant dû | D49: =IF(D$7>YEAR($C$4),"",IFERROR(INDEX(Biens!$P$5:$P$30,MATCH(Synthèse!$C$3,Biens!$A$5:$A$30,0)),0)-D48) -> 167995.07 | E49: =IF(E$7>YEAR($C$4),"",IFERROR(INDEX(Biens!$P$5:$P$30,MATCH(Synthèse!$C$3,Biens!$A$5:$A$30,0)),0)-E48) -> 176171.26 | F49: =IF(F$7>YEAR($C$4),"",IFERROR(INDEX(Biens!$P$5:$P$30,MATCH(Synthèse!$C$3,Biens!$A$5:$A$30,0)),0)-F48) -> 184470.93 | G49: =IF(G$7>YEAR($C$4),"",IFERROR(INDEX(Biens!$P$5:$P$30,MATCH(Synthèse!$C$3,Biens!$A$5:$A$30,0)),0)-G48) | H49: =IF(H$7>YEAR($C$4),"",IFERROR(INDEX(Biens!$P$5:$P$30,MATCH(Synthèse!$C$3,Biens!$A$5:$A$30,0)),0)-H48)
B51: Ce tableau est un outil de suivi, pas un conseil fiscal. Les règles (amortissements, déficits, catégories déductibles) sont à confirmer avec votre expert-comptable ou sur impots.gouv.fr.

Sheet Journal
A1: Journal des mouvements
A2: Une ligne par mouvement d'argent (agence, banque ou autre). Montant toujours positif, sauf annulation ou remise. Saisissez les colonnes A, C à G et M à O : les colonnes grises se calculent.
A4: Date | B4: Année | C4: Bien | D4: Compte | E4: Catégorie | F4: Libellé | G4: Montant | H4: Sens | I4: Traitement fiscal | J4: Groupe | K4: Montant au résultat | L4: Flux de trésorerie | M4: Pièce justificative | N4: Source | O4: Commentaire
A5: 45426 | B5: =IF(A5="","",YEAR(A5)) -> 2024 | C5: APPART-01 | D5: Agence | E5: Honoraires de mise en location | F5: HONORAIRES EDL | G5: 140.04 | H5: =IF(E5="","",IFERROR(INDEX(Catégories!$B$5:$B$60,MATCH(E5,Catégories!$A$5:$A$60,0)),"?")) -> Dépense | I5: =IF(E5="","",IFERROR(INDEX(Catégories!$C$5:$C$60,MATCH(E5,Catégories!$A$5:$A$60,0)),"?")) -> Déductible | J5: =IF(E5="","",IFERROR(INDEX(Catégories!$D$5:$D$60,MATCH(E5,Catégories!$A$5:$A$60,0)),"?")) -> Frais de gestion | K5: =IF(H5="Recette",G5,IF(H5="Dépense",-G5,0)) -> -140.04 | L5: =IF(E5="",0,G5*IFERROR(INDEX(Catégories!$E$5:$E$60,MATCH(E5,Catégories!$A$5:$A$60,0)),0)) -> -140.04 | M5: Bien/04_Agence/2024-05_2026-11_AGENCE_Grand-livre-proprietaire.pdf | N5: Grand livre agence
A6: 45426 | B6: =IF(A6="","",YEAR(A6)) -> 2024 | C6: APPART-01 | D6: Agence | E6: Honoraires de mise en location | F6: TVA HONORAIRES EDL | G6: 28 | H6: =IF(E6="","",IFERROR(INDEX(Catégories!$B$5:$B$60,MATCH(E6,Catégories!$A$5:$A$60,0)),"?")) -> Dépense | I6: =IF(E6="","",IFERROR(INDEX(Catégories!$C$5:$C$60,MATCH(E6,Catégories!$A$5:$A$60,0)),"?")) -> Déductible | J6: =IF(E6="","",IFERROR(INDEX(Catégories!$D$5:$D$60,MATCH(E6,Catégories!$A$5:$A$60,0)),"?")) -> Frais de gestion | K6: =IF(H6="Recette",G6,IF(H6="Dépense",-G6,0)) -> -28 | L6: =IF(E6="",0,G6*IFERROR(INDEX(Catégories!$E$5:$E$60,MATCH(E6,Catégories!$A$5:$A$60,0)),0)) -> -28 | M6: Bien/04_Agence/2024-05_2026-11_AGENCE_Grand-livre-proprietaire.pdf | N6: Grand livre agence
A7: 45426 | B7: =IF(A7="","",YEAR(A7)) -> 2024 | C7: APPART-01 | D7: Agence | E7: Honoraires de mise en location | F7: HONORAIRES LOCATION | G7: 369.86 | H7: =IF(E7="","",IFERROR(INDEX(Catégories!$B$5:$B$60,MATCH(E7,Catégories!$A$5:$A$60,0)),"?")) -> Dépense | I7: =IF(E7="","",IFERROR(INDEX(Catégories!$C$5:$C$60,MATCH(E7,Catégories!$A$5:$A$60,0)),"?")) -> Déductible | J7: =IF(E7="","",IFERROR(INDEX(Catégories!$D$5:$D$60,MATCH(E7,Catégories!$A$5:$A$60,0)),"?")) -> Frais de gestion | K7: =IF(H7="Recette",G7,IF(H7="Dépense",-G7,0)) -> -369.86 | L7: =IF(E7="",0,G7*IFERROR(INDEX(Catégories!$E$5:$E$60,MATCH(E7,Catégories!$A$5:$A$60,0)),0)) -> -369.86 | M7: Bien/04_Agence/2024-05_2026-11_AGENCE_Grand-livre-proprietaire.pdf | N7: Grand livre agence
A8: 45426 | B8: =IF(A8="","",YEAR(A8)) -> 2024 | C8: APPART-01 | D8: Agence | E8: Honoraires de mise en location | F8: TVA HONORAIRES LOCATION | G8: 73.97 | H8: =IF(E8="","",IFERROR(INDEX(Catégories!$B$5:$B$60,MATCH(E8,Catégories!$A$5:$A$60,0)),"?")) -> Dépense | I8: =IF(E8="","",IFERROR(INDEX(Catégories!$C$5:$C$60,MATCH(E8,Catégories!$A$5:$A$60,0)),"?")) -> Déductible | J8: =IF(E8="","",IFERROR(INDEX(Catégories!$D$5:$D$60,MATCH(E8,Catégories!$A$5:$A$60,0)),"?")) -> Frais de gestion | K8: =IF(H8="Recette",G8,IF(H8="Dépense",-G8,0)) -> -73.97 | L8: =IF(E8="",0,G8*IFERROR(INDEX(Catégories!$E$5:$E$60,MATCH(E8,Catégories!$A$5:$A$60,0)),0)) -> -73.97 | M8: Bien/04_Agence/2024-05_2026-11_AGENCE_Grand-livre-proprietaire.pdf | N8: Grand livre agence
A9: 45427 | B9: =IF(A9="","",YEAR(A9)) -> 2024 | C9: APPART-01 | D9: Agence | E9: Loyer hors charges | F9: LOYER PRINCIPAL (18/05/2024 - 31/05/2024) | G9: 466.2 | H9: =IF(E9="","",IFERROR(INDEX(Catégories!$B$5:$B$60,MATCH(E9,Catégories!$A$5:$A$60,0)),"?")) -> Recette | I9: =IF(E9="","",IFERROR(INDEX(Catégories!$C$5:$C$60,MATCH(E9,Catégories!$A$5:$A$60,0)),"?")) -> Imposable | J9: =IF(E9="","",IFERROR(INDEX(Catégories!$D$5:$D$60,MATCH(E9,Catégories!$A$5:$A$60,0)),"?")) -> Loyers | K9: =IF(H9="Recette",G9,IF(H9="Dépense",-G9,0)) -> 466.2 | L9: =IF(E9="",0,G9*IFERROR(INDEX(Catégories!$E$5:$E$60,MATCH(E9,Catégories!$A$5:$A$60,0)),0)) -> 466.2 | M9: Bien/04_Agence/2024-05_2026-11_AGENCE_Grand-livre-proprietaire.pdf | N9: Grand livre agence
A10: 45427 | B10: =IF(A10="","",YEAR(A10)) -> 2024 | C10: APPART-01 | D10: Agence | E10: Honoraires de gestion | F10: HONORAIRES GESTION LOYER PRINCIPAL 6.00% | G10: 27.97 | H10: =IF(E10="","",IFERROR(INDEX(Catégories!$B$5:$B$60,MATCH(E10,Catégories!$A$5:$A$60,0)),"?")) -> Dépense | I10: =IF(E10="","",IFERROR(INDEX(Catégories!$C$5:$C$60,MATCH(E10,Catégories!$A$5:$A$60,0)),"?")) -> Déductible | J10: =IF(E10="","",IFERROR(INDEX(Catégories!$D$5:$D$60,MATCH(E10,Catégories!$A$5:$A$60,0)),"?")) -> Frais de gestion | K10: =IF(H10="Recette",G10,IF(H10="Dépense",-G10,0)) -> -27.97 | L10: =IF(E10="",0,G10*IFERROR(INDEX(Catégories!$E$5:$E$60,MATCH(E10,Catégories!$A$5:$A$60,0)),0)) -> -27.97 | M10: Bien/04_Agence/2024-05_2026-11_AGENCE_Grand-livre-proprietaire.pdf | N10: Grand livre agence
A11: 45427 | B11: =IF(A11="","",YEAR(A11)) -> 2024 | C11: APPART-01 | D11: Agence | E11: Honoraires de gestion | F11: TVA HONORAIRES GESTION LOYER PRINCIPAL | G11: 5.6 | H11: =IF(E11="","",IFERROR(INDEX(Catégories!$B$5:$B$60,MATCH(E11,Catégories!$A$5:$A$60,0)),"?")) -> Dépense | I11: =IF(E11="","",IFERROR(INDEX(Catégories!$C$5:$C$60,MATCH(E11,Catégories!$A$5:$A$60,0)),"?")) -> Déductible | J11: =IF(E11="","",IFERROR(INDEX(Catégories!$D$5:$D$60,MATCH(E11,Catégories!$A$5:$A$60,0)),"?")) -> Frais de gestion | K11: =IF(H11="Recette",G11,IF(H11="Dépense",-G11,0)) -> -5.6 | L11: =IF(E11="",0,G11*IFERROR(INDEX(Catégories!$E$5:$E$60,MATCH(E11,Catégories!$A$5:$A$60,0)),0)) -> -5.6 | M11: Bien/04_Agence/2024-05_2026-11_AGENCE_Grand-livre-proprietaire.pdf | N11: Grand livre agence
A12: 45427 | B12: =IF(A12="","",YEAR(A12)) -> 2024 | C12: APPART-01 | D12: Agence | E12: Provisions sur charges | F12: PROVISIONS CHARGES (18/05/2024 - 31/05/2024) | G12: 37.8 | H12: =IF(E12="","",IFERROR(INDEX(Catégories!$B$5:$B$60,MATCH(E12,Catégories!$A$5:$A$60,0)),"?")) -> Recette | I12: =IF(E12="","",IFERROR(INDEX(Catégories!$C$5:$C$60,MATCH(E12,Catégories!$A$5:$A$60,0)),"?")) -> Imposable | J12: =IF(E12="","",IFERROR(INDEX(Catégories!$D$5:$D$60,MATCH(E12,Catégories!$A$5:$A$60,0)),"?")) -> Charges refacturées | K12: =IF(H12="Recette",G12,IF(H12="Dépense",-G12,0)) -> 37.8 | L12: =IF(E12="",0,G12*IFERROR(INDEX(Catégories!$E$5:$E$60,MATCH(E12,Catégories!$A$5:$A$60,0)),0)) -> 37.8 | M12: Bien/04_Agence/2024-05_2026-11_AGENCE_Grand-livre-proprietaire.pdf | N12: Grand livre agence
A13: 45427 | B13: =IF(A13="","",YEAR(A13)) -> 2024 | C13: APPART-01 | D13: Agence | E13: Honoraires de gestion | F13: HONORAIRES GESTION PROVISIONS CHARGES 6.00% | G13: 2.27 | H13: =IF(E13="","",IFERROR(INDEX(Catégories!$B$5:$B$60,MATCH(E13,Catégories!$A$5:$A$60,0)),"?")) -> Dépense | I13: =IF(E13="","",IFERROR(INDEX(Catégories!$C$5:$C$60,MATCH(E13,Catégories!$A$5:$A$60,0)),"?")) -> Déductible | J13: =IF(E13="","",IFERROR(INDEX(Catégories!$D$5:$D$60,MATCH(E13,Catégories!$A$5:$A$60,0)),"?")) -> Frais de gestion | K13: =IF(H13="Recette",G13,IF(H13="Dépense",-G13,0)) -> -2.27 | L13: =IF(E13="",0,G13*IFERROR(INDEX(Catégories!$E$5:$E$60,MATCH(E13,Catégories!$A$5:$A$60,0)),0)) -> -2.27 | M13: Bien/04_Agence/2024-05_2026-11_AGENCE_Grand-livre-proprietaire.pdf | N13: Grand livre agence
A14: 45427 | B14: =IF(A14="","",YEAR(A14)) -> 2024 | C14: APPART-01 | D14: Agence | E14: Honoraires de gestion | F14: TVA HONORAIRES GESTION PROVISIONS CHARGES | G14: 0.46 | H14: =IF(E14="","",IFERROR(INDEX(Catégories!$B$5:$B$60,MATCH(E14,Catégories!$A$5:$A$60,0)),"?")) -> Dépense | I14: =IF(E14="","",IFERROR(INDEX(Catégories!$C$5:$C$60,MATCH(E14,Catégories!$A$5:$A$60,0)),"?")) -> Déductible | J14: =IF(E14="","",IFERROR(INDEX(Catégories!$D$5:$D$60,MATCH(E14,Catégories!$A$5:$A$60,0)),"?")) -> Frais de gestion | K14: =IF(H14="Recette",G14,IF(H14="Dépense",-G14,0)) -> -0.46 | L14: =IF(E14="",0,G14*IFERROR(INDEX(Catégories!$E$5:$E$60,MATCH(E14,Catégories!$A$5:$A$60,0)),0)) -> -0.46 | M14: Bien/04_Agence/2024-05_2026-11_AGENCE_Grand-livre-proprietaire.pdf | N14: Grand livre agence
A15: 45427 | B15: =IF(A15="","",YEAR(A15)) -> 2024 | C15: APPART-01 | D15: Agence | E15: Dépôt de garantie restitué | F15: DEPOT DE GARANTIE LOCATAIRE - debit | G15: 2064.6 | H15: =IF(E15="","",IFERROR(INDEX(Catégories!$B$5:$B$60,MATCH(E15,Catégories!$A$5:$A$60,0)),"?")) -> Neutre | I15: =IF(E15="","",IFERROR(INDEX(Catégories!$C$5:$C$60,MATCH(E15,Catégories!$A$5:$A$60,0)),"?")) -> Non fiscal | J15: =IF(E15="","",IFERROR(INDEX(Catégories!$D$5:$D$60,MATCH(E15,Catégories!$A$5:$A$60,0)),"?")) -> Dépôt de garantie | K15: =IF(H15="Recette",G15,IF(H15="Dépense",-G15,0)) -> 0 | L15: =IF(E15="",0,G15*IFERROR(INDEX(Catégories!$E$5:$E$60,MATCH(E15,Catégories!$A$5:$A$60,0)),0)) -> -2064.6 | M15: Bien/04_Agence/2024-05_2026-11_AGENCE_Grand-livre-proprietaire.pdf | N15: Grand livre agence | O15: Écriture de passage à l'agence (le dépôt a été versé directement au propriétaire)
A16: 45427 | B16: =IF(A16="","",YEAR(A16)) -> 2024 | C16: APPART-01 | D16: Agence | E16: Dépôt de garantie reçu | F16: DEPOT GARANTIE PROPRIETAIRE/LOCATAIRE - credit | G16: 2064.6 | H16: =IF(E16="","",IFERROR(INDEX(Catégories!$B$5:$B$60,MATCH(E16,Catégories!$A$5:$A$60,0)),"?")) -> Neutre | I16: =IF(E16="","",IFERROR(INDEX(Catégories!$C$5:$C$60,MATCH(E16,Catégories!$A$5:$A$60,0)),"?")) -> Non fiscal | J16: =IF(E16="","",IFERROR(INDEX(Catégories!$D$5:$D$60,MATCH(E16,Catégories!$A$5:$A$60,0)),"?")) -> Dépôt de garantie | K16: =IF(H16="Recette",G16,IF(H16="Dépense",-G16,0)) -> 0 | L16: =IF(E16="",0,G16*IFERROR(INDEX(Catégories!$E$5:$E$60,MATCH(E16,Catégories!$A$5:$A$60,0)),0)) -> 2064.6 | M16: Bien/04_Agence/2024-05_2026-11_AGENCE_Grand-livre-proprietaire.pdf | N16: Grand livre agence | O16: Écriture de passage à l'agence (le dépôt a été versé directement au propriétaire)
A17: 45427 | B17: =IF(A17="","",YEAR(A17)) -> 2024 | C17: APPART-01 | D17: Banque | E17: Dépôt de garantie reçu | F17: VIR INST LOCATAIRE DEPOT DE GARANTIE LOCATAIRE | G17: 2064.6 | H17: =IF(E17="","",IFERROR(INDEX(Catégories!$B$5:$B$60,MATCH(E17,Catégories!$A$5:$A$60,0)),"?")) -> Neutre | I17: =IF(E17="","",IFERROR(INDEX(Catégories!$C$5:$C$60,MATCH(E17,Catégories!$A$5:$A$60,0)),"?")) -> Non fiscal | J17: =IF(E17="","",IFERROR(INDEX(Catégories!$D$5:$D$60,MATCH(E17,Catégories!$A$5:$A$60,0)),"?")) -> Dépôt de garantie | K17: =IF(H17="Recette",G17,IF(H17="Dépense",-G17,0)) -> 0 | L17: =IF(E17="",0,G17*IFERROR(INDEX(Catégories!$E$5:$E$60,MATCH(E17,Catégories!$A$5:$A$60,0)),0)) -> 2064.6 | M17: Banque/Banque_Exempleville_Revenus-Depenses_2024-2026.xlsx | N17: Relevé BANQUE | O17: Dépôt de garantie versé directement par le locataire : à restituer à son départ
A18: 45427 | B18: =IF(A18="","",YEAR(A18)) -> 2024 | C18: APPART-01 | D18: Banque | E18: À qualifier | F18: VIR SEPA FACTURE - | G18: 395.25 | H18: =IF(E18="","",IFERROR(INDEX(Catégories!$B$5:$B$60,MATCH(E18,Catégories!$A$5:$A$60,0)),"?")) -> Dépense | I18: =IF(E18="","",IFERROR(INDEX(Catégories!$C$5:$C$60,MATCH(E18,Catégories!$A$5:$A$60,0)),"?")) -> À valider | J18: =IF(E18="","",IFERROR(INDEX(Catégories!$D$5:$D$60,MATCH(E18,Catégories!$A$5:$A$60,0)),"?")) -> À qualifier | K18: =IF(H18="Recette",G18,IF(H18="Dépense",-G18,0)) -> -395.25 | L18: =IF(E18="",0,G18*IFERROR(INDEX(Catégories!$E$5:$E$60,MATCH(E18,Catégories!$A$5:$A$60,0)),0)) -> -395.25 | M18: Banque/Banque_Exempleville_Revenus-Depenses_2024-2026.xlsx | N18: Relevé BANQUE | O18: Volet du Velux refait avant la location. Non repris par le comptable en 2024 : à lui soumettre (charge ou immobilisation)
A19: 45446 | B19: =IF(A19="","",YEAR(A19)) -> 2024 | C19: APPART-01 | D19: Agence | E19: Loyer hors charges | F19: LOYER PRINCIPAL (01/06/2024 - 30/06/2024) | G19: 1032.3 | H19: =IF(E19="","",IFERROR(INDEX(Catégories!$B$5:$B$60,MATCH(E19,Catégories!$A$5:$A$60,0)),"?")) -> Recette | I19: =IF(E19="","",IFERROR(INDEX(Catégories!$C$5:$C$60,MATCH(E19,Catégories!$A$5:$A$60,0)),"?")) -> Imposable | J19: =IF(E19="","",IFERROR(INDEX(Catégories!$D$5:$D$60,MATCH(E19,Catégories!$A$5:$A$60,0)),"?")) -> Loyers | K19: =IF(H19="Recette",G19,IF(H19="Dépense",-G19,0)) -> 1032.3 | L19: =IF(E19="",0,G19*IFERROR(INDEX(Catégories!$E$5:$E$60,MATCH(E19,Catégories!$A$5:$A$60,0)),0)) -> 1032.3 | M19: Bien/04_Agence/2024-05_2026-11_AGENCE_Grand-livre-proprietaire.pdf | N19: Grand livre agence
A20: 45446 | B20: =IF(A20="","",YEAR(A20)) -> 2024 | C20: APPART-01 | D20: Agence | E20: Honoraires de gestion | F20: HONORAIRES GESTION LOYER PRINCIPAL 6.00% | G20: 61.94 | H20: =IF(E20="","",IFERROR(INDEX(Catégories!$B$5:$B$60,MATCH(E20,Catégories!$A$5:$A$60,0)),"?")) -> Dépense | I20: =IF(E20="","",IFERROR(INDEX(Catégories!$C$5:$C$60,MATCH(E20,Catégories!$A$5:$A$60,0)),"?")) -> Déductible | J20: =IF(E20="","",IFERROR(INDEX(Catégories!$D$5:$D$60,MATCH(E20,Catégories!$A$5:$A$60,0)),"?")) -> Frais de gestion | K20: =IF(H20="Recette",G20,IF(H20="Dépense",-G20,0)) -> -61.94 | L20: =IF(E20="",0,G20*IFERROR(INDEX(Catégories!$E$5:$E$60,MATCH(E20,Catégories!$A$5:$A$60,0)),0)) -> -61.94 | M20: Bien/04_Agence/2024-05_2026-11_AGENCE_Grand-livre-proprietaire.pdf | N20: Grand livre agence
A21: 45446 | B21: =IF(A21="","",YEAR(A21)) -> 2024 | C21: APPART-01 | D21: Agence | E21: Honoraires de gestion | F21: TVA HONORAIRES GESTION LOYER PRINCIPAL | G21: 12.39 | H21: =IF(E21="","",IFERROR(INDEX(Catégories!$B$5:$B$60,MATCH(E21,Catégories!$A$5:$A$60,0)),"?")) -> Dépense | I21: =IF(E21="","",IFERROR(INDEX(Catégories!$C$5:$C$60,MATCH(E21,Catégories!$A$5:$A$60,0)),"?")) -> Déductible | J21: =IF(E21="","",IFERROR(INDEX(Catégories!$D$5:$D$60,MATCH(E21,Catégories!$A$5:$A$60,0)),"?")) -> Frais de gestion | K21: =IF(H21="Recette",G21,IF(H21="Dépense",-G21,0)) -> -12.39 | L21: =IF(E21="",0,G21*IFERROR(INDEX(Catégories!$E$5:$E$60,MATCH(E21,Catégories!$A$5:$A$60,0)),0)) -> -12.39 | M21: Bien/04_Agence/2024-05_2026-11_AGENCE_Grand-livre-proprietaire.pdf | N21: Grand livre agence
A22: 45446 | B22: =IF(A22="","",YEAR(A22)) -> 2024 | C22: APPART-01 | D22: Agence | E22: Provisions sur charges | F22: PROVISIONS CHARGES (01/06/2024 - 30/06/2024) | G22: 83.7 | H22: =IF(E22="","",IFERROR(INDEX(Catégories!$B$5:$B$60,MATCH(E22,Catégories!$A$5:$A$60,0)),"?")) -> Recette | I22: =IF(E22="","",IFERROR(INDEX(Catégories!$C$5:$C$60,MATCH(E22,Catégories!$A$5:$A$60,0)),"?")) -> Imposable | J22: =IF(E22="","",IFERROR(INDEX(Catégories!$D$5:$D$60,MATCH(E22,Catégories!$A$5:$A$60,0)),"?")) -> Charges refacturées | K22: =IF(H22="Recette",G22,IF(H22="Dépense",-G22,0)) -> 83.7 | L22: =IF(E22="",0,G22*IFERROR(INDEX(Catégories!$E$5:$E$60,MATCH(E22,Catégories!$A$5:$A$60,0)),0)) -> 83.7 | M22: Bien/04_Agence/2024-05_2026-11_AGENCE_Grand-livre-proprietaire.pdf | N22: Grand livre agence
A23: 45446 | B23: =IF(A23="","",YEAR(A23)) -> 2024 | C23: APPART-01 | D23: Agence | E23: Honoraires de gestion | F23: HONORAIRES GESTION PROVISIONS CHARGES 6.00% | G23: 5.02 | H23: =IF(E23="","",IFERROR(INDEX(Catégories!$B$5:$B$60,MATCH(E23,Catégories!$A$5:$A$60,0)),"?")) -> Dépense | I23: =IF(E23="","",IFERROR(INDEX(Catégories!$C$5:$C$60,MATCH(E23,Catégories!$A$5:$A$60,0)),"?")) -> Déductible | J23: =IF(E23="","",IFERROR(INDEX(Catégories!$D$5:$D$60,MATCH(E23,Catégories!$A$5:$A$60,0)),"?")) -> Frais de gestion | K23: =IF(H23="Recette",G23,IF(H23="Dépense",-G23,0)) -> -5.02 | L23: =IF(E23="",0,G23*IFERROR(INDEX(Catégories!$E$5:$E$60,MATCH(E23,Catégories!$A$5:$A$60,0)),0)) -> -5.02 | M23: Bien/04_Agence/2024-05_2026-11_AGENCE_Grand-livre-proprietaire.pdf | N23: Grand livre agence
A24: 45446 | B24: =IF(A24="","",YEAR(A24)) -> 2024 | C24: APPART-01 | D24: Agence | E24: Honoraires de gestion | F24: TVA HONORAIRES GESTION PROVISIONS CHARGES | G24: 1 | H24: =IF(E24="","",IFERROR(INDEX(Catégories!$B$5:$B$60,MATCH(E24,Catégories!$A$5:$A$60,0)),"?")) -> Dépense | I24: =IF(E24="","",IFERROR(INDEX(Catégories!$C$5:$C$60,MATCH(E24,Catégories!$A$5:$A$60,0)),"?")) -> Déductible | J24: =IF(E24="","",IFERROR(INDEX(Catégories!$D$5:$D$60,MATCH(E24,Catégories!$A$5:$A$60,0)),"?")) -> Frais de gestion | K24: =IF(H24="Recette",G24,IF(H24="Dépense",-G24,0)) -> -1 | L24: =IF(E24="",0,G24*IFERROR(INDEX(Catégories!$E$5:$E$60,MATCH(E24,Catégories!$A$5:$A$60,0)),0)) -> -1 | M24: Bien/04_Agence/2024-05_2026-11_AGENCE_Grand-livre-proprietaire.pdf | N24: Grand livre agence
A25: 45446 | B25: =IF(A25="","",YEAR(A25)) -> 2024 | C25: APPART-01 | D25: Agence | E25: Honoraires sur travaux | F25: HONORAIRES GESTION SUR TRAVAUX 3%TTC | G25: 6.4 | H25: =IF(E25="","",IFERROR(INDEX(Catégories!$B$5:$B$60,MATCH(E25,Catégories!$A$5:$A$60,0)),"?")) -> Dépense | I25: =IF(E25="","",IFERROR(INDEX(Catégories!$C$5:$C$60,MATCH(E25,Catégories!$A$5:$A$60,0)),"?")) -> Déductible | J25: =IF(E25="","",IFERROR(INDEX(Catégories!$D$5:$D$60,MATCH(E25,Catégories!$A$5:$A$60,0)),"?")) -> Frais de gestion | K25: =IF(H25="Recette",G25,IF(H25="Dépense",-G25,0)) -> -6.4 | L25: =IF(E25="",0,G25*IFERROR(INDEX(Catégories!$E$5:$E$60,MATCH(E25,Catégories!$A$5:$A$60,0)),0)) -> -6.4 | M25: Bien/04_Agence/2024-05_2026-11_AGENCE_Grand-livre-proprietaire.pdf | N25: Grand livre agence
A26: 45446 | B26: =IF(A26="","",YEAR(A26)) -> 2024 | C26: APPART-01 | D26: Agence | E26: Honoraires sur travaux | F26: TVA HONORAIRES GESTION SUR TRAVAUX 3%TTC | G26: 1.27 | H26: =IF(E26="","",IFERROR(INDEX(Catégories!$B$5:$B$60,MATCH(E26,Catégories!$A$5:$A$60,0)),"?")) -> Dépense | I26: =IF(E26="","",IFERROR(INDEX(Catégories!$C$5:$C$60,MATCH(E26,Catégories!$A$5:$A$60,0)),"?")) -> Déductible | J26: =IF(E26="","",IFERROR(INDEX(Catégories!$D$5:$D$60,MATCH(E26,Catégories!$A$5:$A$60,0)),"?")) -> Frais de gestion | K26: =IF(H26="Recette",G26,IF(H26="Dépense",-G26,0)) -> -1.27 | L26: =IF(E26="",0,G26*IFERROR(INDEX(Catégories!$E$5:$E$60,MATCH(E26,Catégories!$A$5:$A$60,0)),0)) -> -1.27 | M26: Bien/04_Agence/2024-05_2026-11_AGENCE_Grand-livre-proprietaire.pdf | N26: Grand livre agence
A27: 45446 | B27: =IF(A27="","",YEAR(A27)) -> 2024 | C27: APPART-01 | D27: Agence | E27: Entretien et réparations | F27: ROBINET CUISINE + PORTE CHAMBRE ARTISAN D | G27: 255.75 | H27: =IF(E27="","",IFERROR(INDEX(Catégories!$B$5:$B$60,MATCH(E27,Catégories!$A$5:$A$60,0)),"?")) -> Dépense | I27: =IF(E27="","",IFERROR(INDEX(Catégories!$C$5:$C$60,MATCH(E27,Catégories!$A$5:$A$60,0)),"?")) -> Déductible | J27: =IF(E27="","",IFERROR(INDEX(Catégories!$D$5:$D$60,MATCH(E27,Catégories!$A$5:$A$60,0)),"?")) -> Entretien et petit équipement | K27: =IF(H27="Recette",G27,IF(H27="Dépense",-G27,0)) -> -255.75 | L27: =IF(E27="",0,G27*IFERROR(INDEX(Catégories!$E$5:$E$60,MATCH(E27,Catégories!$A$5:$A$60,0)),0)) -> -255.75 | M27: Bien/04_Agence/2024-05_2026-11_AGENCE_Grand-livre-proprietaire.pdf | N27: Grand livre agence
A28: 45448 | B28: =IF(A28="","",YEAR(A28)) -> 2024 | C28: APPART-01 | D28: Agence | E28: Entretien et réparations | F28: reparation lave-linge ARTISAN C | G28: 109.74 | H28: =IF(E28="","",IFERROR(INDEX(Catégories!$B$5:$B$60,MATCH(E28,Catégories!$A$5:$A$60,0)),"?")) -> Dépense | I28: =IF(E28="","",IFERROR(INDEX(Catégories!$C$5:$C$60,MATCH(E28,Catégories!$A$5:$A$60,0)),"?")) -> Déductible | J28: =IF(E28="","",IFERROR(INDEX(Catégories!$D$5:$D$60,MATCH(E28,Catégories!$A$5:$A$60,0)),"?")) -> Entretien et petit équipement | K28: =IF(H28="Recette",G28,IF(H28="Dépense",-G28,0)) -> -109.74 | L28: =IF(E28="",0,G28*IFERROR(INDEX(Catégories!$E$5:$E$60,MATCH(E28,Catégories!$A$5:$A$60,0)),0)) -> -109.74 | M28: Bien/04_Agence/2024-05_2026-11_AGENCE_Grand-livre-proprietaire.pdf | N28: Grand livre agence
A29: 45448 | B29: =IF(A29="","",YEAR(A29)) -> 2024 | C29: APPART-01 | D29: Agence | E29: Honoraires sur travaux | F29: HONORAIRES GESTION TRAVAUX 3% TTC (ARTISAN C) | G29: 2.74 | H29: =IF(E29="","",IFERROR(INDEX(Catégories!$B$5:$B$60,MATCH(E29,Catégories!$A$5:$A$60,0)),"?")) -> Dépense | I29: =IF(E29="","",IFERROR(INDEX(Catégories!$C$5:$C$60,MATCH(E29,Catégories!$A$5:$A$60,0)),"?")) -> Déductible | J29: =IF(E29="","",IFERROR(INDEX(Catégories!$D$5:$D$60,MATCH(E29,Catégories!$A$5:$A$60,0)),"?")) -> Frais de gestion | K29: =IF(H29="Recette",G29,IF(H29="Dépense",-G29,0)) -> -2.74 | L29: =IF(E29="",0,G29*IFERROR(INDEX(Catégories!$E$5:$E$60,MATCH(E29,Catégories!$A$5:$A$60,0)),0)) -> -2.74 | M29: Bien/04_Agence/2024-05_2026-11_AGENCE_Grand-livre-proprietaire.pdf | N29: Grand livre agence
A30: 45448 | B30: =IF(A30="","",YEAR(A30)) -> 2024 | C30: APPART-01 | D30: Agence | E30: Honoraires sur travaux | F30: TVA HONORAIRES GESTION TRAVAUX 3% TTC (ARTISAN C) | G30: 0.55 | H30: =IF(E30="","",IFERROR(INDEX(Catégories!$B$5:$B$60,MATCH(E30,Catégories!$A$5:$A$60,0)),"?")) -> Dépense | I30: =IF(E30="","",IFERROR(INDEX(Catégories!$C$5:$C$60,MATCH(E30,Catégories!$A$5:$A$60,0)),"?")) -> Déductible | J30: =IF(E30="","",IFERROR(INDEX(Catégories!$D$5:$D$60,MATCH(E30,Catégories!$A$5:$A$60,0)),"?")) -> Frais de gestion | K30: =IF(H30="Recette",G30,IF(H30="Dépense",-G30,0)) -> -0.55 | L30: =IF(E30="",0,G30*IFERROR(INDEX(Catégories!$E$5:$E$60,MATCH(E30,Catégories!$A$5:$A$60,0)),0)) -> -0.55 | M30: Bien/04_Agence/2024-05_2026-11_AGENCE_Grand-livre-proprietaire.pdf | N30: Grand livre agence
... A33: 45449 | B33: =IF(A33="","",YEAR(A33)) -> 2024 | C33: APPART-01 | D33: Agence | E33: Transfert sortant | F33: Virement de l'agence au propriétaire | G33: 480.09 | H33: =IF(E33="","",IFERROR(INDEX(Catégories!$B$5:$B$60,MATCH(E33,Catégories!$A$5:$A$60,0)),"?")) -> Transfert | I33: =IF(E33="","",IFERROR(INDEX(Catégories!$C$5:$C$60,MATCH(E33,Catégories!$A$5:$A$60,0)),"?")) -> Non fiscal | J33: =IF(E33="","",IFERROR(INDEX(Catégories!$D$5:$D$60,MATCH(E33,Catégories!$A$5:$A$60,0)),"?")) -> Mouvements internes | K33: =IF(H33="Recette",G33,IF(H33="Dépense",-G33,0)) -> 0 | L33: =IF(E33="",0,G33*IFERROR(INDEX(Catégories!$E$5:$E$60,MATCH(E33,Catégories!$A$5:$A$60,0)),0)) -> -480.09 | M33: Bien/04_Agence/2024-05_2026-11_AGENCE_Grand-livre-proprietaire.pdf | N33: Grand livre agence
A34: 45450 | B34: =IF(A34="","",YEAR(A34)) -> 2024 | C34: APPART-01 | D34: Banque | E34: Équipement / mobilier (à amortir) | F34: VIR SEPA DEVIS FRIGO NEUF | G34: 1076.01 | H34: =IF(E34="","",IFERROR(INDEX(Catégories!$B$5:$B$60,MATCH(E34,Catégories!$A$5:$A$60,0)),"?")) -> Dépense | I34: =IF(E34="","",IFERROR(INDEX(Catégories!$C$5:$C$60,MATCH(E34,Catégories!$A$5:$A$60,0)),"?")) -> À amortir | J34: =IF(E34="","",IFERROR(INDEX(Catégories!$D$5:$D$60,MATCH(E34,Catégories!$A$5:$A$60,0)),"?")) -> Investissements | K34: =IF(H34="Recette",G34,IF(H34="Dépense",-G34,0)) -> -1076.01 | L34: =IF(E34="",0,G34*IFERROR(INDEX(Catégories!$E$5:$E$60,MATCH(E34,Catégories!$A$5:$A$60,0)),0)) -> -1076.01 | M34: Banque/Banque_Exempleville_Revenus-Depenses_2024-2026.xlsx | N34: Relevé BANQUE | O34: Réfrigérateur, immobilisé par le comptable
A35: 45450 | B35: =IF(A35="","",YEAR(A35)) -> 2024 | C35: APPART-01 | D35: Banque | E35: Petit équipement | F35: VIR SEPA EXEMPLEVILLE - REPARATION FR | G35: 88.35 | H35: =IF(E35="","",IFERROR(INDEX(Catégories!$B$5:$B$60,MATCH(E35,Catégories!$A$5:$A$60,0)),"?")) -> Dépense | I35: =IF(E35="","",IFERROR(INDEX(Catégories!$C$5:$C$60,MATCH(E35,Catégories!$A$5:$A$60,0)),"?")) -> Déductible | J35: =IF(E35="","",IFERROR(INDEX(Catégories!$D$5:$D$60,MATCH(E35,Catégories!$A$5:$A$60,0)),"?")) -> Entretien et petit équipement | K35: =IF(H35="Recette",G35,IF(H35="Dépense",-G35,0)) -> -88.35 | L35: =IF(E35="",0,G35*IFERROR(INDEX(Catégories!$E$5:$E$60,MATCH(E35,Catégories!$A$5:$A$60,0)),0)) -> -88.35 | M35: Banque/Banque_Exempleville_Revenus-Depenses_2024-2026.xlsx | N35: Relevé BANQUE | O35: Passé en petit équipement par le comptable
A36: 45475 | B36: =IF(A36="","",YEAR(A36)) -> 2024 | C36: APPART-01 | D36: Agence | E36: Loyer hors charges | F36: LOYER PRINCIPAL (01/07/2024 - 31/07/2024) | G36: 1032.3 | H36: =IF(E36="","",IFERROR(INDEX(Catégories!$B$5:$B$60,MATCH(E36,Catégories!$A$5:$A$60,0)),"?")) -> Recette | I36: =IF(E36="","",IFERROR(INDEX(Catégories!$C$5:$C$60,MATCH(E36,Catégories!$A$5:$A$60,0)),"?")) -> Imposable | J36: =IF(E36="","",IFERROR(INDEX(Catégories!$D$5:$D$60,MATCH(E36,Catégories!$A$5:$A$60,0)),"?")) -> Loyers | K36: =IF(H36="Recette",G36,IF(H36="Dépense",-G36,0)) -> 1032.3 | L36: =IF(E36="",0,G36*IFERROR(INDEX(Catégories!$E$5:$E$60,MATCH(E36,Catégories!$A$5:$A$60,0)),0)) -> 1032.3 | M36: Bien/04_Agence/2024-05_2026-11_AGENCE_Grand-livre-proprietaire.pdf | N36: Grand livre agence
A37: 45475 | B37: =IF(A37="","",YEAR(A37)) -> 2024 | C37: APPART-01 | D37: Agence | E37: Honoraires de gestion | F37: HONORAIRES GESTION LOYER PRINCIPAL 6.00% | G37: 61.94 | H37: =IF(E37="","",IFERROR(INDEX(Catégories!$B$5:$B$60,MATCH(E37,Catégories!$A$5:$A$60,0)),"?")) -> Dépense | I37: =IF(E37="","",IFERROR(INDEX(Catégories!$C$5:$C$60,MATCH(E37,Catégories!$A$5:$A$60,0)),"?")) -> Déductible | J37: =IF(E37="","",IFERROR(INDEX(Catégories!$D$5:$D$60,MATCH(E37,Catégories!$A$5:$A$60,0)),"?")) -> Frais de gestion | K37: =IF(H37="Recette",G37,IF(H37="Dépense",-G37,0)) -> -61.94 | L37: =IF(E37="",0,G37*IFERROR(INDEX(Catégories!$E$5:$E$60,MATCH(E37,Catégories!$A$5:$A$60,0)),0)) -> -61.94 | M37: Bien/04_Agence/2024-05_2026-11_AGENCE_Grand-livre-proprietaire.pdf | N37: Grand livre agence
A38: 45475 | B38: =IF(A38="","",YEAR(A38)) -> 2024 | C38: APPART-01 | D38: Agence | E38: Honoraires de gestion | F38: TVA HONORAIRES GESTION LOYER PRINCIPAL | G38: 12.39 | H38: =IF(E38="","",IFERROR(INDEX(Catégories!$B$5:$B$60,MATCH(E38,Catégories!$A$5:$A$60,0)),"?")) -> Dépense | I38: =IF(E38="","",IFERROR(INDEX(Catégories!$C$5:$C$60,MATCH(E38,Catégories!$A$5:$A$60,0)),"?")) -> Déductible | J38: =IF(E38="","",IFERROR(INDEX(Catégories!$D$5:$D$60,MATCH(E38,Catégories!$A$5:$A$60,0)),"?")) -> Frais de gestion | K38: =IF(H38="Recette",G38,IF(H38="Dépense",-G38,0)) -> -12.39 | L38: =IF(E38="",0,G38*IFERROR(INDEX(Catégories!$E$5:$E$60,MATCH(E38,Catégories!$A$5:$A$60,0)),0)) -> -12.39 | M38: Bien/04_Agence/2024-05_2026-11_AGENCE_Grand-livre-proprietaire.pdf | N38: Grand livre agence
A39: 45475 | B39: =IF(A39="","",YEAR(A39)) -> 2024 | C39: APPART-01 | D39: Agence | E39: Provisions sur charges | F39: PROVISIONS CHARGES (01/07/2024 - 31/07/2024) | G39: 83.7 | H39: =IF(E39="","",IFERROR(INDEX(Catégories!$B$5:$B$60,MATCH(E39,Catégories!$A$5:$A$60,0)),"?")) -> Recette | I39: =IF(E39="","",IFERROR(INDEX(Catégories!$C$5:$C$60,MATCH(E39,Catégories!$A$5:$A$60,0)),"?")) -> Imposable | J39: =IF(E39="","",IFERROR(INDEX(Catégories!$D$5:$D$60,MATCH(E39,Catégories!$A$5:$A$60,0)),"?")) -> Charges refacturées | K39: =IF(H39="Recette",G39,IF(H39="Dépense",-G39,0)) -> 83.7 | L39: =IF(E39="",0,G39*IFERROR(INDEX(Catégories!$E$5:$E$60,MATCH(E39,Catégories!$A$5:$A$60,0)),0)) -> 83.7 | M39: Bien/04_Agence/2024-05_2026-11_AGENCE_Grand-livre-proprietaire.pdf | N39: Grand livre agence
A40: 45475 | B40: =IF(A40="","",YEAR(A40)) -> 2024 | C40: APPART-01 | D40: Agence | E40: Honoraires de gestion | F40: HONORAIRES GESTION PROVISIONS CHARGES 6.00% | G40: 5.02 | H40: =IF(E40="","",IFERROR(INDEX(Catégories!$B$5:$B$60,MATCH(E40,Catégories!$A$5:$A$60,0)),"?")) -> Dépense | I40: =IF(E40="","",IFERROR(INDEX(Catégories!$C$5:$C$60,MATCH(E40,Catégories!$A$5:$A$60,0)),"?")) -> Déductible | J40: =IF(E40="","",IFERROR(INDEX(Catégories!$D$5:$D$60,MATCH(E40,Catégories!$A$5:$A$60,0)),"?")) -> Frais de gestion | K40: =IF(H40="Recette",G40,IF(H40="Dépense",-G40,0)) -> -5.02 | L40: =IF(E40="",0,G40*IFERROR(INDEX(Catégories!$E$5:$E$60,MATCH(E40,Catégories!$A$5:$A$60,0)),0)) -> -5.02 | M40: Bien/04_Agence/2024-05_2026-11_AGENCE_Grand-livre-proprietaire.pdf | N40: Grand livre agence
A41: 45475 | B41: =IF(A41="","",YEAR(A41)) -> 2024 | C41: APPART-01 | D41: Agence | E41: Honoraires de gestion | F41: TVA HONORAIRES GESTION PROVISIONS CHARGES | G41: 1 | H41: =IF(E41="","",IFERROR(INDEX(Catégories!$B$5:$B$60,MATCH(E41,Catégories!$A$5:$A$60,0)),"?")) -> Dépense | I41: =IF(E41="","",IFERROR(INDEX(Catégories!$C$5:$C$60,MATCH(E41,Catégories!$A$5:$A$60,0)),"?")) -> Déductible | J41: =IF(E41="","",IFERROR(INDEX(Catégories!$D$5:$D$60,MATCH(E41,Catégories!$A$5:$A$60,0)),"?")) -> Frais de gestion | K41: =IF(H41="Recette",G41,IF(H41="Dépense",-G41,0)) -> -1 | L41: =IF(E41="",0,G41*IFERROR(INDEX(Catégories!$E$5:$E$60,MATCH(E41,Catégories!$A$5:$A$60,0)),0)) -> -1 | M41: Bien/04_Agence/2024-05_2026-11_AGENCE_Grand-livre-proprietaire.pdf | N41: Grand livre agence
A42: 45475 | B42: =IF(A42="","",YEAR(A42)) -> 2024 | C42: APPART-01 | D42: Agence | E42: Transfert sortant | F42: Virement de l'agence au propriétaire | G42: 1035.65 | H42: =IF(E42="","",IFERROR(INDEX(Catégories!$B$5:$B$60,MATCH(E42,Catégories!$A$5:$A$60,0)),"?")) -> Transfert | I42: =IF(E42="","",IFERROR(INDEX(Catégories!$C$5:$C$60,MATCH(E42,Catégories!$A$5:$A$60,0)),"?")) -> Non fiscal | J42: =IF(E42="","",IFERROR(INDEX(Catégories!$D$5:$D$60,MATCH(E42,Catégories!$A$5:$A$60,0)),"?")) -> Mouvements internes | K42: =IF(H42="Recette",G42,IF(H42="Dépense",-G42,0)) -> 0 | L42: =IF(E42="",0,G42*IFERROR(INDEX(Catégories!$E$5:$E$60,MATCH(E42,Catégories!$A$5:$A$60,0)),0)) -> -1035.65 | M42: Bien/04_Agence/2024-05_2026-11_AGENCE_Grand-livre-proprietaire.pdf | N42: Grand livre agence
A43: 45506 | B43: =IF(A43="","",YEAR(A43)) -> 2024 | C43: APPART-01 | D43: Agence | E43: Loyer hors charges | F43: LOYER PRINCIPAL (01/08/2024 - 31/08/2024) | G43: 1032.3 | H43: =IF(E43="","",IFERROR(INDEX(Catégories!$B$5:$B$60,MATCH(E43,Catégories!$A$5:$A$60,0)),"?")) -> Recette | I43: =IF(E43="","",IFERROR(INDEX(Catégories!$C$5:$C$60,MATCH(E43,Catégories!$A$5:$A$60,0)),"?")) -> Imposable | J43: =IF(E43="","",IFERROR(INDEX(Catégories!$D$5:$D$60,MATCH(E43,Catégories!$A$5:$A$60,0)),"?")) -> Loyers | K43: =IF(H43="Recette",G43,IF(H43="Dépense",-G43,0)) -> 1032.3 | L43: =IF(E43="",0,G43*IFERROR(INDEX(Catégories!$E$5:$E$60,MATCH(E43,Catégories!$A$5:$A$60,0)),0)) -> 1032.3 | M43: Bien/04_Agence/2024-05_2026-11_AGENCE_Grand-livre-proprietaire.pdf | N43: Grand livre agence
A44: 45506 | B44: =IF(A44="","",YEAR(A44)) -> 2024 | C44: APPART-01 | D44: Agence | E44: Honoraires de gestion | F44: HONORAIRES GESTION LOYER PRINCIPAL 6.00% | G44: 61.94 | H44: =IF(E44="","",IFERROR(INDEX(Catégories!$B$5:$B$60,MATCH(E44,Catégories!$A$5:$A$60,0)),"?")) -> Dépense | I44: =IF(E44="","",IFERROR(INDEX(Catégories!$C$5:$C$60,MATCH(E44,Catégories!$A$5:$A$60,0)),"?")) -> Déductible | J44: =IF(E44="","",IFERROR(INDEX(Catégories!$D$5:$D$60,MATCH(E44,Catégories!$A$5:$A$60,0)),"?")) -> Frais de gestion | K44: =IF(H44="Recette",G44,IF(H44="Dépense",-G44,0)) -> -61.94 | L44: =IF(E44="",0,G44*IFERROR(INDEX(Catégories!$E$5:$E$60,MATCH(E44,Catégories!$A$5:$A$60,0)),0)) -> -61.94 | M44: Bien/04_Agence/2024-05_2026-11_AGENCE_Grand-livre-proprietaire.pdf | N44: Grand livre agence
A45: 45506 | B45: =IF(A45="","",YEAR(A45)) -> 2024 | C45: APPART-01 | D45: Agence | E45: Honoraires de gestion | F45: TVA HONORAIRES GESTION LOYER PRINCIPAL | G45: 12.39 | H45: =IF(E45="","",IFERROR(INDEX(Catégories!$B$5:$B$60,MATCH(E45,Catégories!$A$5:$A$60,0)),"?")) -> Dépense | I45: =IF(E45="","",IFERROR(INDEX(Catégories!$C$5:$C$60,MATCH(E45,Catégories!$A$5:$A$60,0)),"?")) -> Déductible | J45: =IF(E45="","",IFERROR(INDEX(Catégories!$D$5:$D$60,MATCH(E45,Catégories!$A$5:$A$60,0)),"?")) -> Frais de gestion | K45: =IF(H45="Recette",G45,IF(H45="Dépense",-G45,0)) -> -12.39 | L45: =IF(E45="",0,G45*IFERROR(INDEX(Catégories!$E$5:$E$60,MATCH(E45,Catégories!$A$5:$A$60,0)),0)) -> -12.39 | M45: Bien/04_Agence/2024-05_2026-11_AGENCE_Grand-livre-proprietaire.pdf | N45: Grand livre agence
A46: 45506 | B46: =IF(A46="","",YEAR(A46)) -> 2024 | C46: APPART-01 | D46: Agence | E46: Provisions sur charges | F46: PROVISIONS CHARGES (01/08/2024 - 31/08/2024) | G46: 83.7 | H46: =IF(E46="","",IFERROR(INDEX(Catégories!$B$5:$B$60,MATCH(E46,Catégories!$A$5:$A$60,0)),"?")) -> Recette | I46: =IF(E46="","",IFERROR(INDEX(Catégories!$C$5:$C$60,MATCH(E46,Catégories!$A$5:$A$60,0)),"?")) -> Imposable | J46: =IF(E46="","",IFERROR(INDEX(Catégories!$D$5:$D$60,MATCH(E46,Catégories!$A$5:$A$60,0)),"?")) -> Charges refacturées | K46: =IF(H46="Recette",G46,IF(H46="Dépense",-G46,0)) -> 83.7 | L46: =IF(E46="",0,G46*IFERROR(INDEX(Catégories!$E$5:$E$60,MATCH(E46,Catégories!$A$5:$A$60,0)),0)) -> 83.7 | M46: Bien/04_Agence/2024-05_2026-11_AGENCE_Grand-livre-proprietaire.pdf | N46: Grand livre agence
A47: 45506 | B47: =IF(A47="","",YEAR(A47)) -> 2024 | C47: APPART-01 | D47: Agence | E47: Honoraires de gestion | F47: HONORAIRES GESTION PROVISIONS CHARGES 6.00% | G47: 5.02 | H47: =IF(E47="","",IFERROR(INDEX(Catégories!$B$5:$B$60,MATCH(E47,Catégories!$A$5:$A$60,0)),"?")) -> Dépense | I47: =IF(E47="","",IFERROR(INDEX(Catégories!$C$5:$C$60,MATCH(E47,Catégories!$A$5:$A$60,0)),"?")) -> Déductible | J47: =IF(E47="","",IFERROR(INDEX(Catégories!$D$5:$D$60,MATCH(E47,Catégories!$A$5:$A$60,0)),"?")) -> Frais de gestion | K47: =IF(H47="Recette",G47,IF(H47="Dépense",-G47,0)) -> -5.02 | L47: =IF(E47="",0,G47*IFERROR(INDEX(Catégories!$E$5:$E$60,MATCH(E47,Catégories!$A$5:$A$60,0)),0)) -> -5.02 | M47: Bien/04_Agence/2024-05_2026-11_AGENCE_Grand-livre-proprietaire.pdf | N47: Grand livre agence
... A49: 45506 | B49: =IF(A49="","",YEAR(A49)) -> 2024 | C49: APPART-01 | D49: Agence | E49: Transfert sortant | F49: Virement de l'agence au propriétaire | G49: 1035.65 | H49: =IF(E49="","",IFERROR(INDEX(Catégories!$B$5:$B$60,MATCH(E49,Catégories!$A$5:$A$60,0)),"?")) -> Transfert | I49: =IF(E49="","",IFERROR(INDEX(Catégories!$C$5:$C$60,MATCH(E49,Catégories!$A$5:$A$60,0)),"?")) -> Non fiscal | J49: =IF(E49="","",IFERROR(INDEX(Catégories!$D$5:$D$60,MATCH(E49,Catégories!$A$5:$A$60,0)),"?")) -> Mouvements internes | K49: =IF(H49="Recette",G49,IF(H49="Dépense",-G49,0)) -> 0 | L49: =IF(E49="",0,G49*IFERROR(INDEX(Catégories!$E$5:$E$60,MATCH(E49,Catégories!$A$5:$A$60,0)),0)) -> -1035.65 | M49: Bien/04_Agence/2024-05_2026-11_AGENCE_Grand-livre-proprietaire.pdf | N49: Grand livre agence
A50: 45529 | B50: =IF(A50="","",YEAR(A50)) -> 2024 | C50: APPART-01 | D50: Banque | E50: Charges de copropriété | F50: VIR SEPA CHARGES COPRO | G50: 347.98 | H50: =IF(E50="","",IFERROR(INDEX(Catégories!$B$5:$B$60,MATCH(E50,Catégories!$A$5:$A$60,0)),"?")) -> Dépense | I50: =IF(E50="","",IFERROR(INDEX(Catégories!$C$5:$C$60,MATCH(E50,Catégories!$A$5:$A$60,0)),"?")) -> Déductible | J50: =IF(E50="","",IFERROR(INDEX(Catégories!$D$5:$D$60,MATCH(E50,Catégories!$A$5:$A$60,0)),"?")) -> Copropriété | K50: =IF(H50="Recette",G50,IF(H50="Dépense",-G50,0)) -> -347.98 | L50: =IF(E50="",0,G50*IFERROR(INDEX(Catégories!$E$5:$E$60,MATCH(E50,Catégories!$A$5:$A$60,0)),0)) -> -347.98 | M50: Bien/05_Copropriete/Appels/2024-07-02_Syndic_Appel-T3-2024.pdf | N50: Relevé BANQUE | O50: Appel T3 2024 (637,22 €) moins le crédit de régularisation 2023 (289,24 €)
A51: 45537 | B51: =IF(A51="","",YEAR(A51)) -> 2024 | C51: APPART-01 | D51: Agence | E51: Loyer hors charges | F51: LOYER PRINCIPAL (01/09/2024 - 30/09/2024) | G51: 1032.3 | H51: =IF(E51="","",IFERROR(INDEX(Catégories!$B$5:$B$60,MATCH(E51,Catégories!$A$5:$A$60,0)),"?")) -> Recette | I51: =IF(E51="","",IFERROR(INDEX(Catégories!$C$5:$C$60,MATCH(E51,Catégories!$A$5:$A$60,0)),"?")) -> Imposable | J51: =IF(E51="","",IFERROR(INDEX(Catégories!$D$5:$D$60,MATCH(E51,Catégories!$A$5:$A$60,0)),"?")) -> Loyers | K51: =IF(H51="Recette",G51,IF(H51="Dépense",-G51,0)) -> 1032.3 | L51: =IF(E51="",0,G51*IFERROR(INDEX(Catégories!$E$5:$E$60,MATCH(E51,Catégories!$A$5:$A$60,0)),0)) -> 1032.3 | M51: Bien/04_Agence/2024-05_2026-11_AGENCE_Grand-livre-proprietaire.pdf | N51: Grand livre agence
A52: 45537 | B52: =IF(A52="","",YEAR(A52)) -> 2024 | C52: APPART-01 | D52: Agence | E52: Honoraires de gestion | F52: HONORAIRES GESTION LOYER PRINCIPAL 6.00% | G52: 61.94 | H52: =IF(E52="","",IFERROR(INDEX(Catégories!$B$5:$B$60,MATCH(E52,Catégories!$A$5:$A$60,0)),"?")) -> Dépense | I52: =IF(E52="","",IFERROR(INDEX(Catégories!$C$5:$C$60,MATCH(E52,Catégories!$A$5:$A$60,0)),"?")) -> Déductible | J52: =IF(E52="","",IFERROR(INDEX(Catégories!$D$5:$D$60,MATCH(E52,Catégories!$A$5:$A$60,0)),"?")) -> Frais de gestion | K52: =IF(H52="Recette",G52,IF(H52="Dépense",-G52,0)) -> -61.94 | L52: =IF(E52="",0,G52*IFERROR(INDEX(Catégories!$E$5:$E$60,MATCH(E52,Catégories!$A$5:$A$60,0)),0)) -> -61.94 | M52: Bien/04_Agence/2024-05_2026-11_AGENCE_Grand-livre-proprietaire.pdf | N52: Grand livre agence
A53: 45537 | B53: =IF(A53="","",YEAR(A53)) -> 2024 | C53: APPART-01 | D53: Agence | E53: Honoraires de gestion | F53: TVA HONORAIRES GESTION LOYER PRINCIPAL | G53: 12.39 | H53: =IF(E53="","",IFERROR(INDEX(Catégories!$B$5:$B$60,MATCH(E53,Catégories!$A$5:$A$60,0)),"?")) -> Dépense | I53: =IF(E53="","",IFERROR(INDEX(Catégories!$C$5:$C$60,MATCH(E53,Catégories!$A$5:$A$60,0)),"?")) -> Déductible | J53: =IF(E53="","",IFERROR(INDEX(Catégories!$D$5:$D$60,MATCH(E53,Catégories!$A$5:$A$60,0)),"?")) -> Frais de gestion | K53: =IF(H53="Recette",G53,IF(H53="Dépense",-G53,0)) -> -12.39 | L53: =IF(E53="",0,G53*IFERROR(INDEX(Catégories!$E$5:$E$60,MATCH(E53,Catégories!$A$5:$A$60,0)),0)) -> -12.39 | M53: Bien/04_Agence/2024-05_2026-11_AGENCE_Grand-livre-proprietaire.pdf | N53: Grand livre agence
A54: 45537 | B54: =IF(A54="","",YEAR(A54)) -> 2024 | C54: APPART-01 | D54: Agence | E54: Provisions sur charges | F54: PROVISIONS CHARGES (01/09/2024 - 30/09/2024) | G54: 83.7 | H54: =IF(E54="","",IFERROR(INDEX(Catégories!$B$5:$B$60,MATCH(E54,Catégories!$A$5:$A$60,0)),"?")) -> Recette | I54: =IF(E54="","",IFERROR(INDEX(Catégories!$C$5:$C$60,MATCH(E54,Catégories!$A$5:$A$60,0)),"?")) -> Imposable | J54: =IF(E54="","",IFERROR(INDEX(Catégories!$D$5:$D$60,MATCH(E54,Catégories!$A$5:$A$60,0)),"?")) -> Charges refacturées | K54: =IF(H54="Recette",G54,IF(H54="Dépense",-G54,0)) -> 83.7 | L54: =IF(E54="",0,G54*IFERROR(INDEX(Catégories!$E$5:$E$60,MATCH(E54,Catégories!$A$5:$A$60,0)),0)) -> 83.7 | M54: Bien/04_Agence/2024-05_2026-11_AGENCE_Grand-livre-proprietaire.pdf | N54: Grand livre agence
A55: 45537 | B55: =IF(A55="","",YEAR(A55)) -> 2024 | C55: APPART-01 | D55: Agence | E55: Honoraires de gestion | F55: HONORAIRES GESTION PROVISIONS CHARGES 6.00% | G55: 5.02 | H55: =IF(E55="","",IFERROR(INDEX(Catégories!$B$5:$B$60,MATCH(E55,Catégories!$A$5:$A$60,0)),"?")) -> Dépense | I55: =IF(E55="","",IFERROR(INDEX(Catégories!$C$5:$C$60,MATCH(E55,Catégories!$A$5:$A$60,0)),"?")) -> Déductible | J55: =IF(E55="","",IFERROR(INDEX(Catégories!$D$5:$D$60,MATCH(E55,Catégories!$A$5:$A$60,0)),"?")) -> Frais de gestion | K55: =IF(H55="Recette",G55,IF(H55="Dépense",-G55,0)) -> -5.02 | L55: =IF(E55="",0,G55*IFERROR(INDEX(Catégories!$E$5:$E$60,MATCH(E55,Catégories!$A$5:$A$60,0)),0)) -> -5.02 | M55: Bien/04_Agence/2024-05_2026-11_AGENCE_Grand-livre-proprietaire.pdf | N55: Grand livre agence
A56: 45537 | B56: =IF(A56="","",YEAR(A56)) -> 2024 | C56: APPART-01 | D56: Agence | E56: Honoraires de gestion | F56: TVA HONORAIRES GESTION PROVISIONS CHARGES | G56: 1 | H56: =IF(E56="","",IFERROR(INDEX(Catégories!$B$5:$B$60,MATCH(E56,Catégories!$A$5:$A$60,0)),"?")) -> Dépense | I56: =IF(E56="","",IFERROR(INDEX(Catégories!$C$5:$C$60,MATCH(E56,Catégories!$A$5:$A$60,0)),"?")) -> Déductible | J56: =IF(E56="","",IFERROR(INDEX(Catégories!$D$5:$D$60,MATCH(E56,Catégories!$A$5:$A$60,0)),"?")) -> Frais de gestion | K56: =IF(H56="Recette",G56,IF(H56="Dépense",-G56,0)) -> -1 | L56: =IF(E56="",0,G56*IFERROR(INDEX(Catégories!$E$5:$E$60,MATCH(E56,Catégories!$A$5:$A$60,0)),0)) -> -1 | M56: Bien/04_Agence/2024-05_2026-11_AGENCE_Grand-livre-proprietaire.pdf | N56: Grand livre agence
A57: 45539 | B57: =IF(A57="","",YEAR(A57)) -> 2024 | C57: APPART-01 | D57: Agence | E57: Transfert sortant | F57: Virement de l'agence au propriétaire | G57: 1035.65 | H57: =IF(E57="","",IFERROR(INDEX(Catégories!$B$5:$B$60,MATCH(E57,Catégories!$A$5:$A$60,0)),"?")) -> Transfert | I57: =IF(E57="","",IFERROR(INDEX(Catégories!$C$5:$C$60,MATCH(E57,Catégories!$A$5:$A$60,0)),"?")) -> Non fiscal | J57: =IF(E57="","",IFERROR(INDEX(Catégories!$D$5:$D$60,MATCH(E57,Catégories!$A$5:$A$60,0)),"?")) -> Mouvements internes | K57: =IF(H57="Recette",G57,IF(H57="Dépense",-G57,0)) -> 0 | L57: =IF(E57="",0,G57*IFERROR(INDEX(Catégories!$E$5:$E$60,MATCH(E57,Catégories!$A$5:$A$60,0)),0)) -> -1035.65 | M57: Bien/04_Agence/2024-05_2026-11_AGENCE_Grand-livre-proprietaire.pdf | N57: Grand livre agence
A58: 45559 | B58: =IF(A58="","",YEAR(A58)) -> 2024 | C58: APPART-01 | D58: Banque | E58: Charges de copropriété | F58: VIR SEPA CHARGES T4 | G58: 469.61 | H58: =IF(E58="","",IFERROR(INDEX(Catégories!$B$5:$B$60,MATCH(E58,Catégories!$A$5:$A$60,0)),"?")) -> Dépense | I58: =IF(E58="","",IFERROR(INDEX(Catégories!$C$5:$C$60,MATCH(E58,Catégories!$A$5:$A$60,0)),"?")) -> Déductible | J58: =IF(E58="","",IFERROR(INDEX(Catégories!$D$5:$D$60,MATCH(E58,Catégories!$A$5:$A$60,0)),"?")) -> Copropriété | K58: =IF(H58="Recette",G58,IF(H58="Dépense",-G58,0)) -> -469.61 | L58: =IF(E58="",0,G58*IFERROR(INDEX(Catégories!$E$5:$E$60,MATCH(E58,Catégories!$A$5:$A$60,0)),0)) -> -469.61 | M58: Bien/05_Copropriete/Appels/2024-09-24_Syndic_Appel-T4-2024.pdf | N58: Relevé BANQUE
A59: 45567 | B59: =IF(A59="","",YEAR(A59)) -> 2024 | C59: APPART-01 | D59: Agence | E59: Loyer hors charges | F59: LOYER PRINCIPAL (01/10/2024 - 31/10/2024) | G59: 1032.3 | H59: =IF(E59="","",IFERROR(INDEX(Catégories!$B$5:$B$60,MATCH(E59,Catégories!$A$5:$A$60,0)),"?")) -> Recette | I59: =IF(E59="","",IFERROR(INDEX(Catégories!$C$5:$C$60,MATCH(E59,Catégories!$A$5:$A$60,0)),"?")) -> Imposable | J59: =IF(E59="","",IFERROR(INDEX(Catégories!$D$5:$D$60,MATCH(E59,Catégories!$A$5:$A$60,0)),"?")) -> Loyers | K59: =IF(H59="Recette",G59,IF(H59="Dépense",-G59,0)) -> 1032.3 | L59: =IF(E59="",0,G59*IFERROR(INDEX(Catégories!$E$5:$E$60,MATCH(E59,Catégories!$A$5:$A$60,0)),0)) -> 1032.3 | M59: Bien/04_Agence/2024-05_2026-11_AGENCE_Grand-livre-proprietaire.pdf | N59: Grand livre agence
A60: 45567 | B60: =IF(A60="","",YEAR(A60)) -> 2024 | C60: APPART-01 | D60: Agence | E60: Honoraires de gestion | F60: HONORAIRES GESTION LOYER PRINCIPAL 6.00% | G60: 61.94 | H60: =IF(E60="","",IFERROR(INDEX(Catégories!$B$5:$B$60,MATCH(E60,Catégories!$A$5:$A$60,0)),"?")) -> Dépense | I60: =IF(E60="","",IFERROR(INDEX(Catégories!$C$5:$C$60,MATCH(E60,Catégories!$A$5:$A$60,0)),"?")) -> Déductible | J60: =IF(E60="","",IFERROR(INDEX(Catégories!$D$5:$D$60,MATCH(E60,Catégories!$A$5:$A$60,0)),"?")) -> Frais de gestion | K60: =IF(H60="Recette",G60,IF(H60="Dépense",-G60,0)) -> -61.94 | L60: =IF(E60="",0,G60*IFERROR(INDEX(Catégories!$E$5:$E$60,MATCH(E60,Catégories!$A$5:$A$60,0)),0)) -> -61.94 | M60: Bien/04_Agence/2024-05_2026-11_AGENCE_Grand-livre-proprietaire.pdf | N60: Grand livre agence
A61: 45567 | B61: =IF(A61="","",YEAR(A61)) -> 2024 | C61: APPART-01 | D61: Agence | E61: Honoraires de gestion | F61: TVA HONORAIRES GESTION LOYER PRINCIPAL | G61: 12.39 | H61: =IF(E61="","",IFERROR(INDEX(Catégories!$B$5:$B$60,MATCH(E61,Catégories!$A$5:$A$60,0)),"?")) -> Dépense | I61: =IF(E61="","",IFERROR(INDEX(Catégories!$C$5:$C$60,MATCH(E61,Catégories!$A$5:$A$60,0)),"?")) -> Déductible | J61: =IF(E61="","",IFERROR(INDEX(Catégories!$D$5:$D$60,MATCH(E61,Catégories!$A$5:$A$60,0)),"?")) -> Frais de gestion | K61: =IF(H61="Recette",G61,IF(H61="Dépense",-G61,0)) -> -12.39 | L61: =IF(E61="",0,G61*IFERROR(INDEX(Catégories!$E$5:$E$60,MATCH(E61,Catégories!$A$5:$A$60,0)),0)) -> -12.39 | M61: Bien/04_Agence/2024-05_2026-11_AGENCE_Grand-livre-proprietaire.pdf | N61: Grand livre agence
A62: 45567 | B62: =IF(A62="","",YEAR(A62)) -> 2024 | C62: APPART-01 | D62: Agence | E62: Provisions sur charges | F62: PROVISIONS CHARGES (01/10/2024 - 31/10/2024) | G62: 83.7 | H62: =IF(E62="","",IFERROR(INDEX(Catégories!$B$5:$B$60,MATCH(E62,Catégories!$A$5:$A$60,0)),"?")) -> Recette | I62: =IF(E62="","",IFERROR(INDEX(Catégories!$C$5:$C$60,MATCH(E62,Catégories!$A$5:$A$60,0)),"?")) -> Imposable | J62: =IF(E62="","",IFERROR(INDEX(Catégories!$D$5:$D$60,MATCH(E62,Catégories!$A$5:$A$60,0)),"?")) -> Charges refacturées | K62: =IF(H62="Recette",G62,IF(H62="Dépense",-G62,0)) -> 83.7 | L62: =IF(E62="",0,G62*IFERROR(INDEX(Catégories!$E$5:$E$60,MATCH(E62,Catégories!$A$5:$A$60,0)),0)) -> 83.7 | M62: Bien/04_Agence/2024-05_2026-11_AGENCE_Grand-livre-proprietaire.pdf | N62: Grand livre agence
... A65: 45568 | B65: =IF(A65="","",YEAR(A65)) -> 2024 | C65: APPART-01 | D65: Agence | E65: Transfert sortant | F65: Virement de l'agence au propriétaire | G65: 1035.65 | H65: =IF(E65="","",IFERROR(INDEX(Catégories!$B$5:$B$60,MATCH(E65,Catégories!$A$5:$A$60,0)),"?")) -> Transfert | I65: =IF(E65="","",IFERROR(INDEX(Catégories!$C$5:$C$60,MATCH(E65,Catégories!$A$5:$A$60,0)),"?")) -> Non fiscal | J65: =IF(E65="","",IFERROR(INDEX(Catégories!$D$5:$D$60,MATCH(E65,Catégories!$A$5:$A$60,0)),"?")) -> Mouvements internes | K65: =IF(H65="Recette",G65,IF(H65="Dépense",-G65,0)) -> 0 | L65: =IF(E65="",0,G65*IFERROR(INDEX(Catégories!$E$5:$E$60,MATCH(E65,Catégories!$A$5:$A$60,0)),0)) -> -1035.65 | M65: Bien/04_Agence/2024-05_2026-11_AGENCE_Grand-livre-proprietaire.pdf | N65: Grand livre agence
A66: 45590 | B66: =IF(A66="","",YEAR(A66)) -> 2024 | C66: APPART-01 | D66: Banque | E66: Taxe foncière | F66: PRLV SEPA DGFIP IMPOT TF | G66: 553.35 | H66: =IF(E66="","",IFERROR(INDEX(Catégories!$B$5:$B$60,MATCH(E66,Catégories!$A$5:$A$60,0)),"?")) -> Dépense | I66: =IF(E66="","",IFERROR(INDEX(Catégories!$C$5:$C$60,MATCH(E66,Catégories!$A$5:$A$60,0)),"?")) -> Déductible | J66: =IF(E66="","",IFERROR(INDEX(Catégories!$D$5:$D$60,MATCH(E66,Catégories!$A$5:$A$60,0)),"?")) -> Impôts et taxes | K66: =IF(H66="Recette",G66,IF(H66="Dépense",-G66,0)) -> -553.35 | L66: =IF(E66="",0,G66*IFERROR(INDEX(Catégories!$E$5:$E$60,MATCH(E66,Catégories!$A$5:$A$60,0)),0)) -> -553.35 | M66: Banque/Banque_Exempleville_Revenus-Depenses_2024-2026.xlsx | N66: Relevé BANQUE | O66: Taxe foncière 2024
A67: 45597 | B67: =IF(A67="","",YEAR(A67)) -> 2024 | C67: APPART-01 | D67: Agence | E67: Taxe ordures ménagères refacturée | F67: ORDURES MENAGERES 2024 | G67: 50.76 | H67: =IF(E67="","",IFERROR(INDEX(Catégories!$B$5:$B$60,MATCH(E67,Catégories!$A$5:$A$60,0)),"?")) -> Recette | I67: =IF(E67="","",IFERROR(INDEX(Catégories!$C$5:$C$60,MATCH(E67,Catégories!$A$5:$A$60,0)),"?")) -> Imposable | J67: =IF(E67="","",IFERROR(INDEX(Catégories!$D$5:$D$60,MATCH(E67,Catégories!$A$5:$A$60,0)),"?")) -> Charges refacturées | K67: =IF(H67="Recette",G67,IF(H67="Dépense",-G67,0)) -> 50.76 | L67: =IF(E67="",0,G67*IFERROR(INDEX(Catégories!$E$5:$E$60,MATCH(E67,Catégories!$A$5:$A$60,0)),0)) -> 50.76 | M67: Bien/04_Agence/2024-05_2026-11_AGENCE_Grand-livre-proprietaire.pdf | N67: Grand livre agence
A68: 45597 | B68: =IF(A68="","",YEAR(A68)) -> 2024 | C68: APPART-01 | D68: Agence | E68: Honoraires de gestion | F68: HONORAIRES GESTION ORDURES MENAGERES 2024 6.00% | G68: 3.04 | H68: =IF(E68="","",IFERROR(INDEX(Catégories!$B$5:$B$60,MATCH(E68,Catégories!$A$5:$A$60,0)),"?")) -> Dépense | I68: =IF(E68="","",IFERROR(INDEX(Catégories!$C$5:$C$60,MATCH(E68,Catégories!$A$5:$A$60,0)),"?")) -> Déductible | J68: =IF(E68="","",IFERROR(INDEX(Catégories!$D$5:$D$60,MATCH(E68,Catégories!$A$5:$A$60,0)),"?")) -> Frais de gestion | K68: =IF(H68="Recette",G68,IF(H68="Dépense",-G68,0)) -> -3.04 | L68: =IF(E68="",0,G68*IFERROR(INDEX(Catégories!$E$5:$E$60,MATCH(E68,Catégories!$A$5:$A$60,0)),0)) -> -3.04 | M68: Bien/04_Agence/2024-05_2026-11_AGENCE_Grand-livre-proprietaire.pdf | N68: Grand livre agence
A69: 45597 | B69: =IF(A69="","",YEAR(A69)) -> 2024 | C69: APPART-01 | D69: Agence | E69: Honoraires de gestion | F69: TVA HONORAIRES GESTION ORDURES MENAGERES 2024 | G69: 0.6 | H69: =IF(E69="","",IFERROR(INDEX(Catégories!$B$5:$B$60,MATCH(E69,Catégories!$A$5:$A$60,0)),"?")) -> Dépense | I69: =IF(E69="","",IFERROR(INDEX(Catégories!$C$5:$C$60,MATCH(E69,Catégories!$A$5:$A$60,0)),"?")) -> Déductible | J69: =IF(E69="","",IFERROR(INDEX(Catégories!$D$5:$D$60,MATCH(E69,Catégories!$A$5:$A$60,0)),"?")) -> Frais de gestion | K69: =IF(H69="Recette",G69,IF(H69="Dépense",-G69,0)) -> -0.6 | L69: =IF(E69="",0,G69*IFERROR(INDEX(Catégories!$E$5:$E$60,MATCH(E69,Catégories!$A$5:$A$60,0)),0)) -> -0.6 | M69: Bien/04_Agence/2024-05_2026-11_AGENCE_Grand-livre-proprietaire.pdf | N69: Grand livre agence
A70: 45600 | B70: =IF(A70="","",YEAR(A70)) -> 2024 | C70: APPART-01 | D70: Agence | E70: Loyer hors charges | F70: LOYER PRINCIPAL (01/11/2024 - 30/11/2024) | G70: 1032.3 | H70: =IF(E70="","",IFERROR(INDEX(Catégories!$B$5:$B$60,MATCH(E70,Catégories!$A$5:$A$60,0)),"?")) -> Recette | I70: =IF(E70="","",IFERROR(INDEX(Catégories!$C$5:$C$60,MATCH(E70,Catégories!$A$5:$A$60,0)),"?")) -> Imposable | J70: =IF(E70="","",IFERROR(INDEX(Catégories!$D$5:$D$60,MATCH(E70,Catégories!$A$5:$A$60,0)),"?")) -> Loyers | K70: =IF(H70="Recette",G70,IF(H70="Dépense",-G70,0)) -> 1032.3 | L70: =IF(E70="",0,G70*IFERROR(INDEX(Catégories!$E$5:$E$60,MATCH(E70,Catégories!$A$5:$A$60,0)),0)) -> 1032.3 | M70: Bien/04_Agence/2024-05_2026-11_AGENCE_Grand-livre-proprietaire.pdf | N70: Grand livre agence
A71: 45600 | B71: =IF(A71="","",YEAR(A71)) -> 2024 | C71: APPART-01 | D71: Agence | E71: Honoraires de gestion | F71: HONORAIRES GESTION LOYER PRINCIPAL 6.00% | G71: 61.94 | H71: =IF(E71="","",IFERROR(INDEX(Catégories!$B$5:$B$60,MATCH(E71,Catégories!$A$5:$A$60,0)),"?")) -> Dépense | I71: =IF(E71="","",IFERROR(INDEX(Catégories!$C$5:$C$60,MATCH(E71,Catégories!$A$5:$A$60,0)),"?")) -> Déductible | J71: =IF(E71="","",IFERROR(INDEX(Catégories!$D$5:$D$60,MATCH(E71,Catégories!$A$5:$A$60,0)),"?")) -> Frais de gestion | K71: =IF(H71="Recette",G71,IF(H71="Dépense",-G71,0)) -> -61.94 | L71: =IF(E71="",0,G71*IFERROR(INDEX(Catégories!$E$5:$E$60,MATCH(E71,Catégories!$A$5:$A$60,0)),0)) -> -61.94 | M71: Bien/04_Agence/2024-05_2026-11_AGENCE_Grand-livre-proprietaire.pdf | N71: Grand livre agence
A72: 45600 | B72: =IF(A72="","",YEAR(A72)) -> 2024 | C72: APPART-01 | D72: Agence | E72: Honoraires de gestion | F72: TVA HONORAIRES GESTION LOYER PRINCIPAL | G72: 12.39 | H72: =IF(E72="","",IFERROR(INDEX(Catégories!$B$5:$B$60,MATCH(E72,Catégories!$A$5:$A$60,0)),"?")) -> Dépense | I72: =IF(E72="","",IFERROR(INDEX(Catégories!$C$5:$C$60,MATCH(E72,Catégories!$A$5:$A$60,0)),"?")) -> Déductible | J72: =IF(E72="","",IFERROR(INDEX(Catégories!$D$5:$D$60,MATCH(E72,Catégories!$A$5:$A$60,0)),"?")) -> Frais de gestion | K72: =IF(H72="Recette",G72,IF(H72="Dépense",-G72,0)) -> -12.39 | L72: =IF(E72="",0,G72*IFERROR(INDEX(Catégories!$E$5:$E$60,MATCH(E72,Catégories!$A$5:$A$60,0)),0)) -> -12.39 | M72: Bien/04_Agence/2024-05_2026-11_AGENCE_Grand-livre-proprietaire.pdf | N72: Grand livre agence
A73: 45600 | B73: =IF(A73="","",YEAR(A73)) -> 2024 | C73: APPART-01 | D73: Agence | E73: Provisions sur charges | F73: PROVISIONS CHARGES (01/11/2024 - 30/11/2024) | G73: 83.7 | H73: =IF(E73="","",IFERROR(INDEX(Catégories!$B$5:$B$60,MATCH(E73,Catégories!$A$5:$A$60,0)),"?")) -> Recette | I73: =IF(E73="","",IFERROR(INDEX(Catégories!$C$5:$C$60,MATCH(E73,Catégories!$A$5:$A$60,0)),"?")) -> Imposable | J73: =IF(E73="","",IFERROR(INDEX(Catégories!$D$5:$D$60,MATCH(E73,Catégories!$A$5:$A$60,0)),"?")) -> Charges refacturées | K73: =IF(H73="Recette",G73,IF(H73="Dépense",-G73,0)) -> 83.7 | L73: =IF(E73="",0,G73*IFERROR(INDEX(Catégories!$E$5:$E$60,MATCH(E73,Catégories!$A$5:$A$60,0)),0)) -> 83.7 | M73: Bien/04_Agence/2024-05_2026-11_AGENCE_Grand-livre-proprietaire.pdf | N73: Grand livre agence
A74: 45600 | B74: =IF(A74="","",YEAR(A74)) -> 2024 | C74: APPART-01 | D74: Agence | E74: Honoraires de gestion | F74: HONORAIRES GESTION PROVISIONS CHARGES 6.00% | G74: 5.02 | H74: =IF(E74="","",IFERROR(INDEX(Catégories!$B$5:$B$60,MATCH(E74,Catégories!$A$5:$A$60,0)),"?")) -> Dépense | I74: =IF(E74="","",IFERROR(INDEX(Catégories!$C$5:$C$60,MATCH(E74,Catégories!$A$5:$A$60,0)),"?")) -> Déductible | J74: =IF(E74="","",IFERROR(INDEX(Catégories!$D$5:$D$60,MATCH(E74,Catégories!$A$5:$A$60,0)),"?")) -> Frais de gestion | K74: =IF(H74="Recette",G74,IF(H74="Dépense",-G74,0)) -> -5.02 | L74: =IF(E74="",0,G74*IFERROR(INDEX(Catégories!$E$5:$E$60,MATCH(E74,Catégories!$A$5:$A$60,0)),0)) -> -5.02 | M74: Bien/04_Agence/2024-05_2026-11_AGENCE_Grand-livre-proprietaire.pdf | N74: Grand livre agence
A75: 45600 | B75: =IF(A75="","",YEAR(A75)) -> 2024 | C75: APPART-01 | D75: Agence | E75: Honoraires de gestion | F75: TVA HONORAIRES GESTION PROVISIONS CHARGES | G75: 1 | H75: =IF(E75="","",IFERROR(INDEX(Catégories!$B$5:$B$60,MATCH(E75,Catégories!$A$5:$A$60,0)),"?")) -> Dépense | I75: =IF(E75="","",IFERROR(INDEX(Catégories!$C$5:$C$60,MATCH(E75,Catégories!$A$5:$A$60,0)),"?")) -> Déductible | J75: =IF(E75="","",IFERROR(INDEX(Catégories!$D$5:$D$60,MATCH(E75,Catégories!$A$5:$A$60,0)),"?")) -> Frais de gestion | K75: =IF(H75="Recette",G75,IF(H75="Dépense",-G75,0)) -> -1 | L75: =IF(E75="",0,G75*IFERROR(INDEX(Catégories!$E$5:$E$60,MATCH(E75,Catégories!$A$5:$A$60,0)),0)) -> -1 | M75: Bien/04_Agence/2024-05_2026-11_AGENCE_Grand-livre-proprietaire.pdf | N75: Grand livre agence
A76: 45600 | B76: =IF(A76="","",YEAR(A76)) -> 2024 | C76: APPART-01 | D76: Agence | E76: Transfert sortant | F76: Virement de l'agence au propriétaire | G76: 1082.76 | H76: =IF(E76="","",IFERROR(INDEX(Catégories!$B$5:$B$60,MATCH(E76,Catégories!$A$5:$A$60,0)),"?")) -> Transfert | I76: =IF(E76="","",IFERROR(INDEX(Catégories!$C$5:$C$60,MATCH(E76,Catégories!$A$5:$A$60,0)),"?")) -> Non fiscal | J76: =IF(E76="","",IFERROR(INDEX(Catégories!$D$5:$D$60,MATCH(E76,Catégories!$A$5:$A$60,0)),"?")) -> Mouvements internes | K76: =IF(H76="Recette",G76,IF(H76="Dépense",-G76,0)) -> 0 | L76: =IF(E76="",0,G76*IFERROR(INDEX(Catégories!$E$5:$E$60,MATCH(E76,Catégories!$A$5:$A$60,0)),0)) -> -1082.76 | M76: Bien/04_Agence/2024-05_2026-11_AGENCE_Grand-livre-proprietaire.pdf | N76: Grand livre agence
A77: 45628 | B77: =IF(A77="","",YEAR(A77)) -> 2024 | C77: APPART-01 | D77: Agence | E77: Loyer hors charges | F77: LOYER PRINCIPAL (01/12/2024 - 31/12/2024) | G77: 1032.3 | H77: =IF(E77="","",IFERROR(INDEX(Catégories!$B$5:$B$60,MATCH(E77,Catégories!$A$5:$A$60,0)),"?")) -> Recette | I77: =IF(E77="","",IFERROR(INDEX(Catégories!$C$5:$C$60,MATCH(E77,Catégories!$A$5:$A$60,0)),"?")) -> Imposable | J77: =IF(E77="","",IFERROR(INDEX(Catégories!$D$5:$D$60,MATCH(E77,Catégories!$A$5:$A$60,0)),"?")) -> Loyers | K77: =IF(H77="Recette",G77,IF(H77="Dépense",-G77,0)) -> 1032.3 | L77: =IF(E77="",0,G77*IFERROR(INDEX(Catégories!$E$5:$E$60,MATCH(E77,Catégories!$A$5:$A$60,0)),0)) -> 1032.3 | M77: Bien/04_Agence/2024-05_2026-11_AGENCE_Grand-livre-proprietaire.pdf | N77: Grand livre agence
A78: 45628 | B78: =IF(A78="","",YEAR(A78)) -> 2024 | C78: APPART-01 | D78: Agence | E78: Honoraires de gestion | F78: HONORAIRES GESTION LOYER PRINCIPAL 6.00% | G78: 61.94 | H78: =IF(E78="","",IFERROR(INDEX(Catégories!$B$5:$B$60,MATCH(E78,Catégories!$A$5:$A$60,0)),"?")) -> Dépense | I78: =IF(E78="","",IFERROR(INDEX(Catégories!$C$5:$C$60,MATCH(E78,Catégories!$A$5:$A$60,0)),"?")) -> Déductible | J78: =IF(E78="","",IFERROR(INDEX(Catégories!$D$5:$D$60,MATCH(E78,Catégories!$A$5:$A$60,0)),"?")) -> Frais de gestion | K78: =IF(H78="Recette",G78,IF(H78="Dépense",-G78,0)) -> -61.94 | L78: =IF(E78="",0,G78*IFERROR(INDEX(Catégories!$E$5:$E$60,MATCH(E78,Catégories!$A$5:$A$60,0)),0)) -> -61.94 | M78: Bien/04_Agence/2024-05_2026-11_AGENCE_Grand-livre-proprietaire.pdf | N78: Grand livre agence
... A83: 45630 | B83: =IF(A83="","",YEAR(A83)) -> 2024 | C83: APPART-01 | D83: Agence | E83: Transfert sortant | F83: Virement de l'agence au propriétaire | G83: 1035.65 | H83: =IF(E83="","",IFERROR(INDEX(Catégories!$B$5:$B$60,MATCH(E83,Catégories!$A$5:$A$60,0)),"?")) -> Transfert | I83: =IF(E83="","",IFERROR(INDEX(Catégories!$C$5:$C$60,MATCH(E83,Catégories!$A$5:$A$60,0)),"?")) -> Non fiscal | J83: =IF(E83="","",IFERROR(INDEX(Catégories!$D$5:$D$60,MATCH(E83,Catégories!$A$5:$A$60,0)),"?")) -> Mouvements internes | K83: =IF(H83="Recette",G83,IF(H83="Dépense",-G83,0)) -> 0 | L83: =IF(E83="",0,G83*IFERROR(INDEX(Catégories!$E$5:$E$60,MATCH(E83,Catégories!$A$5:$A$60,0)),0)) -> -1035.65 | M83: Bien/04_Agence/2024-05_2026-11_AGENCE_Grand-livre-proprietaire.pdf | N83: Grand livre agence
A84: 45650 | B84: =IF(A84="","",YEAR(A84)) -> 2024 | C84: APPART-01 | D84: Banque | E84: Charges de copropriété | F84: VIR SEPA CHARGES COPRO | G84: 360 | H84: =IF(E84="","",IFERROR(INDEX(Catégories!$B$5:$B$60,MATCH(E84,Catégories!$A$5:$A$60,0)),"?")) -> Dépense | I84: =IF(E84="","",IFERROR(INDEX(Catégories!$C$5:$C$60,MATCH(E84,Catégories!$A$5:$A$60,0)),"?")) -> Déductible | J84: =IF(E84="","",IFERROR(INDEX(Catégories!$D$5:$D$60,MATCH(E84,Catégories!$A$5:$A$60,0)),"?")) -> Copropriété | K84: =IF(H84="Recette",G84,IF(H84="Dépense",-G84,0)) -> -360 | L84: =IF(E84="",0,G84*IFERROR(INDEX(Catégories!$E$5:$E$60,MATCH(E84,Catégories!$A$5:$A$60,0)),0)) -> -360 | M84: Bien/05_Copropriete/Appels/2024-09-24_Syndic_Appel-travaux-oct-2024.pdf | N84: Relevé BANQUE | O84: Travaux appelés en octobre 2024 (local vélos, refonte du règlement)
A85: 45657 | B85: =IF(A85="","",YEAR(A85)) -> 2024 | C85: APPART-01 | D85: Autre compte | E85: Assurance PNO | F85: Assurance propriétaire non occupant ASSUREUR 2024 | G85: 105.8 | H85: =IF(E85="","",IFERROR(INDEX(Catégories!$B$5:$B$60,MATCH(E85,Catégories!$A$5:$A$60,0)),"?")) -> Dépense | I85: =IF(E85="","",IFERROR(INDEX(Catégories!$C$5:$C$60,MATCH(E85,Catégories!$A$5:$A$60,0)),"?")) -> Déductible | J85: =IF(E85="","",IFERROR(INDEX(Catégories!$D$5:$D$60,MATCH(E85,Catégories!$A$5:$A$60,0)),"?")) -> Assurances | K85: =IF(H85="Recette",G85,IF(H85="Dépense",-G85,0)) -> -105.8 | L85: =IF(E85="",0,G85*IFERROR(INDEX(Catégories!$E$5:$E$60,MATCH(E85,Catégories!$A$5:$A$60,0)),0)) -> -105.8 | M85: Bien/07_Comptabilite/2024_CABINET COMPTABLE_Comptes-annuels-LMNP.pdf | N85: Comptes annuels | O85: Montant retenu par le comptable, payé hors compte BANQUE (date réelle inconnue)
A86: 45659 | B86: =IF(A86="","",YEAR(A86)) -> 2025 | C86: APPART-01 | D86: Agence | E86: Loyer hors charges | F86: LOYER PRINCIPAL (01/01/2025 - 31/01/2025) | G86: 1032.3 | H86: =IF(E86="","",IFERROR(INDEX(Catégories!$B$5:$B$60,MATCH(E86,Catégories!$A$5:$A$60,0)),"?")) -> Recette | I86: =IF(E86="","",IFERROR(INDEX(Catégories!$C$5:$C$60,MATCH(E86,Catégories!$A$5:$A$60,0)),"?")) -> Imposable | J86: =IF(E86="","",IFERROR(INDEX(Catégories!$D$5:$D$60,MATCH(E86,Catégories!$A$5:$A$60,0)),"?")) -> Loyers | K86: =IF(H86="Recette",G86,IF(H86="Dépense",-G86,0)) -> 1032.3 | L86: =IF(E86="",0,G86*IFERROR(INDEX(Catégories!$E$5:$E$60,MATCH(E86,Catégories!$A$5:$A$60,0)),0)) -> 1032.3 | M86: Bien/04_Agence/2024-05_2026-11_AGENCE_Grand-livre-proprietaire.pdf | N86: Grand livre agence
A87: 45659 | B87: =IF(A87="","",YEAR(A87)) -> 2025 | C87: APPART-01 | D87: Agence | E87: Honoraires de gestion | F87: HONORAIRES GESTION LOYER PRINCIPAL 6.00% | G87: 61.94 | H87: =IF(E87="","",IFERROR(INDEX(Catégories!$B$5:$B$60,MATCH(E87,Catégories!$A$5:$A$60,0)),"?")) -> Dépense | I87: =IF(E87="","",IFERROR(INDEX(Catégories!$C$5:$C$60,MATCH(E87,Catégories!$A$5:$A$60,0)),"?")) -> Déductible | J87: =IF(E87="","",IFERROR(INDEX(Catégories!$D$5:$D$60,MATCH(E87,Catégories!$A$5:$A$60,0)),"?")) -> Frais de gestion | K87: =IF(H87="Recette",G87,IF(H87="Dépense",-G87,0)) -> -61.94 | L87: =IF(E87="",0,G87*IFERROR(INDEX(Catégories!$E$5:$E$60,MATCH(E87,Catégories!$A$5:$A$60,0)),0)) -> -61.94 | M87: Bien/04_Agence/2024-05_2026-11_AGENCE_Grand-livre-proprietaire.pdf | N87: Grand livre agence
A88: 45659 | B88: =IF(A88="","",YEAR(A88)) -> 2025 | C88: APPART-01 | D88: Agence | E88: Honoraires de gestion | F88: TVA HONORAIRES GESTION LOYER PRINCIPAL | G88: 12.39 | H88: =IF(E88="","",IFERROR(INDEX(Catégories!$B$5:$B$60,MATCH(E88,Catégories!$A$5:$A$60,0)),"?")) -> Dépense | I88: =IF(E88="","",IFERROR(INDEX(Catégories!$C$5:$C$60,MATCH(E88,Catégories!$A$5:$A$60,0)),"?")) -> Déductible | J88: =IF(E88="","",IFERROR(INDEX(Catégories!$D$5:$D$60,MATCH(E88,Catégories!$A$5:$A$60,0)),"?")) -> Frais de gestion | K88: =IF(H88="Recette",G88,IF(H88="Dépense",-G88,0)) -> -12.39 | L88: =IF(E88="",0,G88*IFERROR(INDEX(Catégories!$E$5:$E$60,MATCH(E88,Catégories!$A$5:$A$60,0)),0)) -> -12.39 | M88: Bien/04_Agence/2024-05_2026-11_AGENCE_Grand-livre-proprietaire.pdf | N88: Grand livre agence
A89: 45659 | B89: =IF(A89="","",YEAR(A89)) -> 2025 | C89: APPART-01 | D89: Agence | E89: Provisions sur charges | F89: PROVISIONS CHARGES (01/01/2025 - 31/01/2025) | G89: 83.7 | H89: =IF(E89="","",IFERROR(INDEX(Catégories!$B$5:$B$60,MATCH(E89,Catégories!$A$5:$A$60,0)),"?")) -> Recette | I89: =IF(E89="","",IFERROR(INDEX(Catégories!$C$5:$C$60,MATCH(E89,Catégories!$A$5:$A$60,0)),"?")) -> Imposable | J89: =IF(E89="","",IFERROR(INDEX(Catégories!$D$5:$D$60,MATCH(E89,Catégories!$A$5:$A$60,0)),"?")) -> Charges refacturées | K89: =IF(H89="Recette",G89,IF(H89="Dépense",-G89,0)) -> 83.7 | L89: =IF(E89="",0,G89*IFERROR(INDEX(Catégories!$E$5:$E$60,MATCH(E89,Catégories!$A$5:$A$60,0)),0)) -> 83.7 | M89: Bien/04_Agence/2024-05_2026-11_AGENCE_Grand-livre-proprietaire.pdf | N89: Grand livre agence
A90: 45659 | B90: =IF(A90="","",YEAR(A90)) -> 2025 | C90: APPART-01 | D90: Agence | E90: Honoraires de gestion | F90: HONORAIRES GESTION PROVISIONS CHARGES 6.00% | G90: 5.02 | H90: =IF(E90="","",IFERROR(INDEX(Catégories!$B$5:$B$60,MATCH(E90,Catégories!$A$5:$A$60,0)),"?")) -> Dépense | I90: =IF(E90="","",IFERROR(INDEX(Catégories!$C$5:$C$60,MATCH(E90,Catégories!$A$5:$A$60,0)),"?")) -> Déductible | J90: =IF(E90="","",IFERROR(INDEX(Catégories!$D$5:$D$60,MATCH(E90,Catégories!$A$5:$A$60,0)),"?")) -> Frais de gestion | K90: =IF(H90="Recette",G90,IF(H90="Dépense",-G90,0)) -> -5.02 | L90: =IF(E90="",0,G90*IFERROR(INDEX(Catégories!$E$5:$E$60,MATCH(E90,Catégories!$A$5:$A$60,0)),0)) -> -5.02 | M90: Bien/04_Agence/2024-05_2026-11_AGENCE_Grand-livre-proprietaire.pdf | N90: Grand livre agence
A91: 45659 | B91: =IF(A91="","",YEAR(A91)) -> 2025 | C91: APPART-01 | D91: Agence | E91: Honoraires de gestion | F91: TVA HONORAIRES GESTION PROVISIONS CHARGES | G91: 1 | H91: =IF(E91="","",IFERROR(INDEX(Catégories!$B$5:$B$60,MATCH(E91,Catégories!$A$5:$A$60,0)),"?")) -> Dépense | I91: =IF(E91="","",IFERROR(INDEX(Catégories!$C$5:$C$60,MATCH(E91,Catégories!$A$5:$A$60,0)),"?")) -> Déductible | J91: =IF(E91="","",IFERROR(INDEX(Catégories!$D$5:$D$60,MATCH(E91,Catégories!$A$5:$A$60,0)),"?")) -> Frais de gestion | K91: =IF(H91="Recette",G91,IF(H91="Dépense",-G91,0)) -> -1 | L91: =IF(E91="",0,G91*IFERROR(INDEX(Catégories!$E$5:$E$60,MATCH(E91,Catégories!$A$5:$A$60,0)),0)) -> -1 | M91: Bien/04_Agence/2024-05_2026-11_AGENCE_Grand-livre-proprietaire.pdf | N91: Grand livre agence
A92: 45659 | B92: =IF(A92="","",YEAR(A92)) -> 2025 | C92: APPART-01 | D92: Agence | E92: Transfert sortant | F92: Virement de l'agence au propriétaire | G92: 1035.65 | H92: =IF(E92="","",IFERROR(INDEX(Catégories!$B$5:$B$60,MATCH(E92,Catégories!$A$5:$A$60,0)),"?")) -> Transfert | I92: =IF(E92="","",IFERROR(INDEX(Catégories!$C$5:$C$60,MATCH(E92,Catégories!$A$5:$A$60,0)),"?")) -> Non fiscal | J92: =IF(E92="","",IFERROR(INDEX(Catégories!$D$5:$D$60,MATCH(E92,Catégories!$A$5:$A$60,0)),"?")) -> Mouvements internes | K92: =IF(H92="Recette",G92,IF(H92="Dépense",-G92,0)) -> 0 | L92: =IF(E92="",0,G92*IFERROR(INDEX(Catégories!$E$5:$E$60,MATCH(E92,Catégories!$A$5:$A$60,0)),0)) -> -1035.65 | M92: Bien/04_Agence/2024-05_2026-11_AGENCE_Grand-livre-proprietaire.pdf | N92: Grand livre agence
A93: 45665 | B93: =IF(A93="","",YEAR(A93)) -> 2025 | C93: APPART-01 | D93: Banque | E93: Charges de copropriété | F93: VIR SEPA CHARGES 1 RUE EXEMPLE | G93: 769.08 | H93: =IF(E93="","",IFERROR(INDEX(Catégories!$B$5:$B$60,MATCH(E93,Catégories!$A$5:$A$60,0)),"?")) -> Dépense | I93: =IF(E93="","",IFERROR(INDEX(Catégories!$C$5:$C$60,MATCH(E93,Catégories!$A$5:$A$60,0)),"?")) -> Déductible | J93: =IF(E93="","",IFERROR(INDEX(Catégories!$D$5:$D$60,MATCH(E93,Catégories!$A$5:$A$60,0)),"?")) -> Copropriété | K93: =IF(H93="Recette",G93,IF(H93="Dépense",-G93,0)) -> -769.08 | L93: =IF(E93="",0,G93*IFERROR(INDEX(Catégories!$E$5:$E$60,MATCH(E93,Catégories!$A$5:$A$60,0)),0)) -> -769.08 | M93: Bien/05_Copropriete/Appels/2024-12-25_Syndic_Appel-T1-2025.pdf | N93: Relevé BANQUE
A94: 45691 | B94: =IF(A94="","",YEAR(A94)) -> 2025 | C94: APPART-01 | D94: Agence | E94: Loyer hors charges | F94: LOYER PRINCIPAL (01/02/2025 - 28/02/2025) | G94: 1032.3 | H94: =IF(E94="","",IFERROR(INDEX(Catégories!$B$5:$B$60,MATCH(E94,Catégories!$A$5:$A$60,0)),"?")) -> Recette | I94: =IF(E94="","",IFERROR(INDEX(Catégories!$C$5:$C$60,MATCH(E94,Catégories!$A$5:$A$60,0)),"?")) -> Imposable | J94: =IF(E94="","",IFERROR(INDEX(Catégories!$D$5:$D$60,MATCH(E94,Catégories!$A$5:$A$60,0)),"?")) -> Loyers | K94: =IF(H94="Recette",G94,IF(H94="Dépense",-G94,0)) -> 1032.3 | L94: =IF(E94="",0,G94*IFERROR(INDEX(Catégories!$E$5:$E$60,MATCH(E94,Catégories!$A$5:$A$60,0)),0)) -> 1032.3 | M94: Bien/04_Agence/2024-05_2026-11_AGENCE_Grand-livre-proprietaire.pdf | N94: Grand livre agence
A95: 45691 | B95: =IF(A95="","",YEAR(A95)) -> 2025 | C95: APPART-01 | D95: Agence | E95: Honoraires de gestion | F95: HONORAIRES GESTION LOYER PRINCIPAL 6.00% | G95: 61.94 | H95: =IF(E95="","",IFERROR(INDEX(Catégories!$B$5:$B$60,MATCH(E95,Catégories!$A$5:$A$60,0)),"?")) -> Dépense | I95: =IF(E95="","",IFERROR(INDEX(Catégories!$C$5:$C$60,MATCH(E95,Catégories!$A$5:$A$60,0)),"?")) -> Déductible | J95: =IF(E95="","",IFERROR(INDEX(Catégories!$D$5:$D$60,MATCH(E95,Catégories!$A$5:$A$60,0)),"?")) -> Frais de gestion | K95: =IF(H95="Recette",G95,IF(H95="Dépense",-G95,0)) -> -61.94 | L95: =IF(E95="",0,G95*IFERROR(INDEX(Catégories!$E$5:$E$60,MATCH(E95,Catégories!$A$5:$A$60,0)),0)) -> -61.94 | M95: Bien/04_Agence/2024-05_2026-11_AGENCE_Grand-livre-proprietaire.pdf | N95: Grand livre agence
A96: 45691 | B96: =IF(A96="","",YEAR(A96)) -> 2025 | C96: APPART-01 | D96: Agence | E96: Honoraires de gestion | F96: TVA HONORAIRES GESTION LOYER PRINCIPAL | G96: 12.39 | H96: =IF(E96="","",IFERROR(INDEX(Catégories!$B$5:$B$60,MATCH(E96,Catégories!$A$5:$A$60,0)),"?")) -> Dépense | I96: =IF(E96="","",IFERROR(INDEX(Catégories!$C$5:$C$60,MATCH(E96,Catégories!$A$5:$A$60,0)),"?")) -> Déductible | J96: =IF(E96="","",IFERROR(INDEX(Catégories!$D$5:$D$60,MATCH(E96,Catégories!$A$5:$A$60,0)),"?")) -> Frais de gestion | K96: =IF(H96="Recette",G96,IF(H96="Dépense",-G96,0)) -> -12.39 | L96: =IF(E96="",0,G96*IFERROR(INDEX(Catégories!$E$5:$E$60,MATCH(E96,Catégories!$A$5:$A$60,0)),0)) -> -12.39 | M96: Bien/04_Agence/2024-05_2026-11_AGENCE_Grand-livre-proprietaire.pdf | N96: Grand livre agence
A97: 45691 | B97: =IF(A97="","",YEAR(A97)) -> 2025 | C97: APPART-01 | D97: Agence | E97: Provisions sur charges | F97: PROVISIONS CHARGES (01/02/2025 - 28/02/2025) | G97: 83.7 | H97: =IF(E97="","",IFERROR(INDEX(Catégories!$B$5:$B$60,MATCH(E97,Catégories!$A$5:$A$60,0)),"?")) -> Recette | I97: =IF(E97="","",IFERROR(INDEX(Catégories!$C$5:$C$60,MATCH(E97,Catégories!$A$5:$A$60,0)),"?")) -> Imposable | J97: =IF(E97="","",IFERROR(INDEX(Catégories!$D$5:$D$60,MATCH(E97,Catégories!$A$5:$A$60,0)),"?")) -> Charges refacturées | K97: =IF(H97="Recette",G97,IF(H97="Dépense",-G97,0)) -> 83.7 | L97: =IF(E97="",0,G97*IFERROR(INDEX(Catégories!$E$5:$E$60,MATCH(E97,Catégories!$A$5:$A$60,0)),0)) -> 83.7 | M97: Bien/04_Agence/2024-05_2026-11_AGENCE_Grand-livre-proprietaire.pdf | N97: Grand livre agence
... A138: 45855 | B138: =IF(A138="","",YEAR(A138)) -> 2025 | C138: APPART-01 | D138: Agence | E138: Transfert entrant | F138: VERSEMENT RECU DU PROPRIETAIRE Facture ARTISAN E | G138: 139.5 | H138: =IF(E138="","",IFERROR(INDEX(Catégories!$B$5:$B$60,MATCH(E138,Catégories!$A$5:$A$60,0)),"?")) -> Transfert | I138: =IF(E138="","",IFERROR(INDEX(Catégories!$C$5:$C$60,MATCH(E138,Catégories!$A$5:$A$60,0)),"?")) -> Non fiscal | J138: =IF(E138="","",IFERROR(INDEX(Catégories!$D$5:$D$60,MATCH(E138,Catégories!$A$5:$A$60,0)),"?")) -> Mouvements internes | K138: =IF(H138="Recette",G138,IF(H138="Dépense",-G138,0)) -> 0 | L138: =IF(E138="",0,G138*IFERROR(INDEX(Catégories!$E$5:$E$60,MATCH(E138,Catégories!$A$5:$A$60,0)),0)) -> 139.5 | M138: Bien/04_Agence/2024-05_2026-11_AGENCE_Grand-livre-proprietaire.pdf | N138: Grand livre agence
A139: 45855 | B139: =IF(A139="","",YEAR(A139)) -> 2025 | C139: APPART-01 | D139: Banque | E139: Transfert sortant | F139: VIR SEPA FACTURE ARTISAN E 1 RUE LECL | G139: 139.5 | H139: =IF(E139="","",IFERROR(INDEX(Catégories!$B$5:$B$60,MATCH(E139,Catégories!$A$5:$A$60,0)),"?")) -> Transfert | I139: =IF(E139="","",IFERROR(INDEX(Catégories!$C$5:$C$60,MATCH(E139,Catégories!$A$5:$A$60,0)),"?")) -> Non fiscal | J139: =IF(E139="","",IFERROR(INDEX(Catégories!$D$5:$D$60,MATCH(E139,Catégories!$A$5:$A$60,0)),"?")) -> Mouvements internes | K139: =IF(H139="Recette",G139,IF(H139="Dépense",-G139,0)) -> 0 | L139: =IF(E139="",0,G139*IFERROR(INDEX(Catégories!$E$5:$E$60,MATCH(E139,Catégories!$A$5:$A$60,0)),0)) -> -139.5 | M139: Banque/Banque_Exempleville_Revenus-Depenses_2024-2026.xlsx | N139: Relevé BANQUE | O139: Versé à l'agence pour payer la recherche de fuite (la dépense figure côté agence)
A140: 45856 | B140: =IF(A140="","",YEAR(A140)) -> 2025 | C140: APPART-01 | D140: Agence | E140: Entretien et réparations | F140: recherche de fuite ARTISAN E F2025-07-221 | G140: 139.5 | H140: =IF(E140="","",IFERROR(INDEX(Catégories!$B$5:$B$60,MATCH(E140,Catégories!$A$5:$A$60,0)),"?")) -> Dépense | I140: =IF(E140="","",IFERROR(INDEX(Catégories!$C$5:$C$60,MATCH(E140,Catégories!$A$5:$A$60,0)),"?")) -> Déductible | J140: =IF(E140="","",IFERROR(INDEX(Catégories!$D$5:$D$60,MATCH(E140,Catégories!$A$5:$A$60,0)),"?")) -> Entretien et petit équipement | K140: =IF(H140="Recette",G140,IF(H140="Dépense",-G140,0)) -> -139.5 | L140: =IF(E140="",0,G140*IFERROR(INDEX(Catégories!$E$5:$E$60,MATCH(E140,Catégories!$A$5:$A$60,0)),0)) -> -139.5 | M140: Bien/04_Agence/2024-05_2026-11_AGENCE_Grand-livre-proprietaire.pdf | N140: Grand livre agence
A141: 45861 | B141: =IF(A141="","",YEAR(A141)) -> 2025 | C141: APPART-01 | D141: Banque | E141: Honoraires comptable | F141: VIR SEPA COMPTABLE CABINET COMPTABLE | G141: 558 | H141: =IF(E141="","",IFERROR(INDEX(Catégories!$B$5:$B$60,MATCH(E141,Catégories!$A$5:$A$60,0)),"?")) -> Dépense | I141: =IF(E141="","",IFERROR(INDEX(Catégories!$C$5:$C$60,MATCH(E141,Catégories!$A$5:$A$60,0)),"?")) -> Déductible | J141: =IF(E141="","",IFERROR(INDEX(Catégories!$D$5:$D$60,MATCH(E141,Catégories!$A$5:$A$60,0)),"?")) -> Frais de gestion | K141: =IF(H141="Recette",G141,IF(H141="Dépense",-G141,0)) -> -558 | L141: =IF(E141="",0,G141*IFERROR(INDEX(Catégories!$E$5:$E$60,MATCH(E141,Catégories!$A$5:$A$60,0)),0)) -> -558 | M141: Banque/Banque_Exempleville_Revenus-Depenses_2024-2026.xlsx | N141: Relevé BANQUE | O141: Honoraires pour les comptes 2024
A142: 45870 | B142: =IF(A142="","",YEAR(A142)) -> 2025 | C142: APPART-01 | D142: Agence | E142: Honoraires sur travaux | F142: HONORAIRES GESTION SUR TRAVAUX ARTISAN E 3% TTC | G142: 3.49 | H142: =IF(E142="","",IFERROR(INDEX(Catégories!$B$5:$B$60,MATCH(E142,Catégories!$A$5:$A$60,0)),"?")) -> Dépense | I142: =IF(E142="","",IFERROR(INDEX(Catégories!$C$5:$C$60,MATCH(E142,Catégories!$A$5:$A$60,0)),"?")) -> Déductible | J142: =IF(E142="","",IFERROR(INDEX(Catégories!$D$5:$D$60,MATCH(E142,Catégories!$A$5:$A$60,0)),"?")) -> Frais de gestion | K142: =IF(H142="Recette",G142,IF(H142="Dépense",-G142,0)) -> -3.49 | L142: =IF(E142="",0,G142*IFERROR(INDEX(Catégories!$E$5:$E$60,MATCH(E142,Catégories!$A$5:$A$60,0)),0)) -> -3.49 | M142: Bien/04_Agence/2024-05_2026-11_AGENCE_Grand-livre-proprietaire.pdf | N142: Grand livre agence
A143: 45870 | B143: =IF(A143="","",YEAR(A143)) -> 2025 | C143: APPART-01 | D143: Agence | E143: Honoraires sur travaux | F143: TVA HONORAIRES GESTION SUR TRAVAUX ARTISAN E 3% TTC | G143: 0.7 | H143: =IF(E143="","",IFERROR(INDEX(Catégories!$B$5:$B$60,MATCH(E143,Catégories!$A$5:$A$60,0)),"?")) -> Dépense | I143: =IF(E143="","",IFERROR(INDEX(Catégories!$C$5:$C$60,MATCH(E143,Catégories!$A$5:$A$60,0)),"?")) -> Déductible | J143: =IF(E143="","",IFERROR(INDEX(Catégories!$D$5:$D$60,MATCH(E143,Catégories!$A$5:$A$60,0)),"?")) -> Frais de gestion | K143: =IF(H143="Recette",G143,IF(H143="Dépense",-G143,0)) -> -0.7 | L143: =IF(E143="",0,G143*IFERROR(INDEX(Catégories!$E$5:$E$60,MATCH(E143,Catégories!$A$5:$A$60,0)),0)) -> -0.7 | M143: Bien/04_Agence/2024-05_2026-11_AGENCE_Grand-livre-proprietaire.pdf | N143: Grand livre agence
A144: 45870 | B144: =IF(A144="","",YEAR(A144)) -> 2025 | C144: APPART-01 | D144: Agence | E144: Loyer hors charges | F144: GRATUITE DE LOYER suite REMPLACEMENT BALLON | G144: -107.46 | H144: =IF(E144="","",IFERROR(INDEX(Catégories!$B$5:$B$60,MATCH(E144,Catégories!$A$5:$A$60,0)),"?")) -> Recette | I144: =IF(E144="","",IFERROR(INDEX(Catégories!$C$5:$C$60,MATCH(E144,Catégories!$A$5:$A$60,0)),"?")) -> Imposable | J144: =IF(E144="","",IFERROR(INDEX(Catégories!$D$5:$D$60,MATCH(E144,Catégories!$A$5:$A$60,0)),"?")) -> Loyers | K144: =IF(H144="Recette",G144,IF(H144="Dépense",-G144,0)) -> -107.46 | L144: =IF(E144="",0,G144*IFERROR(INDEX(Catégories!$E$5:$E$60,MATCH(E144,Catégories!$A$5:$A$60,0)),0)) -> -107.46 | M144: Bien/04_Agence/2024-05_2026-11_AGENCE_Grand-livre-proprietaire.pdf | N144: Grand livre agence | O144: Remise de loyer accordée après le remplacement du ballon
A145: 45870 | B145: =IF(A145="","",YEAR(A145)) -> 2025 | C145: APPART-01 | D145: Agence | E145: Loyer hors charges | F145: LOYER PRINCIPAL (01/08/2025 - 31/08/2025) complement | G145: 107.46 | H145: =IF(E145="","",IFERROR(INDEX(Catégories!$B$5:$B$60,MATCH(E145,Catégories!$A$5:$A$60,0)),"?")) -> Recette | I145: =IF(E145="","",IFERROR(INDEX(Catégories!$C$5:$C$60,MATCH(E145,Catégories!$A$5:$A$60,0)),"?")) -> Imposable | J145: =IF(E145="","",IFERROR(INDEX(Catégories!$D$5:$D$60,MATCH(E145,Catégories!$A$5:$A$60,0)),"?")) -> Loyers | K145: =IF(H145="Recette",G145,IF(H145="Dépense",-G145,0)) -> 107.46 | L145: =IF(E145="",0,G145*IFERROR(INDEX(Catégories!$E$5:$E$60,MATCH(E145,Catégories!$A$5:$A$60,0)),0)) -> 107.46 | M145: Bien/04_Agence/2024-05_2026-11_AGENCE_Grand-livre-proprietaire.pdf | N145: Grand livre agence
A146: 45870 | B146: =IF(A146="","",YEAR(A146)) -> 2025 | C146: APPART-01 | D146: Agence | E146: Honoraires de gestion | F146: HONORAIRES GESTION LOYER PRINCIPAL (01/08/2025 - 31/08/2025) 6.00% | G146: 6.44 | H146: =IF(E146="","",IFERROR(INDEX(Catégories!$B$5:$B$60,MATCH(E146,Catégories!$A$5:$A$60,0)),"?")) -> Dépense | I146: =IF(E146="","",IFERROR(INDEX(Catégories!$C$5:$C$60,MATCH(E146,Catégories!$A$5:$A$60,0)),"?")) -> Déductible | J146: =IF(E146="","",IFERROR(INDEX(Catégories!$D$5:$D$60,MATCH(E146,Catégories!$A$5:$A$60,0)),"?")) -> Frais de gestion | K146: =IF(H146="Recette",G146,IF(H146="Dépense",-G146,0)) -> -6.44 | L146: =IF(E146="",0,G146*IFERROR(INDEX(Catégories!$E$5:$E$60,MATCH(E146,Catégories!$A$5:$A$60,0)),0)) -> -6.44 | M146: Bien/04_Agence/2024-05_2026-11_AGENCE_Grand-livre-proprietaire.pdf | N146: Grand livre agence
A147: 45870 | B147: =IF(A147="","",YEAR(A147)) -> 2025 | C147: APPART-01 | D147: Agence | E147: Honoraires de gestion | F147: TVA HONORAIRES GESTION LOYER PRINCIPAL (01/08/2025 - 31/08/2025) | G147: 1.29 | H147: =IF(E147="","",IFERROR(INDEX(Catégories!$B$5:$B$60,MATCH(E147,Catégories!$A$5:$A$60,0)),"?")) -> Dépense | I147: =IF(E147="","",IFERROR(INDEX(Catégories!$C$5:$C$60,MATCH(E147,Catégories!$A$5:$A$60,0)),"?")) -> Déductible | J147: =IF(E147="","",IFERROR(INDEX(Catégories!$D$5:$D$60,MATCH(E147,Catégories!$A$5:$A$60,0)),"?")) -> Frais de gestion | K147: =IF(H147="Recette",G147,IF(H147="Dépense",-G147,0)) -> -1.29 | L147: =IF(E147="",0,G147*IFERROR(INDEX(Catégories!$E$5:$E$60,MATCH(E147,Catégories!$A$5:$A$60,0)),0)) -> -1.29 | M147: Bien/04_Agence/2024-05_2026-11_AGENCE_Grand-livre-proprietaire.pdf | N147: Grand livre agence
A148: 45870 | B148: =IF(A148="","",YEAR(A148)) -> 2025 | C148: APPART-01 | D148: Agence | E148: Honoraires sur travaux | F148: HONORAIRES GESTION SUR TRAVAUX ARTISAN A 3% TTC | G148: 6.17 | H148: =IF(E148="","",IFERROR(INDEX(Catégories!$B$5:$B$60,MATCH(E148,Catégories!$A$5:$A$60,0)),"?")) -> Dépense | I148: =IF(E148="","",IFERROR(INDEX(Catégories!$C$5:$C$60,MATCH(E148,Catégories!$A$5:$A$60,0)),"?")) -> Déductible | J148: =IF(E148="","",IFERROR(INDEX(Catégories!$D$5:$D$60,MATCH(E148,Catégories!$A$5:$A$60,0)),"?")) -> Frais de gestion | K148: =IF(H148="Recette",G148,IF(H148="Dépense",-G148,0)) -> -6.17 | L148: =IF(E148="",0,G148*IFERROR(INDEX(Catégories!$E$5:$E$60,MATCH(E148,Catégories!$A$5:$A$60,0)),0)) -> -6.17 | M148: Bien/04_Agence/2024-05_2026-11_AGENCE_Grand-livre-proprietaire.pdf | N148: Grand livre agence
A149: 45870 | B149: =IF(A149="","",YEAR(A149)) -> 2025 | C149: APPART-01 | D149: Agence | E149: Honoraires sur travaux | F149: TVA HONORAIRES GESTION SUR TRAVAUX ARTISAN A 3% TTC | G149: 1.24 | H149: =IF(E149="","",IFERROR(INDEX(Catégories!$B$5:$B$60,MATCH(E149,Catégories!$A$5:$A$60,0)),"?")) -> Dépense | I149: =IF(E149="","",IFERROR(INDEX(Catégories!$C$5:$C$60,MATCH(E149,Catégories!$A$5:$A$60,0)),"?")) -> Déductible | J149: =IF(E149="","",IFERROR(INDEX(Catégories!$D$5:$D$60,MATCH(E149,Catégories!$A$5:$A$60,0)),"?")) -> Frais de gestion | K149: =IF(H149="Recette",G149,IF(H149="Dépense",-G149,0)) -> -1.24 | L149: =IF(E149="",0,G149*IFERROR(INDEX(Catégories!$E$5:$E$60,MATCH(E149,Catégories!$A$5:$A$60,0)),0)) -> -1.24 | M149: Bien/04_Agence/2024-05_2026-11_AGENCE_Grand-livre-proprietaire.pdf | N149: Grand livre agence
A150: 45870 | B150: =IF(A150="","",YEAR(A150)) -> 2025 | C150: APPART-01 | D150: Agence | E150: Honoraires sur travaux | F150: HONORAIRES GESTION SUR TRAVAUX ARTISAN A 3% TTC | G150: 39.75 | H150: =IF(E150="","",IFERROR(INDEX(Catégories!$B$5:$B$60,MATCH(E150,Catégories!$A$5:$A$60,0)),"?")) -> Dépense | I150: =IF(E150="","",IFERROR(INDEX(Catégories!$C$5:$C$60,MATCH(E150,Catégories!$A$5:$A$60,0)),"?")) -> Déductible | J150: =IF(E150="","",IFERROR(INDEX(Catégories!$D$5:$D$60,MATCH(E150,Catégories!$A$5:$A$60,0)),"?")) -> Frais de gestion | K150: =IF(H150="Recette",G150,IF(H150="Dépense",-G150,0)) -> -39.75 | L150: =IF(E150="",0,G150*IFERROR(INDEX(Catégories!$E$5:$E$60,MATCH(E150,Catégories!$A$5:$A$60,0)),0)) -> -39.75 | M150: Bien/04_Agence/2024-05_2026-11_AGENCE_Grand-livre-proprietaire.pdf | N150: Grand livre agence
...

Sheet Biens
A1: Biens
A2: Une ligne par bien. Les cellules jaunes sont à renseigner. L'identifiant (colonne A) relie le bien au journal, aux prêts et aux amortissements.
A4: Identifiant | B4: Nom | C4: Adresse | D4: Code postal | E4: Ville | F4: Type de location | G4: Régime fiscal | H4: Date d'acquisition | I4: Prix d'achat (net vendeur) | J4: dont mobilier | K4: Frais d'agence (achat) | L4: Frais de notaire et de garantie | M4: Coût total d'acquisition | N4: Apport personnel | O4: Date de mise en location | P4: Valeur estimée actuelle | Q4: Surface (m²) | R4: Gestionnaire | S4: Syndic | T4: Loyer hors charges actuel | U4: Provision sur charges | V4: Dépôt de garantie
A5: APPART-01 | B5: Appartement exemple | C5: 1 rue de l'Exemple | E5: Exempleville | F5: Meublée | G5: LMNP réel | H5: 43049 | I5: 239010 | J5: 7440 | K5: 9300 | L5: 19848.99 | M5: =IF(A5="","",I5+K5+L5) -> 268158.99 | N5: 97968.99 | O5: 45430 | P5: 283650 | Q5: 40.03 | R5: Agence exemple (6 % HT) | S5: Syndic exemple | T5: 1054.89 | U5: 83.7 | V5: 2064.6
M6: =IF(A6="","",I6+K6+L6)
M7: =IF(A7="","",I7+K7+L7)
M8: =IF(A8="","",I8+K8+L8)
M9: =IF(A9="","",I9+K9+L9)
M10: =IF(A10="","",I10+K10+L10)
M11: =IF(A11="","",I11+K11+L11)
M12: =IF(A12="","",I12+K12+L12)
M13: =IF(A13="","",I13+K13+L13)
M14: =IF(A14="","",I14+K14+L14)
M15: =IF(A15="","",I15+K15+L15)
M16: =IF(A16="","",I16+K16+L16)
M17: =IF(A17="","",I17+K17+L17)
... M30: =IF(A30="","",I30+K30+L30)

Sheet Catégories
A1: Catégories
A2: Chaque catégorie détermine le sens du mouvement, son traitement fiscal (LMNP réel) et son groupe dans la synthèse. Les intérêts et le capital du prêt ne passent pas par le journal : ils viennent de l'onglet Échéancier.
A4: Catégorie | B4: Sens | C4: Traitement fiscal (LMNP réel) | D4: Groupe (synthèse) | E4: Signe trésorerie | F4: Description
A5: Loyer hors charges | B5: Recette | C5: Imposable | D5: Loyers | E5: 1 | F5: Loyer brut, avant honoraires (une remise de loyer se saisit en montant négatif)
A6: Provisions sur charges | B6: Recette | C6: Imposable | D6: Charges refacturées | E6: 1 | F6: Provisions mensuelles payées par le locataire
A7: Régularisation de charges locataire | B7: Recette | C7: Imposable | D7: Charges refacturées | E7: 1 | F7: Solde annuel réclamé (ou rendu, en négatif) au locataire
A8: Taxe ordures ménagères refacturée | B8: Recette | C8: Imposable | D8: Charges refacturées | E8: 1 | F8: TEOM refacturée au locataire
A9: Autres recettes | B9: Recette | C9: Imposable | D9: Autres recettes | E9: 1 | F9: Indemnités, refacturations diverses
A10: Honoraires de gestion | B10: Dépense | C10: Déductible | D10: Frais de gestion | E10: -1 | F10: Honoraires de l'agence, TVA comprise
A11: Honoraires de mise en location | B11: Dépense | C11: Déductible | D11: Frais de gestion | E11: -1 | F11: Recherche de locataire, état des lieux
A12: Honoraires sur travaux | B12: Dépense | C12: Déductible | D12: Frais de gestion | E12: -1 | F12: Commission de l'agence sur les travaux
A13: Honoraires comptable | B13: Dépense | C13: Déductible | D13: Frais de gestion | E13: -1 | F13: Expert-comptable, centre de gestion
A14: Charges de copropriété | B14: Dépense | C14: Déductible | D14: Copropriété | E14: -1 | F14: Appels de fonds payés au syndic (charges, travaux, fonds de travaux)
A15: Assurance PNO | B15: Dépense | C15: Déductible | D15: Assurances | E15: -1 | F15: Assurance propriétaire non occupant, loyers impayés
A16: Taxe foncière | B16: Dépense | C16: Déductible | D16: Impôts et taxes | E16: -1 | F16: Taxe foncière (TEOM incluse)
... A28: Dépôt de garantie restitué | B28: Neutre | C28: Non fiscal | D28: Dépôt de garantie | E28: -1 | F28: Restitution au locataire

Sheet Prêts
A1: Prêts
A2: Une ligne par prêt. Le tableau d'amortissement de la banque se colle dans l'onglet Échéancier.
A4: Identifiant | B4: Bien | C4: Banque | D4: Libellé | E4: Montant emprunté | F4: Taux (hors assurance) | G4: Durée (mois) | H4: 1re échéance | I4: Dernière échéance | J4: Assurance mensuelle | K4: Capital restant dû (date d'arrêté)
A5: P1 | B5: APPART-01 | C5: BANQUE | D5: Prêt immobilier amortissable | E5: 170190 | F5: 0.015 | G5: 240 | H5: 43074 | I5: 50349 | J5: 20.08 | K5: =IF(A5="","",E5-SUMIFS(Échéancier!$F$5:$F$300,Échéancier!$A$5:$A$300,A5,Échéancier!$C$5:$C$300,"<="&Synthèse!$C$4)) -> 100571
K6: =IF(A6="","",E6-SUMIFS(Échéancier!$F$5:$F$300,Échéancier!$A$5:$A$300,A6,Échéancier!$C$5:$C$300,"<="&Synthèse!$C$4))
K7: =IF(A7="","",E7-SUMIFS(Échéancier!$F$5:$F$300,Échéancier!$A$5:$A$300,A7,Échéancier!$C$5:$C$300,"<="&Synthèse!$C$4))
K8: =IF(A8="","",E8-SUMIFS(Échéancier!$F$5:$F$300,Échéancier!$A$5:$A$300,A8,Échéancier!$C$5:$C$300,"<="&Synthèse!$C$4))
K9: =IF(A9="","",E9-SUMIFS(Échéancier!$F$5:$F$300,Échéancier!$A$5:$A$300,A9,Échéancier!$C$5:$C$300,"<="&Synthèse!$C$4))
K10: =IF(A10="","",E10-SUMIFS(Échéancier!$F$5:$F$300,Échéancier!$A$5:$A$300,A10,Échéancier!$C$5:$C$300,"<="&Synthèse!$C$4))
K11: =IF(A11="","",E11-SUMIFS(Échéancier!$F$5:$F$300,Échéancier!$A$5:$A$300,A11,Échéancier!$C$5:$C$300,"<="&Synthèse!$C$4))
K12: =IF(A12="","",E12-SUMIFS(Échéancier!$F$5:$F$300,Échéancier!$A$5:$A$300,A12,Échéancier!$C$5:$C$300,"<="&Synthèse!$C$4))
K13: =IF(A13="","",E13-SUMIFS(Échéancier!$F$5:$F$300,Échéancier!$A$5:$A$300,A13,Échéancier!$C$5:$C$300,"<="&Synthèse!$C$4))
K14: =IF(A14="","",E14-SUMIFS(Échéancier!$F$5:$F$300,Échéancier!$A$5:$A$300,A14,Échéancier!$C$5:$C$300,"<="&Synthèse!$C$4))

Sheet Échéancier
A1: Échéancier des prêts
A2: Source : tableau d'amortissement BANQUE du 03/03/2026 (02_Pret). Une ligne par échéance ; colonnes grises calculées. « Période louée » = 1 si l'échéance tombe après la mise en location du bien.
A4: Prêt | B4: N° | C4: Date | D4: Année | E4: Capital dû avant échéance | F4: Capital | G4: Intérêts | H4: Assurance | I4: Échéance totale | J4: Bien | K4: Période louée
A5: P1 | B5: 1 | C5: 43074 | D5: =IF(C5="","",YEAR(C5)) -> 2017 | E5: 170190 | F5: 608.51 | G5: 196.31 | H5: 18.75 | I5: =IF(C5="","",F5+G5+H5) -> 823.57 | J5: =IF(A5="","",IFERROR(INDEX(Prêts!$B$5:$B$14,MATCH(A5,Prêts!$A$5:$A$14,0)),"?")) -> APPART-01 | K5: =IF(A5="",0,IF(C5>=IFERROR(INDEX(Biens!$O$5:$O$30,MATCH(J5,Biens!$A$5:$A$30,0)),99999),1,0)) -> 0
A6: P1 | B6: 2 | C6: 43105 | D6: =IF(C6="","",YEAR(C6)) -> 2018 | E6: 169581.49 | F6: 609.27 | G6: 211.97 | H6: 20.08 | I6: =IF(C6="","",F6+G6+H6) -> 841.32 | J6: =IF(A6="","",IFERROR(INDEX(Prêts!$B$5:$B$14,MATCH(A6,Prêts!$A$5:$A$14,0)),"?")) -> APPART-01 | K6: =IF(A6="",0,IF(C6>=IFERROR(INDEX(Biens!$O$5:$O$30,MATCH(J6,Biens!$A$5:$A$30,0)),99999),1,0)) -> 0
A7: P1 | B7: 3 | C7: 43136 | D7: =IF(C7="","",YEAR(C7)) -> 2018 | E7: 168972.22 | F7: 610.03 | G7: 211.21 | H7: 20.08 | I7: =IF(C7="","",F7+G7+H7) -> 841.32 | J7: =IF(A7="","",IFERROR(INDEX(Prêts!$B$5:$B$14,MATCH(A7,Prêts!$A$5:$A$14,0)),"?")) -> APPART-01 | K7: =IF(A7="",0,IF(C7>=IFERROR(INDEX(Biens!$O$5:$O$30,MATCH(J7,Biens!$A$5:$A$30,0)),99999),1,0)) -> 0
A8: P1 | B8: 4 | C8: 43164 | D8: =IF(C8="","",YEAR(C8)) -> 2018 | E8: 168362.19 | F8: 610.8 | G8: 210.45 | H8: 20.08 | I8: =IF(C8="","",F8+G8+H8) -> 841.33 | J8: =IF(A8="","",IFERROR(INDEX(Prêts!$B$5:$B$14,MATCH(A8,Prêts!$A$5:$A$14,0)),"?")) -> APPART-01 | K8: =IF(A8="",0,IF(C8>=IFERROR(INDEX(Biens!$O$5:$O$30,MATCH(J8,Biens!$A$5:$A$30,0)),99999),1,0)) -> 0
A9: P1 | B9: 5 | C9: 43195 | D9: =IF(C9="","",YEAR(C9)) -> 2018 | E9: 167751.39 | F9: 611.56 | G9: 209.69 | H9: 20.08 | I9: =IF(C9="","",F9+G9+H9) -> 841.33 | J9: =IF(A9="","",IFERROR(INDEX(Prêts!$B$5:$B$14,MATCH(A9,Prêts!$A$5:$A$14,0)),"?")) -> APPART-01 | K9: =IF(A9="",0,IF(C9>=IFERROR(INDEX(Biens!$O$5:$O$30,MATCH(J9,Biens!$A$5:$A$30,0)),99999),1,0)) -> 0
A10: P1 | B10: 6 | C10: 43225 | D10: =IF(C10="","",YEAR(C10)) -> 2018 | E10: 167139.83 | F10: 612.32 | G10: 208.92 | H10: 20.08 | I10: =IF(C10="","",F10+G10+H10) -> 841.32 | J10: =IF(A10="","",IFERROR(INDEX(Prêts!$B$5:$B$14,MATCH(A10,Prêts!$A$5:$A$14,0)),"?")) -> APPART-01 | K10: =IF(A10="",0,IF(C10>=IFERROR(INDEX(Biens!$O$5:$O$30,MATCH(J10,Biens!$A$5:$A$30,0)),99999),1,0)) -> 0
A11: P1 | B11: 7 | C11: 43256 | D11: =IF(C11="","",YEAR(C11)) -> 2018 | E11: 166527.51 | F11: 613.08 | G11: 208.16 | H11: 20.08 | I11: =IF(C11="","",F11+G11+H11) -> 841.32 | J11: =IF(A11="","",IFERROR(INDEX(Prêts!$B$5:$B$14,MATCH(A11,Prêts!$A$5:$A$14,0)),"?")) -> APPART-01 | K11: =IF(A11="",0,IF(C11>=IFERROR(INDEX(Biens!$O$5:$O$30,MATCH(J11,Biens!$A$5:$A$30,0)),99999),1,0)) -> 0
A12: P1 | B12: 8 | C12: 43286 | D12: =IF(C12="","",YEAR(C12)) -> 2018 | E12: 165914.43 | F12: 613.86 | G12: 207.39 | H12: 20.08 | I12: =IF(C12="","",F12+G12+H12) -> 841.33 | J12: =IF(A12="","",IFERROR(INDEX(Prêts!$B$5:$B$14,MATCH(A12,Prêts!$A$5:$A$14,0)),"?")) -> APPART-01 | K12: =IF(A12="",0,IF(C12>=IFERROR(INDEX(Biens!$O$5:$O$30,MATCH(J12,Biens!$A$5:$A$30,0)),99999),1,0)) -> 0
A13: P1 | B13: 9 | C13: 43317 | D13: =IF(C13="","",YEAR(C13)) -> 2018 | E13: 165300.57 | F13: 614.62 | G13: 206.63 | H13: 20.08 | I13: =IF(C13="","",F13+G13+H13) -> 841.33 | J13: =IF(A13="","",IFERROR(INDEX(Prêts!$B$5:$B$14,MATCH(A13,Prêts!$A$5:$A$14,0)),"?")) -> APPART-01 | K13: =IF(A13="",0,IF(C13>=IFERROR(INDEX(Biens!$O$5:$O$30,MATCH(J13,Biens!$A$5:$A$30,0)),99999),1,0)) -> 0
A14: P1 | B14: 10 | C14: 43348 | D14: =IF(C14="","",YEAR(C14)) -> 2018 | E14: 164685.95 | F14: 615.39 | G14: 205.86 | H14: 20.08 | I14: =IF(C14="","",F14+G14+H14) -> 841.33 | J14: =IF(A14="","",IFERROR(INDEX(Prêts!$B$5:$B$14,MATCH(A14,Prêts!$A$5:$A$14,0)),"?")) -> APPART-01 | K14: =IF(A14="",0,IF(C14>=IFERROR(INDEX(Biens!$O$5:$O$30,MATCH(J14,Biens!$A$5:$A$30,0)),99999),1,0)) -> 0
A15: P1 | B15: 11 | C15: 43378 | D15: =IF(C15="","",YEAR(C15)) -> 2018 | E15: 164070.56 | F15: 616.16 | G15: 205.08 | H15: 20.08 | I15: =IF(C15="","",F15+G15+H15) -> 841.32 | J15: =IF(A15="","",IFERROR(INDEX(Prêts!$B$5:$B$14,MATCH(A15,Prêts!$A$5:$A$14,0)),"?")) -> APPART-01 | K15: =IF(A15="",0,IF(C15>=IFERROR(INDEX(Biens!$O$5:$O$30,MATCH(J15,Biens!$A$5:$A$30,0)),99999),1,0)) -> 0
A16: P1 | B16: 12 | C16: 43409 | D16: =IF(C16="","",YEAR(C16)) -> 2018 | E16: 163454.4 | F16: 616.92 | G16: 204.32 | H16: 20.08 | I16: =IF(C16="","",F16+G16+H16) -> 841.32 | J16: =IF(A16="","",IFERROR(INDEX(Prêts!$B$5:$B$14,MATCH(A16,Prêts!$A$5:$A$14,0)),"?")) -> APPART-01 | K16: =IF(A16="",0,IF(C16>=IFERROR(INDEX(Biens!$O$5:$O$30,MATCH(J16,Biens!$A$5:$A$30,0)),99999),1,0)) -> 0
... A244: P1 | B244: 240 | C244: 50349 | D244: =IF(C244="","",YEAR(C244)) -> 2037 | E244: 819.63 | F244: 819.63 | G244: 1.02 | H244: 11.27 | I244: =IF(C244="","",F244+G244+H244) -> 831.92 | J244: =IF(A244="","",IFERROR(INDEX(Prêts!$B$5:$B$14,MATCH(A244,Prêts!$A$5:$A$14,0)),"?")) -> APPART-01 | K244: =IF(A244="",0,IF(C244>=IFERROR(INDEX(Biens!$O$5:$O$30,MATCH(J244,Biens!$A$5:$A$30,0)),99999),1,0)) -> 1
D245: =IF(C245="","",YEAR(C245)) | I245: =IF(C245="","",F245+G245+H245) | J245: =IF(A245="","",IFERROR(INDEX(Prêts!$B$5:$B$14,MATCH(A245,Prêts!$A$5:$A$14,0)),"?")) | K245: =IF(A245="",0,IF(C245>=IFERROR(INDEX(Biens!$O$5:$O$30,MATCH(J245,Biens!$A$5:$A$30,0)),99999),1,0)) -> 0
D246: =IF(C246="","",YEAR(C246)) | I246: =IF(C246="","",F246+G246+H246) | J246: =IF(A246="","",IFERROR(INDEX(Prêts!$B$5:$B$14,MATCH(A246,Prêts!$A$5:$A$14,0)),"?")) | K246: =IF(A246="",0,IF(C246>=IFERROR(INDEX(Biens!$O$5:$O$30,MATCH(J246,Biens!$A$5:$A$30,0)),99999),1,0)) -> 0
D247: =IF(C247="","",YEAR(C247)) | I247: =IF(C247="","",F247+G247+H247) | J247: =IF(A247="","",IFERROR(INDEX(Prêts!$B$5:$B$14,MATCH(A247,Prêts!$A$5:$A$14,0)),"?")) | K247: =IF(A247="",0,IF(C247>=IFERROR(INDEX(Biens!$O$5:$O$30,MATCH(J247,Biens!$A$5:$A$30,0)),99999),1,0)) -> 0
D248: =IF(C248="","",YEAR(C248)) | I248: =IF(C248="","",F248+G248+H248) | J248: =IF(A248="","",IFERROR(INDEX(Prêts!$B$5:$B$14,MATCH(A248,Prêts!$A$5:$A$14,0)),"?")) | K248: =IF(A248="",0,IF(C248>=IFERROR(INDEX(Biens!$O$5:$O$30,MATCH(J248,Biens!$A$5:$A$30,0)),99999),1,0)) -> 0
D249: =IF(C249="","",YEAR(C249)) | I249: =IF(C249="","",F249+G249+H249) | J249: =IF(A249="","",IFERROR(INDEX(Prêts!$B$5:$B$14,MATCH(A249,Prêts!$A$5:$A$14,0)),"?")) | K249: =IF(A249="",0,IF(C249>=IFERROR(INDEX(Biens!$O$5:$O$30,MATCH(J249,Biens!$A$5:$A$30,0)),99999),1,0)) -> 0
D250: =IF(C250="","",YEAR(C250)) | I250: =IF(C250="","",F250+G250+H250) | J250: =IF(A250="","",IFERROR(INDEX(Prêts!$B$5:$B$14,MATCH(A250,Prêts!$A$5:$A$14,0)),"?")) | K250: =IF(A250="",0,IF(C250>=IFERROR(INDEX(Biens!$O$5:$O$30,MATCH(J250,Biens!$A$5:$A$30,0)),99999),1,0)) -> 0
D251: =IF(C251="","",YEAR(C251)) | I251: =IF(C251="","",F251+G251+H251) | J251: =IF(A251="","",IFERROR(INDEX(Prêts!$B$5:$B$14,MATCH(A251,Prêts!$A$5:$A$14,0)),"?")) | K251: =IF(A251="",0,IF(C251>=IFERROR(INDEX(Biens!$O$5:$O$30,MATCH(J251,Biens!$A$5:$A$30,0)),99999),1,0)) -> 0
D252: =IF(C252="","",YEAR(C252)) | I252: =IF(C252="","",F252+G252+H252) | J252: =IF(A252="","",IFERROR(INDEX(Prêts!$B$5:$B$14,MATCH(A252,Prêts!$A$5:$A$14,0)),"?")) | K252: =IF(A252="",0,IF(C252>=IFERROR(INDEX(Biens!$O$5:$O$30,MATCH(J252,Biens!$A$5:$A$30,0)),99999),1,0)) -> 0
D253: =IF(C253="","",YEAR(C253)) | I253: =IF(C253="","",F253+G253+H253) | J253: =IF(A253="","",IFERROR(INDEX(Prêts!$B$5:$B$14,MATCH(A253,Prêts!$A$5:$A$14,0)),"?")) | K253: =IF(A253="",0,IF(C253>=IFERROR(INDEX(Biens!$O$5:$O$30,MATCH(J253,Biens!$A$5:$A$30,0)),99999),1,0)) -> 0
D254: =IF(C254="","",YEAR(C254)) | I254: =IF(C254="","",F254+G254+H254) | J254: =IF(A254="","",IFERROR(INDEX(Prêts!$B$5:$B$14,MATCH(A254,Prêts!$A$5:$A$14,0)),"?")) | K254: =IF(A254="",0,IF(C254>=IFERROR(INDEX(Biens!$O$5:$O$30,MATCH(J254,Biens!$A$5:$A$30,0)),99999),1,0)) -> 0
D255: =IF(C255="","",YEAR(C255)) | I255: =IF(C255="","",F255+G255+H255) | J255: =IF(A255="","",IFERROR(INDEX(Prêts!$B$5:$B$14,MATCH(A255,Prêts!$A$5:$A$14,0)),"?")) | K255: =IF(A255="",0,IF(C255>=IFERROR(INDEX(Biens!$O$5:$O$30,MATCH(J255,Biens!$A$5:$A$30,0)),99999),1,0)) -> 0
D256: =IF(C256="","",YEAR(C256)) | I256: =IF(C256="","",F256+G256+H256) | J256: =IF(A256="","",IFERROR(INDEX(Prêts!$B$5:$B$14,MATCH(A256,Prêts!$A$5:$A$14,0)),"?")) | K256: =IF(A256="",0,IF(C256>=IFERROR(INDEX(Biens!$O$5:$O$30,MATCH(J256,Biens!$A$5:$A$30,0)),99999),1,0)) -> 0
... D300: =IF(C300="","",YEAR(C300)) | I300: =IF(C300="","",F300+G300+H300) | J300: =IF(A300="","",IFERROR(INDEX(Prêts!$B$5:$B$14,MATCH(A300,Prêts!$A$5:$A$14,0)),"?")) | K300: =IF(A300="",0,IF(C300>=IFERROR(INDEX(Biens!$O$5:$O$30,MATCH(J300,Biens!$A$5:$A$30,0)),99999),1,0)) -> 0

Sheet Amortissements
A1: Amortissements (LMNP réel)
A2: Une ligne par composant ou équipement immobilisé. Dotation linéaire au prorata des jours (base 365). Le terrain ne s'amortit pas.
A4: Bien | B4: Composant | C4: Date de mise en service | D4: Valeur | E4: Durée (années) | F4: Dotation annuelle | G4: Fin d'amortissement | H4: 2024 | I4: 2025 | J4: 2026 | K4: 2027 | L4: 2028 | M4: Commentaire
A5: APPART-01 | B5: Terrain | C5: 45430 | D5: 86490 | E5: 0 | F5: =IF(OR(A5="",E5=0),0,D5/E5) -> 0 | G5: =IF(OR(A5="",E5=0),"",EDATE(C5,ROUND(E5*12,0))-1) | H5: =IF(OR($A5="",$E5=0),0,MIN($F5,MAX(0,MIN(DATE(H$4,12,31),$G5)-MAX(DATE(H$4,1,1),$C5)+1)*$F5/365)) -> 0 | I5: =IF(OR($A5="",$E5=0),0,MIN($F5,MAX(0,MIN(DATE(I$4,12,31),$G5)-MAX(DATE(I$4,1,1),$C5)+1)*$F5/365)) -> 0 | J5: =IF(OR($A5="",$E5=0),0,MIN($F5,MAX(0,MIN(DATE(J$4,12,31),$G5)-MAX(DATE(J$4,1,1),$C5)+1)*$F5/365)) -> 0 | K5: =IF(OR($A5="",$E5=0),0,MIN($F5,MAX(0,MIN(DATE(K$4,12,31),$G5)-MAX(DATE(K$4,1,1),$C5)+1)*$F5/365)) -> 0 | L5: =IF(OR($A5="",$E5=0),0,MIN($F5,MAX(0,MIN(DATE(L$4,12,31),$G5)-MAX(DATE(L$4,1,1),$C5)+1)*$F5/365)) -> 0 | M5: Non amortissable. Valeur retenue par le comptable (comptes 2024).
A6: APPART-01 | B6: Bâtiment | C6: 45430 | D6: 201810 | E6: 22.388075 | F6: =IF(OR(A6="",E6=0),0,D6/E6) -> 9014.1738 | G6: =IF(OR(A6="",E6=0),"",EDATE(C6,ROUND(E6*12,0))-1) -> 53617 | H6: =IF(OR($A6="",$E6=0),0,MIN($F6,MAX(0,MIN(DATE(H$4,12,31),$G6)-MAX(DATE(H$4,1,1),$C6)+1)*$F6/365)) -> 5630.7716 | I6: =IF(OR($A6="",$E6=0),0,MIN($F6,MAX(0,MIN(DATE(I$4,12,31),$G6)-MAX(DATE(I$4,1,1),$C6)+1)*$F6/365)) -> 9014.1738 | J6: =IF(OR($A6="",$E6=0),0,MIN($F6,MAX(0,MIN(DATE(J$4,12,31),$G6)-MAX(DATE(J$4,1,1),$C6)+1)*$F6/365)) -> 9014.1738 | K6: =IF(OR($A6="",$E6=0),0,MIN($F6,MAX(0,MIN(DATE(K$4,12,31),$G6)-MAX(DATE(K$4,1,1),$C6)+1)*$F6/365)) -> 9014.1738 | L6: =IF(OR($A6="",$E6=0),0,MIN($F6,MAX(0,MIN(DATE(L$4,12,31),$G6)-MAX(DATE(L$4,1,1),$C6)+1)*$F6/365)) -> 9014.1738 | M6: Valeur retenue par le comptable. Durée moyenne déduite des comptes 2025 (dotation 9 014,17 €) : à remplacer par le plan par composants du comptable.
A7: APPART-01 | B7: Réfrigérateur | C7: 45454 | D7: 1076.01 | E7: 5 | F7: =IF(OR(A7="",E7=0),0,D7/E7) -> 215.202 | G7: =IF(OR(A7="",E7=0),"",EDATE(C7,ROUND(E7*12,0))-1) -> 47279 | H7: =IF(OR($A7="",$E7=0),0,MIN($F7,MAX(0,MIN(DATE(H$4,12,31),$G7)-MAX(DATE(H$4,1,1),$C7)+1)*$F7/365)) -> 120.27728 | I7: =IF(OR($A7="",$E7=0),0,MIN($F7,MAX(0,MIN(DATE(I$4,12,31),$G7)-MAX(DATE(I$4,1,1),$C7)+1)*$F7/365)) -> 215.202 | J7: =IF(OR($A7="",$E7=0),0,MIN($F7,MAX(0,MIN(DATE(J$4,12,31),$G7)-MAX(DATE(J$4,1,1),$C7)+1)*$F7/365)) -> 215.202 | K7: =IF(OR($A7="",$E7=0),0,MIN($F7,MAX(0,MIN(DATE(K$4,12,31),$G7)-MAX(DATE(K$4,1,1),$C7)+1)*$F7/365)) -> 215.202 | L7: =IF(OR($A7="",$E7=0),0,MIN($F7,MAX(0,MIN(DATE(L$4,12,31),$G7)-MAX(DATE(L$4,1,1),$C7)+1)*$F7/365)) -> 215.202 | M7: Durée et date déduites des comptes 2024 (dotation 120,28 €).
A8: APPART-01 | B8: Ballon d'eau chaude | C8: 45867 | D8: 1590.11 | E8: 10 | F8: =IF(OR(A8="",E8=0),0,D8/E8) -> 159.011 | G8: =IF(OR(A8="",E8=0),"",EDATE(C8,ROUND(E8*12,0))-1) -> 49518 | H8: =IF(OR($A8="",$E8=0),0,MIN($F8,MAX(0,MIN(DATE(H$4,12,31),$G8)-MAX(DATE(H$4,1,1),$C8)+1)*$F8/365)) -> 0 | I8: =IF(OR($A8="",$E8=0),0,MIN($F8,MAX(0,MIN(DATE(I$4,12,31),$G8)-MAX(DATE(I$4,1,1),$C8)+1)*$F8/365)) -> 67.960866 | J8: =IF(OR($A8="",$E8=0),0,MIN($F8,MAX(0,MIN(DATE(J$4,12,31),$G8)-MAX(DATE(J$4,1,1),$C8)+1)*$F8/365)) -> 159.011 | K8: =IF(OR($A8="",$E8=0),0,MIN($F8,MAX(0,MIN(DATE(K$4,12,31),$G8)-MAX(DATE(K$4,1,1),$C8)+1)*$F8/365)) -> 159.011 | L8: =IF(OR($A8="",$E8=0),0,MIN($F8,MAX(0,MIN(DATE(L$4,12,31),$G8)-MAX(DATE(L$4,1,1),$C8)+1)*$F8/365)) -> 159.011 | M8: Durée et date déduites des comptes 2025 (dotation 67,96 €) : à confirmer.
A9: APPART-01 | B9: Mobilier acquis en 2017 (acte de vente) | C9: 43049 | D9: 7440 | E9: 0 | F9: =IF(OR(A9="",E9=0),0,D9/E9) -> 0 | G9: =IF(OR(A9="",E9=0),"",EDATE(C9,ROUND(E9*12,0))-1) | H9: =IF(OR($A9="",$E9=0),0,MIN($F9,MAX(0,MIN(DATE(H$4,12,31),$G9)-MAX(DATE(H$4,1,1),$C9)+1)*$F9/365)) -> 0 | I9: =IF(OR($A9="",$E9=0),0,MIN($F9,MAX(0,MIN(DATE(I$4,12,31),$G9)-MAX(DATE(I$4,1,1),$C9)+1)*$F9/365)) -> 0 | J9: =IF(OR($A9="",$E9=0),0,MIN($F9,MAX(0,MIN(DATE(J$4,12,31),$G9)-MAX(DATE(J$4,1,1),$C9)+1)*$F9/365)) -> 0 | K9: =IF(OR($A9="",$E9=0),0,MIN($F9,MAX(0,MIN(DATE(K$4,12,31),$G9)-MAX(DATE(K$4,1,1),$C9)+1)*$F9/365)) -> 0 | L9: =IF(OR($A9="",$E9=0),0,MIN($F9,MAX(0,MIN(DATE(L$4,12,31),$G9)-MAX(DATE(L$4,1,1),$C9)+1)*$F9/365)) -> 0 | M9: Non amorti par le comptable : question à lui poser (durée 0 = non amorti).
F10: =IF(OR(A10="",E10=0),0,D10/E10) -> 0 | G10: =IF(OR(A10="",E10=0),"",EDATE(C10,ROUND(E10*12,0))-1) | H10: =IF(OR($A10="",$E10=0),0,MIN($F10,MAX(0,MIN(DATE(H$4,12,31),$G10)-MAX(DATE(H$4,1,1),$C10)+1)*$F10/365)) -> 0 | I10: =IF(OR($A10="",$E10=0),0,MIN($F10,MAX(0,MIN(DATE(I$4,12,31),$G10)-MAX(DATE(I$4,1,1),$C10)+1)*$F10/365)) -> 0 | J10: =IF(OR($A10="",$E10=0),0,MIN($F10,MAX(0,MIN(DATE(J$4,12,31),$G10)-MAX(DATE(J$4,1,1),$C10)+1)*$F10/365)) -> 0 | K10: =IF(OR($A10="",$E10=0),0,MIN($F10,MAX(0,MIN(DATE(K$4,12,31),$G10)-MAX(DATE(K$4,1,1),$C10)+1)*$F10/365)) -> 0 | L10: =IF(OR($A10="",$E10=0),0,MIN($F10,MAX(0,MIN(DATE(L$4,12,31),$G10)-MAX(DATE(L$4,1,1),$C10)+1)*$F10/365)) -> 0
F11: =IF(OR(A11="",E11=0),0,D11/E11) -> 0 | G11: =IF(OR(A11="",E11=0),"",EDATE(C11,ROUND(E11*12,0))-1) | H11: =IF(OR($A11="",$E11=0),0,MIN($F11,MAX(0,MIN(DATE(H$4,12,31),$G11)-MAX(DATE(H$4,1,1),$C11)+1)*$F11/365)) -> 0 | I11: =IF(OR($A11="",$E11=0),0,MIN($F11,MAX(0,MIN(DATE(I$4,12,31),$G11)-MAX(DATE(I$4,1,1),$C11)+1)*$F11/365)) -> 0 | J11: =IF(OR($A11="",$E11=0),0,MIN($F11,MAX(0,MIN(DATE(J$4,12,31),$G11)-MAX(DATE(J$4,1,1),$C11)+1)*$F11/365)) -> 0 | K11: =IF(OR($A11="",$E11=0),0,MIN($F11,MAX(0,MIN(DATE(K$4,12,31),$G11)-MAX(DATE(K$4,1,1),$C11)+1)*$F11/365)) -> 0 | L11: =IF(OR($A11="",$E11=0),0,MIN($F11,MAX(0,MIN(DATE(L$4,12,31),$G11)-MAX(DATE(L$4,1,1),$C11)+1)*$F11/365)) -> 0
F12: =IF(OR(A12="",E12=0),0,D12/E12) -> 0 | G12: =IF(OR(A12="",E12=0),"",EDATE(C12,ROUND(E12*12,0))-1) | H12: =IF(OR($A12="",$E12=0),0,MIN($F12,MAX(0,MIN(DATE(H$4,12,31),$G12)-MAX(DATE(H$4,1,1),$C12)+1)*$F12/365)) -> 0 | I12: =IF(OR($A12="",$E12=0),0,MIN($F12,MAX(0,MIN(DATE(I$4,12,31),$G12)-MAX(DATE(I$4,1,1),$C12)+1)*$F12/365)) -> 0 | J12: =IF(OR($A12="",$E12=0),0,MIN($F12,MAX(0,MIN(DATE(J$4,12,31),$G12)-MAX(DATE(J$4,1,1),$C12)+1)*$F12/365)) -> 0 | K12: =IF(OR($A12="",$E12=0),0,MIN($F12,MAX(0,MIN(DATE(K$4,12,31),$G12)-MAX(DATE(K$4,1,1),$C12)+1)*$F12/365)) -> 0 | L12: =IF(OR($A12="",$E12=0),0,MIN($F12,MAX(0,MIN(DATE(L$4,12,31),$G12)-MAX(DATE(L$4,1,1),$C12)+1)*$F12/365)) -> 0
F13: =IF(OR(A13="",E13=0),0,D13/E13) -> 0 | G13: =IF(OR(A13="",E13=0),"",EDATE(C13,ROUND(E13*12,0))-1) | H13: =IF(OR($A13="",$E13=0),0,MIN($F13,MAX(0,MIN(DATE(H$4,12,31),$G13)-MAX(DATE(H$4,1,1),$C13)+1)*$F13/365)) -> 0 | I13: =IF(OR($A13="",$E13=0),0,MIN($F13,MAX(0,MIN(DATE(I$4,12,31),$G13)-MAX(DATE(I$4,1,1),$C13)+1)*$F13/365)) -> 0 | J13: =IF(OR($A13="",$E13=0),0,MIN($F13,MAX(0,MIN(DATE(J$4,12,31),$G13)-MAX(DATE(J$4,1,1),$C13)+1)*$F13/365)) -> 0 | K13: =IF(OR($A13="",$E13=0),0,MIN($F13,MAX(0,MIN(DATE(K$4,12,31),$G13)-MAX(DATE(K$4,1,1),$C13)+1)*$F13/365)) -> 0 | L13: =IF(OR($A13="",$E13=0),0,MIN($F13,MAX(0,MIN(DATE(L$4,12,31),$G13)-MAX(DATE(L$4,1,1),$C13)+1)*$F13/365)) -> 0
F14: =IF(OR(A14="",E14=0),0,D14/E14) -> 0 | G14: =IF(OR(A14="",E14=0),"",EDATE(C14,ROUND(E14*12,0))-1) | H14: =IF(OR($A14="",$E14=0),0,MIN($F14,MAX(0,MIN(DATE(H$4,12,31),$G14)-MAX(DATE(H$4,1,1),$C14)+1)*$F14/365)) -> 0 | I14: =IF(OR($A14="",$E14=0),0,MIN($F14,MAX(0,MIN(DATE(I$4,12,31),$G14)-MAX(DATE(I$4,1,1),$C14)+1)*$F14/365)) -> 0 | J14: =IF(OR($A14="",$E14=0),0,MIN($F14,MAX(0,MIN(DATE(J$4,12,31),$G14)-MAX(DATE(J$4,1,1),$C14)+1)*$F14/365)) -> 0 | K14: =IF(OR($A14="",$E14=0),0,MIN($F14,MAX(0,MIN(DATE(K$4,12,31),$G14)-MAX(DATE(K$4,1,1),$C14)+1)*$F14/365)) -> 0 | L14: =IF(OR($A14="",$E14=0),0,MIN($F14,MAX(0,MIN(DATE(L$4,12,31),$G14)-MAX(DATE(L$4,1,1),$C14)+1)*$F14/365)) -> 0
F15: =IF(OR(A15="",E15=0),0,D15/E15) -> 0 | G15: =IF(OR(A15="",E15=0),"",EDATE(C15,ROUND(E15*12,0))-1) | H15: =IF(OR($A15="",$E15=0),0,MIN($F15,MAX(0,MIN(DATE(H$4,12,31),$G15)-MAX(DATE(H$4,1,1),$C15)+1)*$F15/365)) -> 0 | I15: =IF(OR($A15="",$E15=0),0,MIN($F15,MAX(0,MIN(DATE(I$4,12,31),$G15)-MAX(DATE(I$4,1,1),$C15)+1)*$F15/365)) -> 0 | J15: =IF(OR($A15="",$E15=0),0,MIN($F15,MAX(0,MIN(DATE(J$4,12,31),$G15)-MAX(DATE(J$4,1,1),$C15)+1)*$F15/365)) -> 0 | K15: =IF(OR($A15="",$E15=0),0,MIN($F15,MAX(0,MIN(DATE(K$4,12,31),$G15)-MAX(DATE(K$4,1,1),$C15)+1)*$F15/365)) -> 0 | L15: =IF(OR($A15="",$E15=0),0,MIN($F15,MAX(0,MIN(DATE(L$4,12,31),$G15)-MAX(DATE(L$4,1,1),$C15)+1)*$F15/365)) -> 0
F16: =IF(OR(A16="",E16=0),0,D16/E16) -> 0 | G16: =IF(OR(A16="",E16=0),"",EDATE(C16,ROUND(E16*12,0))-1) | H16: =IF(OR($A16="",$E16=0),0,MIN($F16,MAX(0,MIN(DATE(H$4,12,31),$G16)-MAX(DATE(H$4,1,1),$C16)+1)*$F16/365)) -> 0 | I16: =IF(OR($A16="",$E16=0),0,MIN($F16,MAX(0,MIN(DATE(I$4,12,31),$G16)-MAX(DATE(I$4,1,1),$C16)+1)*$F16/365)) -> 0 | J16: =IF(OR($A16="",$E16=0),0,MIN($F16,MAX(0,MIN(DATE(J$4,12,31),$G16)-MAX(DATE(J$4,1,1),$C16)+1)*$F16/365)) -> 0 | K16: =IF(OR($A16="",$E16=0),0,MIN($F16,MAX(0,MIN(DATE(K$4,12,31),$G16)-MAX(DATE(K$4,1,1),$C16)+1)*$F16/365)) -> 0 | L16: =IF(OR($A16="",$E16=0),0,MIN($F16,MAX(0,MIN(DATE(L$4,12,31),$G16)-MAX(DATE(L$4,1,1),$C16)+1)*$F16/365)) -> 0
F17: =IF(OR(A17="",E17=0),0,D17/E17) -> 0 | G17: =IF(OR(A17="",E17=0),"",EDATE(C17,ROUND(E17*12,0))-1) | H17: =IF(OR($A17="",$E17=0),0,MIN($F17,MAX(0,MIN(DATE(H$4,12,31),$G17)-MAX(DATE(H$4,1,1),$C17)+1)*$F17/365)) -> 0 | I17: =IF(OR($A17="",$E17=0),0,MIN($F17,MAX(0,MIN(DATE(I$4,12,31),$G17)-MAX(DATE(I$4,1,1),$C17)+1)*$F17/365)) -> 0 | J17: =IF(OR($A17="",$E17=0),0,MIN($F17,MAX(0,MIN(DATE(J$4,12,31),$G17)-MAX(DATE(J$4,1,1),$C17)+1)*$F17/365)) -> 0 | K17: =IF(OR($A17="",$E17=0),0,MIN($F17,MAX(0,MIN(DATE(K$4,12,31),$G17)-MAX(DATE(K$4,1,1),$C17)+1)*$F17/365)) -> 0 | L17: =IF(OR($A17="",$E17=0),0,MIN($F17,MAX(0,MIN(DATE(L$4,12,31),$G17)-MAX(DATE(L$4,1,1),$C17)+1)*$F17/365)) -> 0
F18: =IF(OR(A18="",E18=0),0,D18/E18) -> 0 | G18: =IF(OR(A18="",E18=0),"",EDATE(C18,ROUND(E18*12,0))-1) | H18: =IF(OR($A18="",$E18=0),0,MIN($F18,MAX(0,MIN(DATE(H$4,12,31),$G18)-MAX(DATE(H$4,1,1),$C18)+1)*$F18/365)) -> 0 | I18: =IF(OR($A18="",$E18=0),0,MIN($F18,MAX(0,MIN(DATE(I$4,12,31),$G18)-MAX(DATE(I$4,1,1),$C18)+1)*$F18/365)) -> 0 | J18: =IF(OR($A18="",$E18=0),0,MIN($F18,MAX(0,MIN(DATE(J$4,12,31),$G18)-MAX(DATE(J$4,1,1),$C18)+1)*$F18/365)) -> 0 | K18: =IF(OR($A18="",$E18=0),0,MIN($F18,MAX(0,MIN(DATE(K$4,12,31),$G18)-MAX(DATE(K$4,1,1),$C18)+1)*$F18/365)) -> 0 | L18: =IF(OR($A18="",$E18=0),0,MIN($F18,MAX(0,MIN(DATE(L$4,12,31),$G18)-MAX(DATE(L$4,1,1),$C18)+1)*$F18/365)) -> 0
F19: =IF(OR(A19="",E19=0),0,D19/E19) -> 0 | G19: =IF(OR(A19="",E19=0),"",EDATE(C19,ROUND(E19*12,0))-1) | H19: =IF(OR($A19="",$E19=0),0,MIN($F19,MAX(0,MIN(DATE(H$4,12,31),$G19)-MAX(DATE(H$4,1,1),$C19)+1)*$F19/365)) -> 0 | I19: =IF(OR($A19="",$E19=0),0,MIN($F19,MAX(0,MIN(DATE(I$4,12,31),$G19)-MAX(DATE(I$4,1,1),$C19)+1)*$F19/365)) -> 0 | J19: =IF(OR($A19="",$E19=0),0,MIN($F19,MAX(0,MIN(DATE(J$4,12,31),$G19)-MAX(DATE(J$4,1,1),$C19)+1)*$F19/365)) -> 0 | K19: =IF(OR($A19="",$E19=0),0,MIN($F19,MAX(0,MIN(DATE(K$4,12,31),$G19)-MAX(DATE(K$4,1,1),$C19)+1)*$F19/365)) -> 0 | L19: =IF(OR($A19="",$E19=0),0,MIN($F19,MAX(0,MIN(DATE(L$4,12,31),$G19)-MAX(DATE(L$4,1,1),$C19)+1)*$F19/365)) -> 0
F20: =IF(OR(A20="",E20=0),0,D20/E20) -> 0 | G20: =IF(OR(A20="",E20=0),"",EDATE(C20,ROUND(E20*12,0))-1) | H20: =IF(OR($A20="",$E20=0),0,MIN($F20,MAX(0,MIN(DATE(H$4,12,31),$G20)-MAX(DATE(H$4,1,1),$C20)+1)*$F20/365)) -> 0 | I20: =IF(OR($A20="",$E20=0),0,MIN($F20,MAX(0,MIN(DATE(I$4,12,31),$G20)-MAX(DATE(I$4,1,1),$C20)+1)*$F20/365)) -> 0 | J20: =IF(OR($A20="",$E20=0),0,MIN($F20,MAX(0,MIN(DATE(J$4,12,31),$G20)-MAX(DATE(J$4,1,1),$C20)+1)*$F20/365)) -> 0 | K20: =IF(OR($A20="",$E20=0),0,MIN($F20,MAX(0,MIN(DATE(K$4,12,31),$G20)-MAX(DATE(K$4,1,1),$C20)+1)*$F20/365)) -> 0 | L20: =IF(OR($A20="",$E20=0),0,MIN($F20,MAX(0,MIN(DATE(L$4,12,31),$G20)-MAX(DATE(L$4,1,1),$C20)+1)*$F20/365)) -> 0
F21: =IF(OR(A21="",E21=0),0,D21/E21) -> 0 | G21: =IF(OR(A21="",E21=0),"",EDATE(C21,ROUND(E21*12,0))-1) | H21: =IF(OR($A21="",$E21=0),0,MIN($F21,MAX(0,MIN(DATE(H$4,12,31),$G21)-MAX(DATE(H$4,1,1),$C21)+1)*$F21/365)) -> 0 | I21: =IF(OR($A21="",$E21=0),0,MIN($F21,MAX(0,MIN(DATE(I$4,12,31),$G21)-MAX(DATE(I$4,1,1),$C21)+1)*$F21/365)) -> 0 | J21: =IF(OR($A21="",$E21=0),0,MIN($F21,MAX(0,MIN(DATE(J$4,12,31),$G21)-MAX(DATE(J$4,1,1),$C21)+1)*$F21/365)) -> 0 | K21: =IF(OR($A21="",$E21=0),0,MIN($F21,MAX(0,MIN(DATE(K$4,12,31),$G21)-MAX(DATE(K$4,1,1),$C21)+1)*$F21/365)) -> 0 | L21: =IF(OR($A21="",$E21=0),0,MIN($F21,MAX(0,MIN(DATE(L$4,12,31),$G21)-MAX(DATE(L$4,1,1),$C21)+1)*$F21/365)) -> 0
... F40: =IF(OR(A40="",E40=0),0,D40/E40) -> 0 | G40: =IF(OR(A40="",E40=0),"",EDATE(C40,ROUND(E40*12,0))-1) | H40: =IF(OR($A40="",$E40=0),0,MIN($F40,MAX(0,MIN(DATE(H$4,12,31),$G40)-MAX(DATE(H$4,1,1),$C40)+1)*$F40/365)) -> 0 | I40: =IF(OR($A40="",$E40=0),0,MIN($F40,MAX(0,MIN(DATE(I$4,12,31),$G40)-MAX(DATE(I$4,1,1),$C40)+1)*$F40/365)) -> 0 | J40: =IF(OR($A40="",$E40=0),0,MIN($F40,MAX(0,MIN(DATE(J$4,12,31),$G40)-MAX(DATE(J$4,1,1),$C40)+1)*$F40/365)) -> 0 | K40: =IF(OR($A40="",$E40=0),0,MIN($F40,MAX(0,MIN(DATE(K$4,12,31),$G40)-MAX(DATE(K$4,1,1),$C40)+1)*$F40/365)) -> 0 | L40: =IF(OR($A40="",$E40=0),0,MIN($F40,MAX(0,MIN(DATE(L$4,12,31),$G40)-MAX(DATE(L$4,1,1),$C40)+1)*$F40/365)) -> 0

Sheet Revente
A1: Simulation de revente
A2: Saisissez les cellules jaunes. Estimation indicative de la somme perçue et de l'impôt sur la plus-value (régime des particuliers, LMNP). Le bien doit être le même que celui choisi dans la Synthèse.
B4: Hypothèses
B5: Bien | C5: APPART-01
B6: Date de vente envisagée | C6: 46568
B7: Prix de vente (net vendeur) | C7: 279000
B8: Frais d'agence à votre charge (% du prix) | C8: 0 | D8: 0 % si les frais d'agence sont payés par l'acheteur
B9: Frais divers de vente (diagnostics, état daté, mainlevée) | C9: 1674
B10: Indemnités de remboursement anticipé | C10: 0 | D10: Votre offre de prêt les exclut en cas de remboursement par la revente du bien : à confirmer avec le BANQUE.
B11: Frais d'acquisition réels justifiables (2017) | C11: 27900 | D11: Droits, émoluments du notaire et honoraires d'agence payés à l'achat (hors frais de garantie du prêt), selon l'acte de vente.
B12: Taux d'impôt sur le revenu sur la plus-value | C12: 0.19
B13: Taux des prélèvements sociaux sur la plus-value | C13: 0.172 | D13: 17,2 % maintenu en 2026 pour les plus-values immobilières.
B15: Somme perçue à la vente
B16: Prix de vente | C16: =C7 -> 279000
B17: − Frais d'agence | C17: =-C7*C8 -> 0
B18: − Frais divers de vente | C18: =-C9 -> -1674
B19: − Capital restant dû à la date de vente | C19: =-(SUMIFS(Prêts!$E$5:$E$14,Prêts!$B$5:$B$14,$C$5)-SUMIFS(Échéancier!$F$5:$F$300,Échéancier!$J$5:$J$300,$C$5,Échéancier!$C$5:$C$300,"<="&C6)) -> -94982.35
B20: − Indemnités de remboursement anticipé | C20: =-C10 -> 0
B21: Somme perçue avant impôt | C21: =SUM(C16:C20) -> 182343.65
B22: − Impôt sur la plus-value (calcul ci-dessous) | C22: =-C46 -> 0
B23: Somme nette perçue après impôt | C23: =C21+C22 -> 182343.65
B25: Pour mémoire : apport personnel initial | C25: =IFERROR(INDEX(Biens!$N$5:$N$30,MATCH($C$5,Biens!$A$5:$A$30,0)),0) -> 97968.99
B26: Pour mémoire : cash-flow cumulé depuis la mise en location | C26: =SUMIFS(Journal!$K$5:$K$1004,Journal!$C$5:$C$1004,$C$5,Journal!$A$5:$A$1004,"<="&MIN(C6,Synthèse!$C$4))-SUMIFS(Échéancier!$I$5:$I$300,Échéancier!$J$5:$J$300,$C$5,Échéancier!$K$5:$K$300,1,Échéancier!$C$5:$C$300,"<="&MIN(C6,Synthèse!$C$4)) -> -9915.98 | D26: Arrêté à la date de mise à jour des données (Synthèse, C4).
B27: Pour mémoire : dépôt de garantie à restituer au locataire | C27: =IFERROR(INDEX(Biens!$V$5:$V$30,MATCH($C$5,Biens!$A$5:$A$30,0)),0) -> 2064.6
B32: Calcul de la plus-value
B33: Durée de détention (années pleines) | C33: =DATEDIF(IFERROR(INDEX(Biens!$H$5:$H$30,MATCH($C$5,Biens!$A$5:$A$30,0)),0),C6,"y") -> 9
B34: Prix de cession (prix − frais de vente) | C34: =C7-C7*C8-C9 -> 277326
B35: Prix d'acquisition du logement (hors mobilier) | C35: =IFERROR(INDEX(Biens!$I$5:$I$30,MATCH($C$5,Biens!$A$5:$A$30,0)),0)-IFERROR(INDEX(Biens!$J$5:$J$30,MATCH($C$5,Biens!$A$5:$A$30,0)),0) -> 231570
B36: + Frais d'acquisition (réels ou forfait 7,5 %, le plus élevé) | C36: =MAX(C11,0.075*C35) -> 27900
B37: + Forfait travaux 15 % (détention de plus de 5 ans) | C37: =IF(C33>5,0.15*C35,0) -> 34735.5
B38: − Amortissements déduits à réintégrer | C38: =-SUM(IF(ISNUMBER(Synthèse!D32),Synthèse!D25+Synthèse!D26-Synthèse!D32,N(Synthèse!D27)),IF(ISNUMBER(Synthèse!E32),Synthèse!E25+Synthèse!E26-Synthèse!E32,N(Synthèse!E27)),IF(ISNUMBER(Synthèse!F32),Synthèse!F25+Synthèse!F26-Synthèse!F32,N(Synthèse!F27)),IF(ISNUMBER(Synthèse!G32),Synthèse!G25+Synthèse!G26-Synthèse!G32,N(Synthèse!G27)),IF(ISNUMBER(Synthèse!H32),Synthèse!H25+Synthèse!H26-Synthèse!H32,N(Synthèse!H27))) -> -13921.516 | D38: Amortissements effectivement déduits (comptable pour les années déclarées, outil pour l'année en cours) ; ceux mis en report ne sont pas réintégrés. Ceux de l'année de la vente ne sont pas comptés.
B39: Prix d'acquisition corrigé | C39: =SUM(C35:C38) -> 280283.98
B40: Plus-value brute | C40: =MAX(0,C34-C39) -> 0
B41: Abattement pour durée de détention (impôt sur le revenu) | C41: =IF(C33<6,0,IF(C33<=21,(C33-5)*0.06,1)) -> 0.24
B42: Abattement pour durée de détention (prélèvements sociaux) | C42: =IF(C33<6,0,IF(C33<=21,(C33-5)*0.0165,IF(C33=22,0.28,MIN(1,0.28+(C33-22)*0.09)))) -> 0.066
B43: Impôt sur le revenu | C43: =C40*(1-C41)*C12 -> 0
B44: Prélèvements sociaux | C44: =C40*(1-C42)*C13 -> 0
B45: Surtaxe (plus-value imposable supérieure à 46 500 €) | C45: =IF(C40*(1-C41)>50000,"À calculer",0) -> 0
B46: Impôt total sur la plus-value | C46: =C43+C44+N(C45) -> 0
B48: Estimation indicative, pas un conseil fiscal : depuis le 15/02/2025, les amortissements LMNP déduits sont réintégrés dans la plus-value. Le bien n'étant plus votre résidence principale, l'exonération de la résidence principale ne s'applique pas ; l'exonération pour remploi dans une nouvelle résidence principale est traitée dans l'onglet Vendre quand. Le notaire calcule l'impôt réel : faites-lui confirmer les frais retenus, le forfait de 15 % et les amortissements déduits (fournis par le comptable).

Sheet Vendre quand
A1: Vendre quand ?
A2: Compare trois dates de vente : somme perçue, impôt sur la plus-value, effort de trésorerie d'ici là, gain total depuis l'achat et TRI. Les frais de vente et les taux d'imposition viennent de l'onglet Revente.
B4: Paramètres
B5: Bien | C5: =Revente!C5 -> APPART-01 | D5: Le même bien que dans l'onglet Revente (et la Synthèse).
B6: Données réelles jusqu'au | C6: =Synthèse!C4 -> 46320 | D6: Date de mise à jour du Journal (Synthèse, C4). Au-delà : projection.
B7: Date d'acquisition | C7: =IFERROR(INDEX(Biens!$H$5:$H$30,MATCH($C$5,Biens!$A$5:$A$30,0)),0) -> 43049 | D7: Onglet Biens.
B8: Apport personnel | C8: =IFERROR(INDEX(Biens!$N$5:$N$30,MATCH($C$5,Biens!$A$5:$A$30,0)),0) -> 97968.99 | D8: Onglet Biens.
B9: Fin d'occupation comme résidence principale | C9: 45231 | D9: Date à laquelle vous avez quitté le logement. Laissez vide s'il n'a jamais été votre résidence principale.
B10: Loyer évité à l'achat (par mois, charges comprises) | C10: 976.5 | D10: Ce que vous auriez payé pour louer un logement équivalent : compté comme un gain tant que vous y habitiez.
B11: Indexation annuelle du loyer évité | C11: 0.0178 | D11: IRL : +1,8 % par an en moyenne entre 2017 et 2023.
B12: Projection : loyer net versé par l'agence (par mois) | C12: 1056.61 | D12: Dernier virement complet de l'agence (loyer + provisions − honoraires).
B13: Projection : dépenses payées par vous (par an, hors prêt) | C13: 5598.6 | D13: Copropriété 4 026 € (niveau 2026) + taxe foncière 571 € + CFE 325 € + comptable 558 € + PNO 116 €.
B14: Projection : évolution annuelle des loyers et des charges | C14: 0.015
B15: Projection : amortissements déduits par an | C15: 4185 | D15: Pour les années après la date de mise à jour. Chiffre à demander au comptable (résultat avant amortissements de l'année).
B16: Frais liés à l'année de la vente | C16: 558 | D16: Dernière liasse LMNP (comptable). Payés à la vente dans le calcul.
B17: Part du prix réinvestie dans votre résidence principale | C17: 1 | D17: Pour l'exonération pour remploi (voir plus bas). Achat à deux : seule votre part compte.
B18: Autres dettes à rembourser à la vente | C18: 0 | D18: Par exemple un prêt familial ayant servi à l'apport. Sert à calculer la somme disponible pour le prochain achat.
B20: Scénarios de vente
B21: Rubrique | C21: Scénario 1 | D21: Scénario 2 | E21: Scénario 3 | F21: Explication
B22: Date de vente | C22: 46568 | D22: 46934 | E22: 47299
B23: Prix de vente (net vendeur) | C23: 279000 | D23: 279000 | E23: 279000
B25: Somme perçue
B26: Prix de vente | C26: =C23 -> 279000 | D26: =D23 -> 279000 | E26: =E23 -> 279000
B27: − Frais d'agence | C27: =-C23*Revente!$C$8 -> 0 | D27: =-D23*Revente!$C$8 -> 0 | E27: =-E23*Revente!$C$8 -> 0
B28: − Frais divers de vente | C28: =-Revente!$C$9 -> -1674 | D28: =-Revente!$C$9 -> -1674 | E28: =-Revente!$C$9 -> -1674
B29: − Capital restant dû | C29: =-(SUMIFS(Prêts!$E$5:$E$14,Prêts!$B$5:$B$14,$C$5)-SUMIFS(Échéancier!$F$5:$F$300,Échéancier!$J$5:$J$300,$C$5,Échéancier!$C$5:$C$300,"<="&C22)) -> -94982.35 | D29: =-(SUMIFS(Prêts!$E$5:$E$14,Prêts!$B$5:$B$14,$C$5)-SUMIFS(Échéancier!$F$5:$F$300,Échéancier!$J$5:$J$300,$C$5,Échéancier!$C$5:$C$300,"<="&D22)) -> -86493.93 | E29: =-(SUMIFS(Prêts!$E$5:$E$14,Prêts!$B$5:$B$14,$C$5)-SUMIFS(Échéancier!$F$5:$F$300,Échéancier!$J$5:$J$300,$C$5,Échéancier!$C$5:$C$300,"<="&E22)) -> -77877.34
B30: − Indemnités de remboursement anticipé | C30: =-Revente!$C$10 -> 0 | D30: =-Revente!$C$10 -> 0 | E30: =-Revente!$C$10 -> 0
B31: − Impôt sur la plus-value | C31: =-C44 -> 0 | D31: =-D44 -> -356.82839 | E31: =-E44 -> -1496.812 | F31: Sans exonération pour remploi (ligne 46).
B32: Somme nette perçue | C32: =SUM(C26:C31) -> 182343.65 | D32: =SUM(D26:D31) -> 190475.24 | E32: =SUM(E26:E31) -> 197951.85
B33: − Autres dettes à rembourser | C33: =-$C$18 -> 0 | D33: =-$C$18 -> 0 | E33: =-$C$18 -> 0
B34: Somme disponible pour le prochain achat | C34: =C32+C33 -> 182343.65 | D34: =D32+D33 -> 190475.24 | E34: =E32+E33 -> 197951.85
B36: Plus-value
B37: Durée de détention (années pleines) | C37: =DATEDIF($C$7,C22,"y") -> 9 | D37: =DATEDIF($C$7,D22,"y") -> 10 | E37: =DATEDIF($C$7,E22,"y") -> 11
B38: Prix de cession (prix − frais de vente) | C38: =C23*(1-Revente!$C$8)-Revente!$C$9 -> 277326 | D38: =D23*(1-Revente!$C$8)-Revente!$C$9 -> 277326 | E38: =E23*(1-Revente!$C$8)-Revente!$C$9 -> 277326
B39: Prix d'achat + frais d'acquisition + forfait travaux 15 % | C39: =(IFERROR(INDEX(Biens!$I$5:$I$30,MATCH($C$5,Biens!$A$5:$A$30,0)),0)-IFERROR(INDEX(Biens!$J$5:$J$30,MATCH($C$5,Biens!$A$5:$A$30,0)),0))+MAX(Revente!$C$11,0.075*(IFERROR(INDEX(Biens!$I$5:$I$30,MATCH($C$5,Biens!$A$5:$A$30,0)),0)-IFERROR(INDEX(Biens!$J$5:$J$30,MATCH($C$5,Biens!$A$5:$A$30,0)),0)))+IF(C37>5,0.15*(IFERROR(INDEX(Biens!$I$5:$I$30,MATCH($C$5,Biens!$A$5:$A$30,0)),0)-IFERROR(INDEX(Biens!$J$5:$J$30,MATCH($C$5,Biens!$A$5:$A$30,0)),0)),0) -> 294205.5 | D39: =(IFERROR(INDEX(Biens!$I$5:$I$30,MATCH($C$5,Biens!$A$5:$A$30,0)),0)-IFERROR(INDEX(Biens!$J$5:$J$30,MATCH($C$5,Biens!$A$5:$A$30,0)),0))+MAX(Revente!$C$11,0.075*(IFERROR(INDEX(Biens!$I$5:$I$30,MATCH($C$5,Biens!$A$5:$A$30,0)),0)-IFERROR(INDEX(Biens!$J$5:$J$30,MATCH($C$5,Biens!$A$5:$A$30,0)),0)))+IF(D37>5,0.15*(IFERROR(INDEX(Biens!$I$5:$I$30,MATCH($C$5,Biens!$A$5:$A$30,0)),0)-IFERROR(INDEX(Biens!$J$5:$J$30,MATCH($C$5,Biens!$A$5:$A$30,0)),0)),0) -> 294205.5 | E39: =(IFERROR(INDEX(Biens!$I$5:$I$30,MATCH($C$5,Biens!$A$5:$A$30,0)),0)-IFERROR(INDEX(Biens!$J$5:$J$30,MATCH($C$5,Biens!$A$5:$A$30,0)),0))+MAX(Revente!$C$11,0.075*(IFERROR(INDEX(Biens!$I$5:$I$30,MATCH($C$5,Biens!$A$5:$A$30,0)),0)-IFERROR(INDEX(Biens!$J$5:$J$30,MATCH($C$5,Biens!$A$5:$A$30,0)),0)))+IF(E37>5,0.15*(IFERROR(INDEX(Biens!$I$5:$I$30,MATCH($C$5,Biens!$A$5:$A$30,0)),0)-IFERROR(INDEX(Biens!$J$5:$J$30,MATCH($C$5,Biens!$A$5:$A$30,0)),0)),0) -> 294205.5 | F39: Mêmes règles que l'onglet Revente : prix hors mobilier, frais réels ou forfait 7,5 %, forfait travaux si plus de 5 ans.
B40: − Amortissements déduits (années avant celle de la vente) | C40: =-SUMPRODUCT(($B$113:$B$128<YEAR(C22))*$C$113:$C$128) -> -13921.516 | D40: =-SUMPRODUCT(($B$113:$B$128<YEAR(D22))*$C$113:$C$128) -> -18106.516 | E40: =-SUMPRODUCT(($B$113:$B$128<YEAR(E22))*$C$113:$C$128) -> -22291.516 | F40: Réintégrés dans la plus-value depuis le 15/02/2025. Détail par année plus bas.
B41: Plus-value brute | C41: =MAX(0,C38-C39-C40) -> 0 | D41: =MAX(0,D38-D39-D40) -> 1227.0155 | E41: =MAX(0,E38-E39-E40) -> 5412.0155
B42: Abattement pour durée de détention (impôt sur le revenu) | C42: =IF(C37<6,0,IF(C37<=21,(C37-5)*0.06,1)) -> 0.24 | D42: =IF(D37<6,0,IF(D37<=21,(D37-5)*0.06,1)) -> 0.3 | E42: =IF(E37<6,0,IF(E37<=21,(E37-5)*0.06,1)) -> 0.36
B43: Abattement pour durée de détention (prélèvements sociaux) | C43: =IF(C37<6,0,IF(C37<=21,(C37-5)*0.0165,IF(C37=22,0.28,MIN(1,0.28+(C37-22)*0.09)))) -> 0.066 | D43: =IF(D37<6,0,IF(D37<=21,(D37-5)*0.0165,IF(D37=22,0.28,MIN(1,0.28+(D37-22)*0.09)))) -> 0.0825 | E43: =IF(E37<6,0,IF(E37<=21,(E37-5)*0.0165,IF(E37=22,0.28,MIN(1,0.28+(E37-22)*0.09)))) -> 0.099
B44: Impôt sur la plus-value | C44: =C41*(1-C42)*Revente!$C$12+C41*(1-C43)*Revente!$C$13 -> 0 | D44: =D41*(1-D42)*Revente!$C$12+D41*(1-D43)*Revente!$C$13 -> 356.82839 | E44: =E41*(1-E42)*Revente!$C$12+E41*(1-E43)*Revente!$C$13 -> 1496.812 | F44: Surtaxe non comptée (elle ne s'applique qu'au-delà de 46 500 € de plus-value imposable).
B45: Condition des 4 ans pour l'exonération pour remploi | C45: =IF($C$9="","Non applicable",IF(C22>=EDATE($C$9,48),"Oui","Non")) -> Non | D45: =IF($C$9="","Non applicable",IF(D22>=EDATE($C$9,48),"Oui","Non")) -> Oui | E45: =IF($C$9="","Non applicable",IF(E22>=EDATE($C$9,48),"Oui","Non")) -> Oui | F45: Première vente d'un logement qui n'est pas votre résidence principale, sans avoir été propriétaire de votre résidence principale dans les 4 ans (de date à date) avant la vente, prix réinvesti dans votre résidence principale sous 24 mois. À confirmer avec le notaire.
B46: Impôt évité si le prix est réinvesti | C46: =IF(C45="Oui",C44*$C$17,0) -> 0 | D46: =IF(D45="Oui",D44*$C$17,0) -> 356.82839 | E46: =IF(E45="Oui",E44*$C$17,0) -> 1496.812
B47: Somme nette avec remploi | C47: =C32+C46 -> 182343.65 | D47: =D32+D46 -> 190832.07 | E47: =E32+E46 -> 199448.66
B49: D'ici la vente
B50: Mois entre la mise à jour et la vente | C50: =SUMPRODUCT(($B$133:$B$432>$C$6)*($C$133:$C$432<=C22)) -> 8 | D50: =SUMPRODUCT(($B$133:$B$432>$C$6)*($C$133:$C$432<=D22)) -> 20 | E50: =SUMPRODUCT(($B$133:$B$432>$C$6)*($C$133:$C$432<=E22)) -> 32
B51: Cash-flow à remettre de votre poche (total) | C51: =SUMPRODUCT(($B$133:$B$432>$C$6)*($C$133:$C$432<=C22)*($E$133:$E$432+$H$133:$H$432))-$C$16 -> -2515.0246 | D51: =SUMPRODUCT(($B$133:$B$432>$C$6)*($C$133:$C$432<=D22)*($E$133:$E$432+$H$133:$H$432))-$C$16 -> -5370.0918 | E51: =SUMPRODUCT(($B$133:$B$432>$C$6)*($C$133:$C$432<=E22)*($E$133:$E$432+$H$133:$H$432))-$C$16 -> -8116.5465 | F51: Loyers projetés moins dépenses et échéances de prêt, plus les frais de l'année de la vente.
B52: Soit par mois | C52: =IF(C50>0,C51/C50,0) -> -314.37808 | D52: =IF(D50>0,D51/D50,0) -> -268.50459 | E52: =IF(E50>0,E51/E50,0) -> -253.64208
B53: Capital remboursé sur la période | C53: =SUMIFS(Échéancier!$F$5:$F$300,Échéancier!$J$5:$J$300,$C$5,Échéancier!$C$5:$C$300,">"&$C$6,Échéancier!$C$5:$C$300,"<="&C22) -> 5588.65 | D53: =SUMIFS(Échéancier!$F$5:$F$300,Échéancier!$J$5:$J$300,$C$5,Échéancier!$C$5:$C$300,">"&$C$6,Échéancier!$C$5:$C$300,"<="&D22) -> 14077.07 | E53: =SUMIFS(Échéancier!$F$5:$F$300,Échéancier!$J$5:$J$300,$C$5,Échéancier!$C$5:$C$300,">"&$C$6,Échéancier!$C$5:$C$300,"<="&E22) -> 22693.66
B55: Bilan depuis l'achat
B56: Gain total depuis l'achat | C56: =SUM(J132:J435) -> 61716.836 | D56: =SUM(K132:K435) -> 66993.361 | E56: =SUM(L132:L435) -> 71723.512 | F56: Tous les flux : apport, loyer évité pendant l'occupation, prêt, dépenses, loyers, vente nette (sans exonération).
B57: TRI (rendement annuel de votre apport) | C57: =XIRR(J132:J435,$C$132:$C$435) -> 0.049883106 | D57: =XIRR(K132:K435,$C$132:$C$435) -> 0.047654766 | E57: =XIRR(L132:L435,$C$132:$C$435) -> 0.045439644
B58: Gain en plus par rapport au scénario précédent | C58: ="" | D58: =D56-C56 -> 5276.5244 | E58: =E56-D56 -> 4730.1517
B59: Rendement annuel de l'attente | C59: ="" | D59: =IF(D22>C22,D58/C32/((D22-C22)/365),"") -> 0.02885819 | E59: =IF(E22>D22,E58/D32/((E22-D22)/365),"") -> 0.02483342 | F59: Ce que rapporte le fait d'attendre, rapporté à la somme que vous auriez touchée en vendant plus tôt. À comparer au taux de votre futur prêt.
B61: Estimation indicative, pas un conseil fiscal. Le notaire calcule l'impôt réel : faites-lui confirmer les frais d'acquisition et le forfait de 15 %, les amortissements déduits (fournis par le comptable) et l'éligibilité à l'exonération pour remploi.
B65: Dépenses payées avant la mise en location (résidence principale, puis logement vide)
B66: Ce qui a été payé depuis la mise en location se saisit dans le Journal. Les échéances du prêt viennent de l'Échéancier : ne pas les saisir ici.
B67: Libellé | C67: Date | D67: Montant payé | E67: Bien | F67: Nature et source
B68: Taxe foncière 2017 (prorata remboursé au vendeur) | C68: 43049 | D68: 59.38 | E68: APPART-01 | F68: Réel : acte de vente
B69: Copropriété 2017 (10/11 au 31/12) | C69: 43084 | D69: 278.07 | E69: APPART-01 | F69: Estimation : 1 953 € par an au prorata
B70: Copropriété 2018 | C70: 43282 | D70: 1953 | E70: APPART-01 | F70: Estimation (décomptes annuels non retrouvés)
B71: Taxe foncière 2018 | C71: 43388 | D71: 430.59 | E71: APPART-01 | F71: Estimation
B72: Copropriété 2019 | C72: 43647 | D72: 1953 | E72: APPART-01 | F72: Estimation (décomptes annuels non retrouvés)
B73: Taxe foncière 2019 | C73: 43753 | D73: 440.82 | E73: APPART-01 | F73: Estimation
B74: Copropriété 2020 | C74: 44013 | D74: 1953 | E74: APPART-01 | F74: Estimation (décomptes annuels non retrouvés)
B75: Taxe foncière 2020 | C75: 44119 | D75: 445.47 | E75: APPART-01 | F75: Estimation
B76: Copropriété 2021 | C76: 44378 | D76: 1953 | E76: APPART-01 | F76: Estimation (décomptes annuels non retrouvés)
B77: Taxe foncière 2021 | C77: 44484 | D77: 446.4 | E77: APPART-01 | F77: Estimation
B78: Copropriété 2022 | C78: 44743 | D78: 1953 | E78: APPART-01 | F78: Estimation (décomptes annuels non retrouvés)
B79: Taxe foncière 2022 | C79: 44849 | D79: 462.21 | E79: APPART-01 | F79: Réel : avis 2022 (06_Impots-locaux)
... B90: Copropriété : appel T2 2024 | C90: 45392 | D90: 752.3 | E90: APPART-01 | F90: Réel : relevé BANQUE
B107: Total | D107: =SUMIFS(D68:D106,E68:E106,$C$5) -> 17750.1
B110: Amortissements déduits par année (calcul)
B112: Année | C112: Déduits | D112: Origine
B113: 2017 | C113: =IF(B113>YEAR($C$6),IF(B113>=YEAR(IFERROR(INDEX(Biens!$O$5:$O$30,MATCH($C$5,Biens!$A$5:$A$30,0)),0)),$C$15,0),IFERROR(IF(ISNUMBER(INDEX(Synthèse!$D$32:$H$32,MATCH(B113,Synthèse!$D$7:$H$7,0))),INDEX(Synthèse!$D$25:$H$25,MATCH(B113,Synthèse!$D$7:$H$7,0))+INDEX(Synthèse!$D$26:$H$26,MATCH(B113,Synthèse!$D$7:$H$7,0))-INDEX(Synthèse!$D$32:$H$32,MATCH(B113,Synthèse!$D$7:$H$7,0)),N(INDEX(Synthèse!$D$27:$H$27,MATCH(B113,Synthèse!$D$7:$H$7,0)))),0)) -> 0 | D113: =IF(B113>YEAR($C$6),IF(C113>0,"Projection (C15)",""),IF(C113>0,"Comptable, puis Synthèse pour l'année en cours",""))
B114: 2018 | C114: =IF(B114>YEAR($C$6),IF(B114>=YEAR(IFERROR(INDEX(Biens!$O$5:$O$30,MATCH($C$5,Biens!$A$5:$A$30,0)),0)),$C$15,0),IFERROR(IF(ISNUMBER(INDEX(Synthèse!$D$32:$H$32,MATCH(B114,Synthèse!$D$7:$H$7,0))),INDEX(Synthèse!$D$25:$H$25,MATCH(B114,Synthèse!$D$7:$H$7,0))+INDEX(Synthèse!$D$26:$H$26,MATCH(B114,Synthèse!$D$7:$H$7,0))-INDEX(Synthèse!$D$32:$H$32,MATCH(B114,Synthèse!$D$7:$H$7,0)),N(INDEX(Synthèse!$D$27:$H$27,MATCH(B114,Synthèse!$D$7:$H$7,0)))),0)) -> 0 | D114: =IF(B114>YEAR($C$6),IF(C114>0,"Projection (C15)",""),IF(C114>0,"Comptable, puis Synthèse pour l'année en cours",""))
B115: 2019 | C115: =IF(B115>YEAR($C$6),IF(B115>=YEAR(IFERROR(INDEX(Biens!$O$5:$O$30,MATCH($C$5,Biens!$A$5:$A$30,0)),0)),$C$15,0),IFERROR(IF(ISNUMBER(INDEX(Synthèse!$D$32:$H$32,MATCH(B115,Synthèse!$D$7:$H$7,0))),INDEX(Synthèse!$D$25:$H$25,MATCH(B115,Synthèse!$D$7:$H$7,0))+INDEX(Synthèse!$D$26:$H$26,MATCH(B115,Synthèse!$D$7:$H$7,0))-INDEX(Synthèse!$D$32:$H$32,MATCH(B115,Synthèse!$D$7:$H$7,0)),N(INDEX(Synthèse!$D$27:$H$27,MATCH(B115,Synthèse!$D$7:$H$7,0)))),0)) -> 0 | D115: =IF(B115>YEAR($C$6),IF(C115>0,"Projection (C15)",""),IF(C115>0,"Comptable, puis Synthèse pour l'année en cours",""))
B116: 2020 | C116: =IF(B116>YEAR($C$6),IF(B116>=YEAR(IFERROR(INDEX(Biens!$O$5:$O$30,MATCH($C$5,Biens!$A$5:$A$30,0)),0)),$C$15,0),IFERROR(IF(ISNUMBER(INDEX(Synthèse!$D$32:$H$32,MATCH(B116,Synthèse!$D$7:$H$7,0))),INDEX(Synthèse!$D$25:$H$25,MATCH(B116,Synthèse!$D$7:$H$7,0))+INDEX(Synthèse!$D$26:$H$26,MATCH(B116,Synthèse!$D$7:$H$7,0))-INDEX(Synthèse!$D$32:$H$32,MATCH(B116,Synthèse!$D$7:$H$7,0)),N(INDEX(Synthèse!$D$27:$H$27,MATCH(B116,Synthèse!$D$7:$H$7,0)))),0)) -> 0 | D116: =IF(B116>YEAR($C$6),IF(C116>0,"Projection (C15)",""),IF(C116>0,"Comptable, puis Synthèse pour l'année en cours",""))
B117: 2021 | C117: =IF(B117>YEAR($C$6),IF(B117>=YEAR(IFERROR(INDEX(Biens!$O$5:$O$30,MATCH($C$5,Biens!$A$5:$A$30,0)),0)),$C$15,0),IFERROR(IF(ISNUMBER(INDEX(Synthèse!$D$32:$H$32,MATCH(B117,Synthèse!$D$7:$H$7,0))),INDEX(Synthèse!$D$25:$H$25,MATCH(B117,Synthèse!$D$7:$H$7,0))+INDEX(Synthèse!$D$26:$H$26,MATCH(B117,Synthèse!$D$7:$H$7,0))-INDEX(Synthèse!$D$32:$H$32,MATCH(B117,Synthèse!$D$7:$H$7,0)),N(INDEX(Synthèse!$D$27:$H$27,MATCH(B117,Synthèse!$D$7:$H$7,0)))),0)) -> 0 | D117: =IF(B117>YEAR($C$6),IF(C117>0,"Projection (C15)",""),IF(C117>0,"Comptable, puis Synthèse pour l'année en cours",""))
B118: 2022 | C118: =IF(B118>YEAR($C$6),IF(B118>=YEAR(IFERROR(INDEX(Biens!$O$5:$O$30,MATCH($C$5,Biens!$A$5:$A$30,0)),0)),$C$15,0),IFERROR(IF(ISNUMBER(INDEX(Synthèse!$D$32:$H$32,MATCH(B118,Synthèse!$D$7:$H$7,0))),INDEX(Synthèse!$D$25:$H$25,MATCH(B118,Synthèse!$D$7:$H$7,0))+INDEX(Synthèse!$D$26:$H$26,MATCH(B118,Synthèse!$D$7:$H$7,0))-INDEX(Synthèse!$D$32:$H$32,MATCH(B118,Synthèse!$D$7:$H$7,0)),N(INDEX(Synthèse!$D$27:$H$27,MATCH(B118,Synthèse!$D$7:$H$7,0)))),0)) -> 0 | D118: =IF(B118>YEAR($C$6),IF(C118>0,"Projection (C15)",""),IF(C118>0,"Comptable, puis Synthèse pour l'année en cours",""))
B119: 2023 | C119: =IF(B119>YEAR($C$6),IF(B119>=YEAR(IFERROR(INDEX(Biens!$O$5:$O$30,MATCH($C$5,Biens!$A$5:$A$30,0)),0)),$C$15,0),IFERROR(IF(ISNUMBER(INDEX(Synthèse!$D$32:$H$32,MATCH(B119,Synthèse!$D$7:$H$7,0))),INDEX(Synthèse!$D$25:$H$25,MATCH(B119,Synthèse!$D$7:$H$7,0))+INDEX(Synthèse!$D$26:$H$26,MATCH(B119,Synthèse!$D$7:$H$7,0))-INDEX(Synthèse!$D$32:$H$32,MATCH(B119,Synthèse!$D$7:$H$7,0)),N(INDEX(Synthèse!$D$27:$H$27,MATCH(B119,Synthèse!$D$7:$H$7,0)))),0)) -> 0 | D119: =IF(B119>YEAR($C$6),IF(C119>0,"Projection (C15)",""),IF(C119>0,"Comptable, puis Synthèse pour l'année en cours",""))
B120: 2024 | C120: =IF(B120>YEAR($C$6),IF(B120>=YEAR(IFERROR(INDEX(Biens!$O$5:$O$30,MATCH($C$5,Biens!$A$5:$A$30,0)),0)),$C$15,0),IFERROR(IF(ISNUMBER(INDEX(Synthèse!$D$32:$H$32,MATCH(B120,Synthèse!$D$7:$H$7,0))),INDEX(Synthèse!$D$25:$H$25,MATCH(B120,Synthèse!$D$7:$H$7,0))+INDEX(Synthèse!$D$26:$H$26,MATCH(B120,Synthèse!$D$7:$H$7,0))-INDEX(Synthèse!$D$32:$H$32,MATCH(B120,Synthèse!$D$7:$H$7,0)),N(INDEX(Synthèse!$D$27:$H$27,MATCH(B120,Synthèse!$D$7:$H$7,0)))),0)) -> 3916.3589 | D120: =IF(B120>YEAR($C$6),IF(C120>0,"Projection (C15)",""),IF(C120>0,"Comptable, puis Synthèse pour l'année en cours","")) -> Comptable, puis Synthèse pour l'année en cours
B121: 2025 | C121: =IF(B121>YEAR($C$6),IF(B121>=YEAR(IFERROR(INDEX(Biens!$O$5:$O$30,MATCH($C$5,Biens!$A$5:$A$30,0)),0)),$C$15,0),IFERROR(IF(ISNUMBER(INDEX(Synthèse!$D$32:$H$32,MATCH(B121,Synthèse!$D$7:$H$7,0))),INDEX(Synthèse!$D$25:$H$25,MATCH(B121,Synthèse!$D$7:$H$7,0))+INDEX(Synthèse!$D$26:$H$26,MATCH(B121,Synthèse!$D$7:$H$7,0))-INDEX(Synthèse!$D$32:$H$32,MATCH(B121,Synthèse!$D$7:$H$7,0)),N(INDEX(Synthèse!$D$27:$H$27,MATCH(B121,Synthèse!$D$7:$H$7,0)))),0)) -> 7307.7267 | D121: =IF(B121>YEAR($C$6),IF(C121>0,"Projection (C15)",""),IF(C121>0,"Comptable, puis Synthèse pour l'année en cours","")) -> Comptable, puis Synthèse pour l'année en cours
B122: 2026 | C122: =IF(B122>YEAR($C$6),IF(B122>=YEAR(IFERROR(INDEX(Biens!$O$5:$O$30,MATCH($C$5,Biens!$A$5:$A$30,0)),0)),$C$15,0),IFERROR(IF(ISNUMBER(INDEX(Synthèse!$D$32:$H$32,MATCH(B122,Synthèse!$D$7:$H$7,0))),INDEX(Synthèse!$D$25:$H$25,MATCH(B122,Synthèse!$D$7:$H$7,0))+INDEX(Synthèse!$D$26:$H$26,MATCH(B122,Synthèse!$D$7:$H$7,0))-INDEX(Synthèse!$D$32:$H$32,MATCH(B122,Synthèse!$D$7:$H$7,0)),N(INDEX(Synthèse!$D$27:$H$27,MATCH(B122,Synthèse!$D$7:$H$7,0)))),0)) -> 2697.43 | D122: =IF(B122>YEAR($C$6),IF(C122>0,"Projection (C15)",""),IF(C122>0,"Comptable, puis Synthèse pour l'année en cours","")) -> Comptable, puis Synthèse pour l'année en cours
B123: 2027 | C123: =IF(B123>YEAR($C$6),IF(B123>=YEAR(IFERROR(INDEX(Biens!$O$5:$O$30,MATCH($C$5,Biens!$A$5:$A$30,0)),0)),$C$15,0),IFERROR(IF(ISNUMBER(INDEX(Synthèse!$D$32:$H$32,MATCH(B123,Synthèse!$D$7:$H$7,0))),INDEX(Synthèse!$D$25:$H$25,MATCH(B123,Synthèse!$D$7:$H$7,0))+INDEX(Synthèse!$D$26:$H$26,MATCH(B123,Synthèse!$D$7:$H$7,0))-INDEX(Synthèse!$D$32:$H$32,MATCH(B123,Synthèse!$D$7:$H$7,0)),N(INDEX(Synthèse!$D$27:$H$27,MATCH(B123,Synthèse!$D$7:$H$7,0)))),0)) -> 4185 | D123: =IF(B123>YEAR($C$6),IF(C123>0,"Projection (C15)",""),IF(C123>0,"Comptable, puis Synthèse pour l'année en cours","")) -> Projection (C15)
B124: 2028 | C124: =IF(B124>YEAR($C$6),IF(B124>=YEAR(IFERROR(INDEX(Biens!$O$5:$O$30,MATCH($C$5,Biens!$A$5:$A$30,0)),0)),$C$15,0),IFERROR(IF(ISNUMBER(INDEX(Synthèse!$D$32:$H$32,MATCH(B124,Synthèse!$D$7:$H$7,0))),INDEX(Synthèse!$D$25:$H$25,MATCH(B124,Synthèse!$D$7:$H$7,0))+INDEX(Synthèse!$D$26:$H$26,MATCH(B124,Synthèse!$D$7:$H$7,0))-INDEX(Synthèse!$D$32:$H$32,MATCH(B124,Synthèse!$D$7:$H$7,0)),N(INDEX(Synthèse!$D$27:$H$27,MATCH(B124,Synthèse!$D$7:$H$7,0)))),0)) -> 4185 | D124: =IF(B124>YEAR($C$6),IF(C124>0,"Projection (C15)",""),IF(C124>0,"Comptable, puis Synthèse pour l'année en cours","")) -> Projection (C15)
... B128: 2032 | C128: =IF(B128>YEAR($C$6),IF(B128>=YEAR(IFERROR(INDEX(Biens!$O$5:$O$30,MATCH($C$5,Biens!$A$5:$A$30,0)),0)),$C$15,0),IFERROR(IF(ISNUMBER(INDEX(Synthèse!$D$32:$H$32,MATCH(B128,Synthèse!$D$7:$H$7,0))),INDEX(Synthèse!$D$25:$H$25,MATCH(B128,Synthèse!$D$7:$H$7,0))+INDEX(Synthèse!$D$26:$H$26,MATCH(B128,Synthèse!$D$7:$H$7,0))-INDEX(Synthèse!$D$32:$H$32,MATCH(B128,Synthèse!$D$7:$H$7,0)),N(INDEX(Synthèse!$D$27:$H$27,MATCH(B128,Synthèse!$D$7:$H$7,0)))),0)) -> 4185 | D128: =IF(B128>YEAR($C$6),IF(C128>0,"Projection (C15)",""),IF(C128>0,"Comptable, puis Synthèse pour l'année en cours","")) -> Projection (C15)
B129: Flux mensuels (calcul du gain et du TRI)
B130: Montants positifs = argent reçu ou économisé, négatifs = argent versé. Un scénario reprend les flux jusqu'à sa date de vente, puis la somme nette de la vente.
B131: Mois | C131: Date du flux | D131: Loyer évité | E131: Échéances de prêt | F131: Dépenses avant location | G131: Mouvements réels (Journal) | H131: Projection hors prêt | I131: Total du mois | J131: Scénario 1 | K131: Scénario 2 | L131: Scénario 3
B132: Apport à l'achat | C132: =$C$7 -> 43049 | I132: =-$C$8 -> -97968.99 | J132: =$I$132 -> -97968.99 | K132: =$I$132 -> -97968.99 | L132: =$I$132 -> -97968.99
B133: =DATE(YEAR($C$7),MONTH($C$7),1) -> 43040 | C133: =B133+14 -> 43054 | D133: =IF(OR($C$9="",B133>=$C$9),0,$C$10*(1+$C$11)^IF(B133<$C$7,0,DATEDIF($C$7,B133,"y"))*MAX(0,MIN(EDATE(B133,1),$C$9)-MAX(B133,$C$7))/(EDATE(B133,1)-B133)) -> 683.55 | E133: =-SUMIFS(Échéancier!$I$5:$I$300,Échéancier!$J$5:$J$300,$C$5,Échéancier!$C$5:$C$300,">="&B133,Échéancier!$C$5:$C$300,"<"&EDATE(B133,1)) -> 0 | F133: =-SUMIFS($D$68:$D$106,$E$68:$E$106,$C$5,$C$68:$C$106,">="&B133,$C$68:$C$106,"<"&EDATE(B133,1)) -> -59.38 | G133: =SUMIFS(Journal!$K$5:$K$1004,Journal!$C$5:$C$1004,$C$5,Journal!$A$5:$A$1004,">="&B133,Journal!$A$5:$A$1004,"<"&MIN(EDATE(B133,1),$C$6+1)) -> 0 | H133: =IF(B133<=$C$6,0,($C$12-$C$13/12)*(1+$C$14)^(YEAR(B133)-YEAR($C$6))) -> 0 | I133: =SUM(D133:H133) -> 624.17 | J133: =IF(C133<=$C$22,I133,0) -> 624.17 | K133: =IF(C133<=$D$22,I133,0) -> 624.17 | L133: =IF(C133<=$E$22,I133,0) -> 624.17
B134: =EDATE(B133,1) -> 43070 | C134: =B134+14 -> 43084 | D134: =IF(OR($C$9="",B134>=$C$9),0,$C$10*(1+$C$11)^IF(B134<$C$7,0,DATEDIF($C$7,B134,"y"))*MAX(0,MIN(EDATE(B134,1),$C$9)-MAX(B134,$C$7))/(EDATE(B134,1)-B134)) -> 976.5 | E134: =-SUMIFS(Échéancier!$I$5:$I$300,Échéancier!$J$5:$J$300,$C$5,Échéancier!$C$5:$C$300,">="&B134,Échéancier!$C$5:$C$300,"<"&EDATE(B134,1)) -> -823.57 | F134: =-SUMIFS($D$68:$D$106,$E$68:$E$106,$C$5,$C$68:$C$106,">="&B134,$C$68:$C$106,"<"&EDATE(B134,1)) -> -278.07 | G134: =SUMIFS(Journal!$K$5:$K$1004,Journal!$C$5:$C$1004,$C$5,Journal!$A$5:$A$1004,">="&B134,Journal!$A$5:$A$1004,"<"&MIN(EDATE(B134,1),$C$6+1)) -> 0 | H134: =IF(B134<=$C$6,0,($C$12-$C$13/12)*(1+$C$14)^(YEAR(B134)-YEAR($C$6))) -> 0 | I134: =SUM(D134:H134) -> -125.14 | J134: =IF(C134<=$C$22,I134,0) -> -125.14 | K134: =IF(C134<=$D$22,I134,0) -> -125.14 | L134: =IF(C134<=$E$22,I134,0) -> -125.14
B135: =EDATE(B134,1) -> 43101 | C135: =B135+14 -> 43115 | D135: =IF(OR($C$9="",B135>=$C$9),0,$C$10*(1+$C$11)^IF(B135<$C$7,0,DATEDIF($C$7,B135,"y"))*MAX(0,MIN(EDATE(B135,1),$C$9)-MAX(B135,$C$7))/(EDATE(B135,1)-B135)) -> 976.5 | E135: =-SUMIFS(Échéancier!$I$5:$I$300,Échéancier!$J$5:$J$300,$C$5,Échéancier!$C$5:$C$300,">="&B135,Échéancier!$C$5:$C$300,"<"&EDATE(B135,1)) -> -841.32 | F135: =-SUMIFS($D$68:$D$106,$E$68:$E$106,$C$5,$C$68:$C$106,">="&B135,$C$68:$C$106,"<"&EDATE(B135,1)) -> 0 | G135: =SUMIFS(Journal!$K$5:$K$1004,Journal!$C$5:$C$1004,$C$5,Journal!$A$5:$A$1004,">="&B135,Journal!$A$5:$A$1004,"<"&MIN(EDATE(B135,1),$C$6+1)) -> 0 | H135: =IF(B135<=$C$6,0,($C$12-$C$13/12)*(1+$C$14)^(YEAR(B135)-YEAR($C$6))) -> 0 | I135: =SUM(D135:H135) -> 135.18 | J135: =IF(C135<=$C$22,I135,0) -> 135.18 | K135: =IF(C135<=$D$22,I135,0) -> 135.18 | L135: =IF(C135<=$E$22,I135,0) -> 135.18
B136: =EDATE(B135,1) -> 43132 | C136: =B136+14 -> 43146 | D136: =IF(OR($C$9="",B136>=$C$9),0,$C$10*(1+$C$11)^IF(B136<$C$7,0,DATEDIF($C$7,B136,"y"))*MAX(0,MIN(EDATE(B136,1),$C$9)-MAX(B136,$C$7))/(EDATE(B136,1)-B136)) -> 976.5 | E136: =-SUMIFS(Échéancier!$I$5:$I$300,Échéancier!$J$5:$J$300,$C$5,Échéancier!$C$5:$C$300,">="&B136,Échéancier!$C$5:$C$300,"<"&EDATE(B136,1)) -> -841.32 | F136: =-SUMIFS($D$68:$D$106,$E$68:$E$106,$C$5,$C$68:$C$106,">="&B136,$C$68:$C$106,"<"&EDATE(B136,1)) -> 0 | G136: =SUMIFS(Journal!$K$5:$K$1004,Journal!$C$5:$C$1004,$C$5,Journal!$A$5:$A$1004,">="&B136,Journal!$A$5:$A$1004,"<"&MIN(EDATE(B136,1),$C$6+1)) -> 0 | H136: =IF(B136<=$C$6,0,($C$12-$C$13/12)*(1+$C$14)^(YEAR(B136)-YEAR($C$6))) -> 0 | I136: =SUM(D136:H136) -> 135.18 | J136: =IF(C136<=$C$22,I136,0) -> 135.18 | K136: =IF(C136<=$D$22,I136,0) -> 135.18 | L136: =IF(C136<=$E$22,I136,0) -> 135.18
B137: =EDATE(B136,1) -> 43160 | C137: =B137+14 -> 43174 | D137: =IF(OR($C$9="",B137>=$C$9),0,$C$10*(1+$C$11)^IF(B137<$C$7,0,DATEDIF($C$7,B137,"y"))*MAX(0,MIN(EDATE(B137,1),$C$9)-MAX(B137,$C$7))/(EDATE(B137,1)-B137)) -> 976.5 | E137: =-SUMIFS(Échéancier!$I$5:$I$300,Échéancier!$J$5:$J$300,$C$5,Échéancier!$C$5:$C$300,">="&B137,Échéancier!$C$5:$C$300,"<"&EDATE(B137,1)) -> -841.33 | F137: =-SUMIFS($D$68:$D$106,$E$68:$E$106,$C$5,$C$68:$C$106,">="&B137,$C$68:$C$106,"<"&EDATE(B137,1)) -> 0 | G137: =SUMIFS(Journal!$K$5:$K$1004,Journal!$C$5:$C$1004,$C$5,Journal!$A$5:$A$1004,">="&B137,Journal!$A$5:$A$1004,"<"&MIN(EDATE(B137,1),$C$6+1)) -> 0 | H137: =IF(B137<=$C$6,0,($C$12-$C$13/12)*(1+$C$14)^(YEAR(B137)-YEAR($C$6))) -> 0 | I137: =SUM(D137:H137) -> 135.17 | J137: =IF(C137<=$C$22,I137,0) -> 135.17 | K137: =IF(C137<=$D$22,I137,0) -> 135.17 | L137: =IF(C137<=$E$22,I137,0) -> 135.17
B138: =EDATE(B137,1) -> 43191 | C138: =B138+14 -> 43205 | D138: =IF(OR($C$9="",B138>=$C$9),0,$C$10*(1+$C$11)^IF(B138<$C$7,0,DATEDIF($C$7,B138,"y"))*MAX(0,MIN(EDATE(B138,1),$C$9)-MAX(B138,$C$7))/(EDATE(B138,1)-B138)) -> 976.5 | E138: =-SUMIFS(Échéancier!$I$5:$I$300,Échéancier!$J$5:$J$300,$C$5,Échéancier!$C$5:$C$300,">="&B138,Échéancier!$C$5:$C$300,"<"&EDATE(B138,1)) -> -841.33 | F138: =-SUMIFS($D$68:$D$106,$E$68:$E$106,$C$5,$C$68:$C$106,">="&B138,$C$68:$C$106,"<"&EDATE(B138,1)) -> 0 | G138: =SUMIFS(Journal!$K$5:$K$1004,Journal!$C$5:$C$1004,$C$5,Journal!$A$5:$A$1004,">="&B138,Journal!$A$5:$A$1004,"<"&MIN(EDATE(B138,1),$C$6+1)) -> 0 | H138: =IF(B138<=$C$6,0,($C$12-$C$13/12)*(1+$C$14)^(YEAR(B138)-YEAR($C$6))) -> 0 | I138: =SUM(D138:H138) -> 135.17 | J138: =IF(C138<=$C$22,I138,0) -> 135.17 | K138: =IF(C138<=$D$22,I138,0) -> 135.17 | L138: =IF(C138<=$E$22,I138,0) -> 135.17
B139: =EDATE(B138,1) -> 43221 | C139: =B139+14 -> 43235 | D139: =IF(OR($C$9="",B139>=$C$9),0,$C$10*(1+$C$11)^IF(B139<$C$7,0,DATEDIF($C$7,B139,"y"))*MAX(0,MIN(EDATE(B139,1),$C$9)-MAX(B139,$C$7))/(EDATE(B139,1)-B139)) -> 976.5 | E139: =-SUMIFS(Échéancier!$I$5:$I$300,Échéancier!$J$5:$J$300,$C$5,Échéancier!$C$5:$C$300,">="&B139,Échéancier!$C$5:$C$300,"<"&EDATE(B139,1)) -> -841.32 | F139: =-SUMIFS($D$68:$D$106,$E$68:$E$106,$C$5,$C$68:$C$106,">="&B139,$C$68:$C$106,"<"&EDATE(B139,1)) -> 0 | G139: =SUMIFS(Journal!$K$5:$K$1004,Journal!$C$5:$C$1004,$C$5,Journal!$A$5:$A$1004,">="&B139,Journal!$A$5:$A$1004,"<"&MIN(EDATE(B139,1),$C$6+1)) -> 0 | H139: =IF(B139<=$C$6,0,($C$12-$C$13/12)*(1+$C$14)^(YEAR(B139)-YEAR($C$6))) -> 0 | I139: =SUM(D139:H139) -> 135.18 | J139: =IF(C139<=$C$22,I139,0) -> 135.18 | K139: =IF(C139<=$D$22,I139,0) -> 135.18 | L139: =IF(C139<=$E$22,I139,0) -> 135.18
B140: =EDATE(B139,1) -> 43252 | C140: =B140+14 -> 43266 | D140: =IF(OR($C$9="",B140>=$C$9),0,$C$10*(1+$C$11)^IF(B140<$C$7,0,DATEDIF($C$7,B140,"y"))*MAX(0,MIN(EDATE(B140,1),$C$9)-MAX(B140,$C$7))/(EDATE(B140,1)-B140)) -> 976.5 | E140: =-SUMIFS(Échéancier!$I$5:$I$300,Échéancier!$J$5:$J$300,$C$5,Échéancier!$C$5:$C$300,">="&B140,Échéancier!$C$5:$C$300,"<"&EDATE(B140,1)) -> -841.32 | F140: =-SUMIFS($D$68:$D$106,$E$68:$E$106,$C$5,$C$68:$C$106,">="&B140,$C$68:$C$106,"<"&EDATE(B140,1)) -> 0 | G140: =SUMIFS(Journal!$K$5:$K$1004,Journal!$C$5:$C$1004,$C$5,Journal!$A$5:$A$1004,">="&B140,Journal!$A$5:$A$1004,"<"&MIN(EDATE(B140,1),$C$6+1)) -> 0 | H140: =IF(B140<=$C$6,0,($C$12-$C$13/12)*(1+$C$14)^(YEAR(B140)-YEAR($C$6))) -> 0 | I140: =SUM(D140:H140) -> 135.18 | J140: =IF(C140<=$C$22,I140,0) -> 135.18 | K140: =IF(C140<=$D$22,I140,0) -> 135.18 | L140: =IF(C140<=$E$22,I140,0) -> 135.18
B141: =EDATE(B140,1) -> 43282 | C141: =B141+14 -> 43296 | D141: =IF(OR($C$9="",B141>=$C$9),0,$C$10*(1+$C$11)^IF(B141<$C$7,0,DATEDIF($C$7,B141,"y"))*MAX(0,MIN(EDATE(B141,1),$C$9)-MAX(B141,$C$7))/(EDATE(B141,1)-B141)) -> 976.5 | E141: =-SUMIFS(Échéancier!$I$5:$I$300,Échéancier!$J$5:$J$300,$C$5,Échéancier!$C$5:$C$300,">="&B141,Échéancier!$C$5:$C$300,"<"&EDATE(B141,1)) -> -841.33 | F141: =-SUMIFS($D$68:$D$106,$E$68:$E$106,$C$5,$C$68:$C$106,">="&B141,$C$68:$C$106,"<"&EDATE(B141,1)) -> -1953 | G141: =SUMIFS(Journal!$K$5:$K$1004,Journal!$C$5:$C$1004,$C$5,Journal!$A$5:$A$1004,">="&B141,Journal!$A$5:$A$1004,"<"&MIN(EDATE(B141,1),$C$6+1)) -> 0 | H141: =IF(B141<=$C$6,0,($C$12-$C$13/12)*(1+$C$14)^(YEAR(B141)-YEAR($C$6))) -> 0 | I141: =SUM(D141:H141) -> -1817.83 | J141: =IF(C141<=$C$22,I141,0) -> -1817.83 | K141: =IF(C141<=$D$22,I141,0) -> -1817.83 | L141: =IF(C141<=$E$22,I141,0) -> -1817.83
B142: =EDATE(B141,1) -> 43313 | C142: =B142+14 -> 43327 | D142: =IF(OR($C$9="",B142>=$C$9),0,$C$10*(1+$C$11)^IF(B142<$C$7,0,DATEDIF($C$7,B142,"y"))*MAX(0,MIN(EDATE(B142,1),$C$9)-MAX(B142,$C$7))/(EDATE(B142,1)-B142)) -> 976.5 | E142: =-SUMIFS(Échéancier!$I$5:$I$300,Échéancier!$J$5:$J$300,$C$5,Échéancier!$C$5:$C$300,">="&B142,Échéancier!$C$5:$C$300,"<"&EDATE(B142,1)) -> -841.33 | F142: =-SUMIFS($D$68:$D$106,$E$68:$E$106,$C$5,$C$68:$C$106,">="&B142,$C$68:$C$106,"<"&EDATE(B142,1)) -> 0 | G142: =SUMIFS(Journal!$K$5:$K$1004,Journal!$C$5:$C$1004,$C$5,Journal!$A$5:$A$1004,">="&B142,Journal!$A$5:$A$1004,"<"&MIN(EDATE(B142,1),$C$6+1)) -> 0 | H142: =IF(B142<=$C$6,0,($C$12-$C$13/12)*(1+$C$14)^(YEAR(B142)-YEAR($C$6))) -> 0 | I142: =SUM(D142:H142) -> 135.17 | J142: =IF(C142<=$C$22,I142,0) -> 135.17 | K142: =IF(C142<=$D$22,I142,0) -> 135.17 | L142: =IF(C142<=$E$22,I142,0) -> 135.17
...

Sheet Échéances
A1: Échéances et rappels
A2: Calendrier récurrent de la gestion du bien. Mettez à jour la colonne « Prochaine date » après chaque échéance.
A4: Échéance | B4: Bien | C4: Périodicité | D4: Prochaine date | E4: Montant estimé | F4: Action à faire
A5: Taxe foncière | B5: APPART-01 | C5: Annuelle (15 octobre) | D5: 46310 | E5: 566.37 | F5: Paiement 2026 validé : vérifier le débit sur le relevé
A6: Appel de charges de copropriété | B6: APPART-01 | C6: Trimestrielle (1er janv., avr., juil., oct.) | D6: 46388 | E6: 604.5 | F6: Payer le syndic ; budget 2027 à 38 130 € + appel complémentaire travaux en 2027
A7: CFE | B7: APPART-01 | C7: Annuelle (15 décembre) | D7: 46371 | E7: 318.99 | F7: Vérifier l'avis 2026 dans l'espace professionnel impots.gouv.fr
A8: Régularisation des charges locataire | B8: APPART-01 | C8: Annuelle (après le décompte du syndic) | D8: 46356 | E8: 111.6 | F8: Décompte 2025 reçu le 22/10/2026 : vérifier que l'agence réclame ≈ 111 € au locataire
A9: Révision du loyer (IRL) | B9: APPART-01 | C9: Annuelle (mai) | D9: 46508 | F9: Vérifier l'indexation appliquée par l'agence
A10: Assurance PNO (ASSUREUR) | B10: APPART-01 | C10: Annuelle (1er avril) | D10: 46478 | E10: 114.39 | F10: Renouvellement tacite
A11: Liasse LMNP (2031 / 2033) | B11: Tous | C11: Annuelle (mai) | D11: 46508 | E11: 558 | F11: Transmettre au comptable le journal 2026 ; signaler le volet du Velux (395 €, 2024)
A12: Déclaration de revenus (2042-C-PRO) | B12: Tous | C12: Annuelle (mai-juin) | D12: 46527 | F12: Reporter le résultat LMNP fourni par le comptable
A13: Assemblée générale de copropriété | B13: APPART-01 | C13: Annuelle (octobre) | D13: 46675 | F13: Voter ou envoyer un pouvoir ; mettre à jour les travaux votés
A14: Fin du bail / restitution du dépôt de garantie | B14: APPART-01 | C14: Au départ du locataire | E14: 2064.6 | F14: Restituer sous 1 mois (2 mois en cas de retenues)
A15: Interdiction de louer les logements classés E (DPE) | B15: APPART-01 | C15: Réglementaire | D15: 48945 | F15: DPE de 2017 en classe E : vérifier le DPE de 2024

Sheet Contrôles
A1: Contrôles
A2: Vérifications automatiques de cohérence. Une ligne « À vérifier » signale une anomalie à corriger dans le Journal.
A4: Contrôle | B4: Valeur calculée | C4: Valeur attendue | D4: Écart | E4: Statut | F4: Explication
A5: Solde du compte agence (Journal) | B5: =SUMIFS(Journal!$L$5:$L$1004,Journal!$D$5:$D$1004,"Agence") -> 77.81 | C5: 77.81 | D5: =B5-C5 -> 0 | E5: =IF(ABS(D5)<0.01,"OK",IF(ROW()>=12,"Écart expliqué","À vérifier")) -> OK | F5: Solde créditeur du grand livre de l'agence au 25/10/2026
A6: Lignes avec une catégorie inconnue | B6: =COUNTIF(Journal!$H$5:$H$1004,"?") -> 0 | C6: 0 | D6: =B6-C6 -> 0 | E6: =IF(ABS(D6)<0.01,"OK",IF(ROW()>=12,"Écart expliqué","À vérifier")) -> OK | F6: Catégorie absente de l'onglet Catégories
A7: Lignes sans catégorie | B7: =COUNTIFS(Journal!$A$5:$A$1004,"<>",Journal!$E$5:$E$1004,"") -> 0 | C7: 0 | D7: =B7-C7 -> 0 | E7: =IF(ABS(D7)<0.01,"OK",IF(ROW()>=12,"Écart expliqué","À vérifier")) -> OK | F7: Toute ligne datée doit avoir une catégorie
A8: Lignes « À qualifier » | B8: =COUNTIF(Journal!$I$5:$I$1004,"À valider") -> 1 | C8: 0 | D8: =B8-C8 -> 1 | E8: =IF(ABS(D8)<0.01,"OK",IF(ROW()>=12,"Écart expliqué","À vérifier")) -> À vérifier | F8: Dépenses à faire valider par le comptable (Velux 395 € en 2024)
A9: Dotations aux amortissements 2024 (modèle) | B9: =Synthèse!D25 -> 5751.0489 | C9: 5751.05 | D9: =B9-C9 -> -0.0011386301 | E9: =IF(ABS(D9)<0.5,"OK",IF(ROW()>=12,"Écart expliqué","À vérifier")) -> OK | F9: Comptes annuels 2024 : 5 751,05 €
A10: Dotations aux amortissements 2025 (modèle) | B10: =Synthèse!E25 -> 9297.3367 | C10: 9297.34 | D10: =B10-C10 -> -0.0033342466 | E10: =IF(ABS(D10)<0.5,"OK",IF(ROW()>=12,"Écart expliqué","À vérifier")) -> OK | F10: Comptes annuels 2025 : 9 297,34 €
A11: Intérêts et assurance emprunteur 2025 | B11: =Synthèse!E21+Synthèse!E22 -> 1919.72 | C11: 1919.71 | D11: =B11-C11 -> 0.01 | E11: =IF(ABS(D11)<0.01,"OK",IF(ROW()>=12,"Écart expliqué","À vérifier")) -> OK | F11: Comptes annuels 2025 : 1 919,71 €
A12: Recettes 2024 | B12: =Synthèse!D13 -> 8366.76 | C12: 8316 | D12: =B12-C12 -> 50.76 | E12: =IF(ABS(D12)<0.01,"OK",IF(ROW()>=12,"Écart expliqué","À vérifier")) -> Écart expliqué | F12: Le comptable n'a pas retenu la TEOM refacturée (50,76 €)
A13: Recettes 2025 | B13: =Synthèse!E13 -> 13703.15 | C13: 14434.33 | D13: =B13-C13 -> -731.18 | E13: =IF(ABS(D13)<0.01,"OK",IF(ROW()>=12,"Écart expliqué","À vérifier")) -> Écart expliqué | F13: Écart identifié : provision 2024 reprise lors de la régularisation (623,70 €) et remise de loyer (107,46 €) comptées en plus par le comptable
A14: Charges hors amortissements 2024 | B14: =Synthèse!D23 -> 4726.86 | C14: 4399.83 | D14: =B14-C14 -> 327.03 | E14: =IF(ABS(D14)<0.01,"OK",IF(ROW()>=12,"Écart expliqué","À vérifier")) -> Écart expliqué | F14: Le comptable n'a retenu aucune charge de copropriété en 2024 (1 177 € payés) ; il a compté 669 € d'honoraires comptables (payés en 2025 dans le journal) ; intérêts : échéances de juin à décembre (1 176 €) contre 1 356 € retenus
A15: Charges hors amortissements 2025 | B15: =Synthèse!E23 -> 7020.35 | C15: 7126.6 | D15: =B15-C15 -> -106.25 | E15: =IF(ABS(D15)<0.01,"OK",IF(ROW()>=12,"Écart expliqué","À vérifier")) -> Écart expliqué | F15: Copropriété : 2 532,89 € retenus contre 2 426,77 € payés
A16: Vendre quand : scénario 1 identique à l'onglet Revente | B16: ='Vendre quand'!C32 -> 182343.65 | C16: =Revente!C23 -> 182343.65 | D16: =B16-C16 -> 0 | E16: =IF(OR('Vendre quand'!C22<>Revente!C6,'Vendre quand'!C23<>Revente!C7),"Non comparable",IF(ABS(D16)<1,"OK","À vérifier")) -> OK | F16: Somme nette perçue : les deux onglets doivent donner le même résultat quand le scénario 1 a la même date et le même prix que l'onglet Revente.

Sheet Listes
A1: Listes
A2: Valeurs proposées dans les menus déroulants. Vous pouvez en ajouter en bas de chaque colonne.
A4: Comptes | B4: Régimes fiscaux | C4: Types de location | D4: Sens | E4: Traitements fiscaux
A5: Banque | B5: LMNP réel | C5: Meublée | D5: Recette | E5: Imposable
A6: Agence | B6: LMNP micro-BIC | C6: Nue | D6: Dépense | E6: Déductible
A7: Autre compte | B7: LMP réel | C7: Saisonnière | D7: Transfert | E7: À amortir
B8: Location nue réel | D8: Neutre | E8: À valider
B9: Micro-foncier | E9: Non fiscal
B10: SCI à l'IS
